[
  {
    "idTeam": 456402,
    "actorName": "CESC MONTER PALAU",
    "actorId": 7485849,
    "actorShirtNumber": "18",
    "idMove": 178,
    "move": "Salt guanyat",
    "min": 10,
    "sec": 0,
    "period": 1,
    "score": "0-0",
    "teamAction": false,
    "timestamp": "20251004200010",
    "licenseId": 1157164,
    "eventUuid": "2ab74041-2f23-4592-afbf-651b8e9a6e7a"
  },
  {
    "idTeam": 456403,
    "actorName": "MARTÍ SÁNCHEZ LORENTE",
    "actorId": 7485865,
    "actorShirtNumber": "9",
    "idMove": 179,
    "move": "Salt perdut",
    "min": 10,
    "sec": 0,
    "period": 1,
    "score": "0-0",
    "teamAction": false,
    "timestamp": "20251004200010",
    "licenseId": 1172976,
    "eventUuid": "e5950c41-f706-44d5-8970-5db435d0389e"
  },
  {
    "idTeam": 456402,
    "actorName": "ARNAU CUBERES TORO",
    "actorId": 7485850,
    "actorShirtNumber": "12",
    "idMove": 93,
    "move": "Cistella de 2",
    "min": 10,
    "sec": 0,
    "period": 1,
    "score": "2-0",
    "teamAction": false,
    "timestamp": "20251004200014",
    "licenseId": 1157166,
    "eventUuid": "1e91f136-6128-4014-94e0-9a4f59c8ebcb"
  },
  {
    "idTeam": 456403,
    "actorName": "MARTÍ SÁNCHEZ LORENTE",
    "actorId": 7485865,
    "actorShirtNumber": "9",
    "idMove": 93,
    "move": "Cistella de 2",
    "min": 8,
    "sec": 0,
    "period": 1,
    "score": "2-2",
    "teamAction": false,
    "timestamp": "20251004200122",
    "licenseId": 1172976,
    "eventUuid": "dd053a85-0119-414a-9c34-d94fe0376ae4"
  },
  {
    "idTeam": 456402,
    "actorName": "ALEIX ELENO ESPINA",
    "actorId": 7485848,
    "actorShirtNumber": "14",
    "idMove": 161,
    "move": "Personal 2 tirs lliures, 1a falta",
    "min": 8,
    "sec": 0,
    "period": 1,
    "score": "2-2",
    "teamAction": false,
    "foulNumber": 1,
    "timestamp": "20251004200238",
    "licenseId": 1157163,
    "eventUuid": "7ab3c394-f83f-4a60-990a-4e1f9c1c685d"
  },
  {
    "idTeam": 456403,
    "actorName": "JOEL ARMINDO ROCHA CREUS",
    "actorId": 7485863,
    "actorShirtNumber": "3",
    "idMove": 96,
    "move": "Intent fallat de 1",
    "min": 8,
    "sec": 0,
    "period": 1,
    "score": "2-2",
    "teamAction": false,
    "timestamp": "20251004200248",
    "licenseId": 1172974,
    "eventUuid": "510d8469-697c-4704-91a4-aebb5608c9d6"
  },
  {
    "idTeam": 456403,
    "actorName": "JOEL ARMINDO ROCHA CREUS",
    "actorId": 7485863,
    "actorShirtNumber": "3",
    "idMove": 92,
    "move": "Cistella de 1",
    "min": 8,
    "sec": 0,
    "period": 1,
    "score": "2-3",
    "teamAction": false,
    "timestamp": "20251004200248",
    "licenseId": 1172974,
    "eventUuid": "97de4e7d-5877-4500-88bb-87b8bf4e704e"
  },
  {
    "idTeam": 456402,
    "actorName": "JOAN MARC PUJOL QUINGA",
    "actorId": 7485856,
    "actorShirtNumber": "88",
    "idMove": 93,
    "move": "Cistella de 2",
    "min": 7,
    "sec": 0,
    "period": 1,
    "score": "4-3",
    "teamAction": false,
    "timestamp": "20251004200316",
    "licenseId": 1192245,
    "eventUuid": "6db5e0d0-b3b6-4045-a5bd-30397aa691c5"
  },
  {
    "idTeam": 456403,
    "actorName": "DENNIS ANDREI AVRAM",
    "actorId": 7485861,
    "actorShirtNumber": "2",
    "idMove": 93,
    "move": "Cistella de 2",
    "min": 7,
    "sec": 0,
    "period": 1,
    "score": "4-5",
    "teamAction": false,
    "timestamp": "20251004200346",
    "licenseId": 1172970,
    "eventUuid": "c83eccfa-1b35-4578-b95a-412f97bf9b7b"
  },
  {
    "idTeam": 456403,
    "actorName": "JOEL ARMINDO ROCHA CREUS",
    "actorId": 7485863,
    "actorShirtNumber": "3",
    "idMove": 161,
    "move": "Personal 2 tirs lliures, 1a falta",
    "min": 7,
    "sec": 0,
    "period": 1,
    "score": "4-5",
    "teamAction": false,
    "foulNumber": 1,
    "timestamp": "20251004200353",
    "licenseId": 1172974,
    "eventUuid": "7766135b-cc22-4a57-ba3f-268d821abd5a"
  },
  {
    "idTeam": 456402,
    "actorName": "ALEIX ELENO ESPINA",
    "actorId": 7485848,
    "actorShirtNumber": "14",
    "idMove": 96,
    "move": "Intent fallat de 1",
    "min": 7,
    "sec": 0,
    "period": 1,
    "score": "4-5",
    "teamAction": false,
    "timestamp": "20251004200407",
    "licenseId": 1157163,
    "eventUuid": "433739b7-d6b7-40d5-b9e2-29349d1c132b"
  },
  {
    "idTeam": 456402,
    "actorName": "ALEIX ELENO ESPINA",
    "actorId": 7485848,
    "actorShirtNumber": "14",
    "idMove": 96,
    "move": "Intent fallat de 1",
    "min": 7,
    "sec": 0,
    "period": 1,
    "score": "4-5",
    "teamAction": false,
    "timestamp": "20251004200407",
    "licenseId": 1157163,
    "eventUuid": "07986343-5c60-423e-8987-b1d74f770584"
  },
  {
    "idTeam": 456403,
    "actorName": "MARTÍ SÁNCHEZ LORENTE",
    "actorId": 7485865,
    "actorShirtNumber": "9",
    "idMove": 159,
    "move": "Personal, 1a falta",
    "min": 6,
    "sec": 0,
    "period": 1,
    "score": "4-5",
    "teamAction": false,
    "foulNumber": 1,
    "timestamp": "20251004200511",
    "licenseId": 1172976,
    "eventUuid": "6f7ce7d4-b786-45ba-a365-81198e8e3b71"
  },
  {
    "idTeam": 456403,
    "actorName": "JOEL ARMINDO ROCHA CREUS",
    "actorId": 7485863,
    "actorShirtNumber": "3",
    "idMove": 115,
    "move": "Surt del camp",
    "min": 6,
    "sec": 0,
    "period": 1,
    "score": "4-5",
    "teamAction": false,
    "timestamp": "20251004200516",
    "licenseId": 1172974,
    "eventUuid": "00cb1713-c29d-4799-8df1-06f9b3d12681"
  },
  {
    "idTeam": 456403,
    "actorName": "MARTÍ SÁNCHEZ LORENTE",
    "actorId": 7485865,
    "actorShirtNumber": "9",
    "idMove": 115,
    "move": "Surt del camp",
    "min": 6,
    "sec": 0,
    "period": 1,
    "score": "4-5",
    "teamAction": false,
    "timestamp": "20251004200516",
    "licenseId": 1172976,
    "eventUuid": "d6cebae7-e54f-4b86-a8df-c4071b288ee5"
  },
  {
    "idTeam": 456403,
    "actorName": "MARIO GALLEGO TOLEDANO",
    "actorId": 7485862,
    "actorShirtNumber": "7",
    "idMove": 112,
    "move": "Entra al camp",
    "min": 6,
    "sec": 0,
    "period": 1,
    "score": "4-5",
    "teamAction": false,
    "timestamp": "20251004200516",
    "licenseId": 1172972,
    "eventUuid": "c41aa38d-c4ee-456a-aad2-47574110feb3"
  },
  {
    "idTeam": 456403,
    "actorName": "MARC VILARDELL GARCIA",
    "actorId": 7485860,
    "actorShirtNumber": "23",
    "idMove": 112,
    "move": "Entra al camp",
    "min": 6,
    "sec": 0,
    "period": 1,
    "score": "4-5",
    "teamAction": false,
    "timestamp": "20251004200516",
    "licenseId": 1172967,
    "eventUuid": "dccb1812-7a3f-4d8d-b190-626017348fdb"
  },
  {
    "idTeam": 456402,
    "actorName": "CESC MONTER PALAU",
    "actorId": 7485849,
    "actorShirtNumber": "18",
    "idMove": 94,
    "move": "Cistella de 3",
    "min": 6,
    "sec": 0,
    "period": 1,
    "score": "7-5",
    "teamAction": false,
    "timestamp": "20251004200555",
    "licenseId": 1157164,
    "eventUuid": "3c327def-252d-4efa-9ad8-89828ba66390"
  },
  {
    "idTeam": 456402,
    "actorName": "JOAN MARC PUJOL QUINGA",
    "actorId": 7485856,
    "actorShirtNumber": "88",
    "idMove": 93,
    "move": "Cistella de 2",
    "min": 4,
    "sec": 0,
    "period": 1,
    "score": "9-5",
    "teamAction": false,
    "timestamp": "20251004200659",
    "licenseId": 1192245,
    "eventUuid": "7a07d390-861a-4241-8dbb-4ed6ab196023"
  },
  {
    "idTeam": 456403,
    "actorName": "SANT QUIRZE BÀSQUET CLUB",
    "actorId": 0,
    "actorShirtNumber": "",
    "idMove": 113,
    "move": "Temps mort",
    "min": 4,
    "sec": 0,
    "period": 1,
    "score": "9-5",
    "teamAction": true,
    "timestamp": "20251004200721",
    "eventUuid": "75bf8bb2-bd80-4118-bd78-854668bae599"
  },
  {
    "idTeam": 456402,
    "actorName": "JOAN MARC PUJOL QUINGA",
    "actorId": 7485856,
    "actorShirtNumber": "88",
    "idMove": 115,
    "move": "Surt del camp",
    "min": 4,
    "sec": 0,
    "period": 1,
    "score": "9-5",
    "teamAction": false,
    "timestamp": "20251004200825",
    "licenseId": 1192245,
    "eventUuid": "a64017cf-ca3c-42f1-9546-81e01f577494"
  },
  {
    "idTeam": 456402,
    "actorName": "DILAN SALAZAR MAYORGA",
    "actorId": 7485853,
    "actorShirtNumber": "77",
    "idMove": 112,
    "move": "Entra al camp",
    "min": 4,
    "sec": 0,
    "period": 1,
    "score": "9-5",
    "teamAction": false,
    "timestamp": "20251004200825",
    "licenseId": 1158309,
    "eventUuid": "8488956b-b637-4cdd-b784-3acb7dbf1bdf"
  },
  {
    "idTeam": 456402,
    "actorName": "CESC MONTER PALAU",
    "actorId": 7485849,
    "actorShirtNumber": "18",
    "idMove": 93,
    "move": "Cistella de 2",
    "min": 4,
    "sec": 0,
    "period": 1,
    "score": "11-5",
    "teamAction": false,
    "timestamp": "20251004200934",
    "licenseId": 1157164,
    "eventUuid": "459eada7-3e66-4ddc-ac4a-70aa95d84451"
  },
  {
    "idTeam": 456402,
    "actorName": "DILAN SALAZAR MAYORGA",
    "actorId": 7485853,
    "actorShirtNumber": "77",
    "idMove": 159,
    "move": "Personal, 1a falta",
    "min": 4,
    "sec": 0,
    "period": 1,
    "score": "11-5",
    "teamAction": false,
    "foulNumber": 1,
    "timestamp": "20251004200951",
    "licenseId": 1158309,
    "eventUuid": "b5c303c9-a3ec-4dfe-977e-87791907891a"
  },
  {
    "idTeam": 456402,
    "actorName": "CESC MONTER PALAU",
    "actorId": 7485849,
    "actorShirtNumber": "18",
    "idMove": 115,
    "move": "Surt del camp",
    "min": 4,
    "sec": 0,
    "period": 1,
    "score": "11-5",
    "teamAction": false,
    "timestamp": "20251004201002",
    "licenseId": 1157164,
    "eventUuid": "69f6bfa9-4c2b-4d94-9092-663500e8ea08"
  },
  {
    "idTeam": 456402,
    "actorName": "MARC ELENO ESPINA",
    "actorId": 71051759600204400,
    "actorShirtNumber": "20",
    "idMove": 112,
    "move": "Entra al camp",
    "min": 4,
    "sec": 0,
    "period": 1,
    "score": "11-5",
    "teamAction": false,
    "timestamp": "20251004201002",
    "licenseId": 1154262,
    "eventUuid": "43e52b4e-d46d-40fb-be0e-54b7c3f945ae"
  },
  {
    "idTeam": 456403,
    "actorName": "VICTOR RODRIGUEZ SANCHEZ",
    "actorId": 7485868,
    "actorShirtNumber": "20",
    "idMove": 115,
    "move": "Surt del camp",
    "min": 4,
    "sec": 0,
    "period": 1,
    "score": "11-5",
    "teamAction": false,
    "timestamp": "20251004201002",
    "licenseId": 1174171,
    "eventUuid": "e5f0bab4-0da0-4584-85ce-d5746c6979af"
  },
  {
    "idTeam": 456403,
    "actorName": "MARTÍ SÁNCHEZ LORENTE",
    "actorId": 7485865,
    "actorShirtNumber": "9",
    "idMove": 112,
    "move": "Entra al camp",
    "min": 4,
    "sec": 0,
    "period": 1,
    "score": "11-5",
    "teamAction": false,
    "timestamp": "20251004201002",
    "licenseId": 1172976,
    "eventUuid": "aaed8b4c-747e-4258-9e07-635ce41778f1"
  },
  {
    "idTeam": 456403,
    "actorName": "MARIO GALLEGO TOLEDANO",
    "actorId": 7485862,
    "actorShirtNumber": "7",
    "idMove": 93,
    "move": "Cistella de 2",
    "min": 3,
    "sec": 0,
    "period": 1,
    "score": "11-7",
    "teamAction": false,
    "timestamp": "20251004201019",
    "licenseId": 1172972,
    "eventUuid": "c6f420a5-c09b-4ee4-aec0-b31e851daa3c"
  },
  {
    "idTeam": 456402,
    "actorName": "ARNAU CUBERES TORO",
    "actorId": 7485850,
    "actorShirtNumber": "12",
    "idMove": 93,
    "move": "Cistella de 2",
    "min": 3,
    "sec": 0,
    "period": 1,
    "score": "13-7",
    "teamAction": false,
    "timestamp": "20251004201056",
    "licenseId": 1157166,
    "eventUuid": "b41f4dd6-c91d-43c0-92c2-487262461b5c"
  },
  {
    "idTeam": 456403,
    "actorName": "ALEX VALERO GIL",
    "actorId": 7485859,
    "actorShirtNumber": "89",
    "idMove": 161,
    "move": "Personal 2 tirs lliures, 1a falta",
    "min": 2,
    "sec": 0,
    "period": 1,
    "score": "13-7",
    "teamAction": false,
    "foulNumber": 1,
    "timestamp": "20251004201128",
    "licenseId": 1166232,
    "eventUuid": "ec8b585a-27c9-4982-bcf1-b580b4a5992c"
  },
  {
    "idTeam": 456402,
    "actorName": "DILAN SALAZAR MAYORGA",
    "actorId": 7485853,
    "actorShirtNumber": "77",
    "idMove": 96,
    "move": "Intent fallat de 1",
    "min": 2,
    "sec": 0,
    "period": 1,
    "score": "13-7",
    "teamAction": false,
    "timestamp": "20251004201134",
    "licenseId": 1158309,
    "eventUuid": "60d2b5f1-5e83-40b8-9602-00e3f5939f00"
  },
  {
    "idTeam": 456402,
    "actorName": "DILAN SALAZAR MAYORGA",
    "actorId": 7485853,
    "actorShirtNumber": "77",
    "idMove": 96,
    "move": "Intent fallat de 1",
    "min": 2,
    "sec": 0,
    "period": 1,
    "score": "13-7",
    "teamAction": false,
    "timestamp": "20251004201133",
    "licenseId": 1158309,
    "eventUuid": "35bd20f7-2d37-4686-8b45-305d55353388"
  },
  {
    "idTeam": 456402,
    "actorName": "MARC ELENO ESPINA",
    "actorId": 71051759600204400,
    "actorShirtNumber": "20",
    "idMove": 93,
    "move": "Cistella de 2",
    "min": 2,
    "sec": 0,
    "period": 1,
    "score": "15-7",
    "teamAction": false,
    "timestamp": "20251004201233",
    "licenseId": 1154262,
    "eventUuid": "fa98c9de-e233-4207-92b1-0824f7b5743d"
  },
  {
    "idTeam": 456402,
    "actorName": "ARNAU CUBERES TORO",
    "actorId": 7485850,
    "actorShirtNumber": "12",
    "idMove": 93,
    "move": "Cistella de 2",
    "min": 2,
    "sec": 0,
    "period": 1,
    "score": "17-7",
    "teamAction": false,
    "timestamp": "20251004201255",
    "licenseId": 1157166,
    "eventUuid": "35a85a63-998a-4479-a587-5e02eed51dfc"
  },
  {
    "idTeam": 456403,
    "actorName": "ALEX VALERO GIL",
    "actorId": 7485859,
    "actorShirtNumber": "89",
    "idMove": 159,
    "move": "Personal, 2a falta",
    "min": 1,
    "sec": 0,
    "period": 1,
    "score": "17-7",
    "teamAction": false,
    "foulNumber": 2,
    "timestamp": "20251004201316",
    "licenseId": 1166232,
    "eventUuid": "2ffaa05f-40f6-4df5-8821-9a99e77061d0"
  },
  {
    "idTeam": 456402,
    "actorName": "MARC ELENO ESPINA",
    "actorId": 71051759600204400,
    "actorShirtNumber": "20",
    "idMove": 93,
    "move": "Cistella de 2",
    "min": 1,
    "sec": 0,
    "period": 1,
    "score": "19-7",
    "teamAction": false,
    "timestamp": "20251004201353",
    "licenseId": 1154262,
    "eventUuid": "2dcc733a-329a-40d3-8e97-ccb70227c878"
  },
  {
    "idTeam": 456403,
    "actorName": "ALEX VALERO GIL",
    "actorId": 7485859,
    "actorShirtNumber": "89",
    "idMove": 93,
    "move": "Cistella de 2",
    "min": 1,
    "sec": 0,
    "period": 1,
    "score": "19-9",
    "teamAction": false,
    "timestamp": "20251004201433",
    "licenseId": 1166232,
    "eventUuid": "9a01833b-7fea-4869-af17-e577ff43e690"
  },
  {
    "idTeam": 456402,
    "actorName": "MARC ELENO ESPINA",
    "actorId": 71051759600204400,
    "actorShirtNumber": "20",
    "idMove": 159,
    "move": "Personal, 1a falta",
    "min": 0,
    "sec": 0,
    "period": 1,
    "score": "19-9",
    "teamAction": false,
    "foulNumber": 1,
    "timestamp": "20251004201516",
    "licenseId": 1154262,
    "eventUuid": "2c8db479-a604-4a43-b6fc-7f9b6b138f41"
  },
  {
    "idTeam": 456403,
    "actorName": "ALEX VALERO GIL",
    "actorId": 7485859,
    "actorShirtNumber": "89",
    "idMove": 115,
    "move": "Surt del camp",
    "min": 0,
    "sec": 0,
    "period": 1,
    "score": "19-9",
    "teamAction": false,
    "timestamp": "20251004201531",
    "licenseId": 1166232,
    "eventUuid": "11acdcaf-8bb2-40bf-9d57-56695c5802c5"
  },
  {
    "idTeam": 456403,
    "actorName": "JOEL ARMINDO ROCHA CREUS",
    "actorId": 7485863,
    "actorShirtNumber": "3",
    "idMove": 112,
    "move": "Entra al camp",
    "min": 0,
    "sec": 0,
    "period": 1,
    "score": "19-9",
    "teamAction": false,
    "timestamp": "20251004201531",
    "licenseId": 1172974,
    "eventUuid": "f95af9c6-be4f-48c1-8169-bf5f94d24531"
  },
  {
    "idTeam": 0,
    "actorName": "",
    "actorId": 0,
    "actorShirtNumber": "",
    "idMove": 116,
    "move": "Final de període",
    "min": 0,
    "sec": 0,
    "period": 1,
    "score": "19-9",
    "teamAction": true,
    "timestamp": "20251004201552",
    "eventUuid": "6343ad88-ed24-466e-ab4b-17eb89c829bc"
  },
  {
    "idTeam": 456402,
    "actorName": "ALEIX ELENO ESPINA",
    "actorId": 7485848,
    "actorShirtNumber": "14",
    "idMove": 115,
    "move": "Surt del camp",
    "min": 10,
    "sec": 0,
    "period": 2,
    "score": "19-9",
    "teamAction": false,
    "timestamp": "20251004201646",
    "licenseId": 1157163,
    "eventUuid": "f8adaf56-ffda-4db6-95cc-d5c37e57ce63"
  },
  {
    "idTeam": 456402,
    "actorName": "CESC MONTER PALAU",
    "actorId": 7485849,
    "actorShirtNumber": "18",
    "idMove": 112,
    "move": "Entra al camp",
    "min": 10,
    "sec": 0,
    "period": 2,
    "score": "19-9",
    "teamAction": false,
    "timestamp": "20251004201646",
    "licenseId": 1157164,
    "eventUuid": "26754277-71ad-43f7-9578-279d4b33212c"
  },
  {
    "idTeam": 456403,
    "actorName": "DENNIS ANDREI AVRAM",
    "actorId": 7485861,
    "actorShirtNumber": "2",
    "idMove": 115,
    "move": "Surt del camp",
    "min": 10,
    "sec": 0,
    "period": 2,
    "score": "19-9",
    "teamAction": false,
    "timestamp": "20251004201646",
    "licenseId": 1172970,
    "eventUuid": "390409cd-8fb3-491d-ab12-197d24f79624"
  },
  {
    "idTeam": 456403,
    "actorName": "JOAN PUJANTE HOMS",
    "actorId": 7485869,
    "actorShirtNumber": "4",
    "idMove": 112,
    "move": "Entra al camp",
    "min": 10,
    "sec": 0,
    "period": 2,
    "score": "19-9",
    "teamAction": false,
    "timestamp": "20251004201646",
    "licenseId": 1177314,
    "eventUuid": "21531df7-4b55-43fe-9c09-9efe4d1b78c6"
  },
  {
    "idTeam": 456402,
    "actorName": "CESC MONTER PALAU",
    "actorId": 7485849,
    "actorShirtNumber": "18",
    "idMove": 93,
    "move": "Cistella de 2",
    "min": 9,
    "sec": 0,
    "period": 2,
    "score": "21-9",
    "teamAction": false,
    "timestamp": "20251004201802",
    "licenseId": 1157164,
    "eventUuid": "37bc00c1-0f3a-4073-be02-8c2e08864f07"
  },
  {
    "idTeam": 456402,
    "actorName": "MARC ELENO ESPINA",
    "actorId": 71051759600204400,
    "actorShirtNumber": "20",
    "idMove": 93,
    "move": "Cistella de 2",
    "min": 9,
    "sec": 0,
    "period": 2,
    "score": "23-9",
    "teamAction": false,
    "timestamp": "20251004201821",
    "licenseId": 1154262,
    "eventUuid": "ab7e9f62-e2bd-4867-ac09-34eaef73b8df"
  },
  {
    "idTeam": 456402,
    "actorName": "FRANCESC ALVAREZ HEREDIA",
    "actorId": 7485852,
    "actorShirtNumber": "23",
    "idMove": 159,
    "move": "Personal, 1a falta",
    "min": 9,
    "sec": 0,
    "period": 2,
    "score": "23-9",
    "teamAction": false,
    "foulNumber": 1,
    "timestamp": "20251004201829",
    "licenseId": 1157169,
    "eventUuid": "b92c1a81-6262-4b45-8de6-d5540c1d4480"
  },
  {
    "idTeam": 456402,
    "actorName": "DILAN SALAZAR MAYORGA",
    "actorId": 7485853,
    "actorShirtNumber": "77",
    "idMove": 115,
    "move": "Surt del camp",
    "min": 9,
    "sec": 0,
    "period": 2,
    "score": "23-9",
    "teamAction": false,
    "timestamp": "20251004201839",
    "licenseId": 1158309,
    "eventUuid": "7798dd16-0070-4668-9731-4487b943763b"
  },
  {
    "idTeam": 456402,
    "actorName": "JORDI CALLE VALENCIA",
    "actorId": 71051759600363140,
    "actorShirtNumber": "6",
    "idMove": 112,
    "move": "Entra al camp",
    "min": 9,
    "sec": 0,
    "period": 2,
    "score": "23-9",
    "teamAction": false,
    "timestamp": "20251004201839",
    "licenseId": 1154263,
    "eventUuid": "850c5a06-4774-47ba-85ec-b90340151126"
  },
  {
    "idTeam": 456402,
    "actorName": "MARC ELENO ESPINA",
    "actorId": 71051759600204400,
    "actorShirtNumber": "20",
    "idMove": 93,
    "move": "Cistella de 2",
    "min": 8,
    "sec": 0,
    "period": 2,
    "score": "25-9",
    "teamAction": false,
    "timestamp": "20251004201912",
    "licenseId": 1154262,
    "eventUuid": "68e5d248-1d50-4844-91e2-927ee1cf196e"
  },
  {
    "idTeam": 456403,
    "actorName": "MARTÍ SÁNCHEZ LORENTE",
    "actorId": 7485865,
    "actorShirtNumber": "9",
    "idMove": 93,
    "move": "Cistella de 2",
    "min": 8,
    "sec": 0,
    "period": 2,
    "score": "25-11",
    "teamAction": false,
    "timestamp": "20251004201930",
    "licenseId": 1172976,
    "eventUuid": "91bafe30-a90d-4f30-b037-f8c949a7cfbb"
  },
  {
    "idTeam": 456403,
    "actorName": "JOAN PUJANTE HOMS",
    "actorId": 7485869,
    "actorShirtNumber": "4",
    "idMove": 161,
    "move": "Personal 2 tirs lliures, 1a falta",
    "min": 7,
    "sec": 0,
    "period": 2,
    "score": "25-11",
    "teamAction": false,
    "foulNumber": 1,
    "timestamp": "20251004201940",
    "licenseId": 1177314,
    "eventUuid": "5aea958a-39ce-463d-80f4-0c7313f00a16"
  },
  {
    "idTeam": 456402,
    "actorName": "CESC MONTER PALAU",
    "actorId": 7485849,
    "actorShirtNumber": "18",
    "idMove": 115,
    "move": "Surt del camp",
    "min": 7,
    "sec": 0,
    "period": 2,
    "score": "25-11",
    "teamAction": false,
    "timestamp": "20251004201953",
    "licenseId": 1157164,
    "eventUuid": "b91821c9-9ede-4c4d-8057-c15c95a62a7a"
  },
  {
    "idTeam": 456402,
    "actorName": "MARC ELENO ESPINA",
    "actorId": 71051759600204400,
    "actorShirtNumber": "20",
    "idMove": 115,
    "move": "Surt del camp",
    "min": 7,
    "sec": 0,
    "period": 2,
    "score": "25-11",
    "teamAction": false,
    "timestamp": "20251004201953",
    "licenseId": 1154262,
    "eventUuid": "ab82c818-75bf-43cf-bbea-23f2cbcfa5cd"
  },
  {
    "idTeam": 456402,
    "actorName": "JOAN MARC PUJOL QUINGA",
    "actorId": 7485856,
    "actorShirtNumber": "88",
    "idMove": 112,
    "move": "Entra al camp",
    "min": 7,
    "sec": 0,
    "period": 2,
    "score": "25-11",
    "teamAction": false,
    "timestamp": "20251004201953",
    "licenseId": 1192245,
    "eventUuid": "743c5ab4-5491-46b0-a788-61c17b700098"
  },
  {
    "idTeam": 456402,
    "actorName": "ALEIX ELENO ESPINA",
    "actorId": 7485848,
    "actorShirtNumber": "14",
    "idMove": 112,
    "move": "Entra al camp",
    "min": 7,
    "sec": 0,
    "period": 2,
    "score": "25-11",
    "teamAction": false,
    "timestamp": "20251004201953",
    "licenseId": 1157163,
    "eventUuid": "384368fe-eac1-4d54-a0f4-8379ca58745e"
  },
  {
    "idTeam": 456403,
    "actorName": "MARC VILARDELL GARCIA",
    "actorId": 7485860,
    "actorShirtNumber": "23",
    "idMove": 115,
    "move": "Surt del camp",
    "min": 7,
    "sec": 0,
    "period": 2,
    "score": "25-11",
    "teamAction": false,
    "timestamp": "20251004201953",
    "licenseId": 1172967,
    "eventUuid": "64cc24a0-a3da-4747-a84f-f9d126d94504"
  },
  {
    "idTeam": 456403,
    "actorName": "ALEX VALERO GIL",
    "actorId": 7485859,
    "actorShirtNumber": "89",
    "idMove": 112,
    "move": "Entra al camp",
    "min": 7,
    "sec": 0,
    "period": 2,
    "score": "25-11",
    "teamAction": false,
    "timestamp": "20251004201953",
    "licenseId": 1166232,
    "eventUuid": "29677b74-46b0-4145-a78f-d176fcab64d4"
  },
  {
    "idTeam": 456402,
    "actorName": "JOAN MARC PUJOL QUINGA",
    "actorId": 7485856,
    "actorShirtNumber": "88",
    "idMove": 92,
    "move": "Cistella de 1",
    "min": 7,
    "sec": 0,
    "period": 2,
    "score": "26-11",
    "teamAction": false,
    "timestamp": "20251004202031",
    "licenseId": 1192245,
    "eventUuid": "7635b016-6760-40a7-9248-15cdd533ef99"
  },
  {
    "idTeam": 456402,
    "actorName": "JOAN MARC PUJOL QUINGA",
    "actorId": 7485856,
    "actorShirtNumber": "88",
    "idMove": 96,
    "move": "Intent fallat de 1",
    "min": 7,
    "sec": 0,
    "period": 2,
    "score": "26-11",
    "teamAction": false,
    "timestamp": "20251004202032",
    "licenseId": 1192245,
    "eventUuid": "7bb3055f-1585-4a85-ac10-468dddc3ff61"
  },
  {
    "idTeam": 456402,
    "actorName": "FRANCESC ALVAREZ HEREDIA",
    "actorId": 7485852,
    "actorShirtNumber": "23",
    "idMove": 93,
    "move": "Cistella de 2",
    "min": 7,
    "sec": 0,
    "period": 2,
    "score": "28-11",
    "teamAction": false,
    "timestamp": "20251004202135",
    "licenseId": 1157169,
    "eventUuid": "74b366e1-1f44-4351-8321-4543dc6ee3b5"
  },
  {
    "idTeam": 456403,
    "actorName": "JOAN PUJANTE HOMS",
    "actorId": 7485869,
    "actorShirtNumber": "4",
    "idMove": 93,
    "move": "Cistella de 2",
    "min": 7,
    "sec": 0,
    "period": 2,
    "score": "28-13",
    "teamAction": false,
    "timestamp": "20251004202146",
    "licenseId": 1177314,
    "eventUuid": "add3613b-17c7-45a2-8bb4-3b4df9861d56"
  },
  {
    "idTeam": 456403,
    "actorName": "ALEX VALERO GIL",
    "actorId": 7485859,
    "actorShirtNumber": "89",
    "idMove": 94,
    "move": "Cistella de 3",
    "min": 7,
    "sec": 0,
    "period": 2,
    "score": "28-16",
    "teamAction": false,
    "timestamp": "20251004202217",
    "licenseId": 1166232,
    "eventUuid": "8609eafa-185f-4f78-aff3-4a1537740e29"
  },
  {
    "idTeam": 456403,
    "actorName": "MARIO GALLEGO TOLEDANO",
    "actorId": 7485862,
    "actorShirtNumber": "7",
    "idMove": 93,
    "move": "Cistella de 2",
    "min": 6,
    "sec": 0,
    "period": 2,
    "score": "28-18",
    "teamAction": false,
    "timestamp": "20251004202256",
    "licenseId": 1172972,
    "eventUuid": "1473d3b8-f22b-4de2-8f5c-669dc6203ee8"
  },
  {
    "idTeam": 456403,
    "actorName": "MARIO GALLEGO TOLEDANO",
    "actorId": 7485862,
    "actorShirtNumber": "7",
    "idMove": 161,
    "move": "Personal 2 tirs lliures, 1a falta",
    "min": 6,
    "sec": 0,
    "period": 2,
    "score": "28-18",
    "teamAction": false,
    "foulNumber": 1,
    "timestamp": "20251004202312",
    "licenseId": 1172972,
    "eventUuid": "6423b6ab-27ad-44df-90b0-7f66ac65e94e"
  },
  {
    "idTeam": 456402,
    "actorName": "ARNAU CUBERES TORO",
    "actorId": 7485850,
    "actorShirtNumber": "12",
    "idMove": 115,
    "move": "Surt del camp",
    "min": 6,
    "sec": 0,
    "period": 2,
    "score": "28-18",
    "teamAction": false,
    "timestamp": "20251004202326",
    "licenseId": 1157166,
    "eventUuid": "bf2255b7-1cfb-4621-b919-67fb3e9efada"
  },
  {
    "idTeam": 456402,
    "actorName": "CESC MONTER PALAU",
    "actorId": 7485849,
    "actorShirtNumber": "18",
    "idMove": 112,
    "move": "Entra al camp",
    "min": 6,
    "sec": 0,
    "period": 2,
    "score": "28-18",
    "teamAction": false,
    "timestamp": "20251004202326",
    "licenseId": 1157164,
    "eventUuid": "1c7295aa-8d15-48d6-8ba5-eab962806322"
  },
  {
    "idTeam": 456403,
    "actorName": "MARTÍ SÁNCHEZ LORENTE",
    "actorId": 7485865,
    "actorShirtNumber": "9",
    "idMove": 115,
    "move": "Surt del camp",
    "min": 6,
    "sec": 0,
    "period": 2,
    "score": "28-18",
    "teamAction": false,
    "timestamp": "20251004202326",
    "licenseId": 1172976,
    "eventUuid": "6539d01f-ee77-43ce-a266-cdfce09bf47b"
  },
  {
    "idTeam": 456403,
    "actorName": "VICTOR RODRIGUEZ SANCHEZ",
    "actorId": 7485868,
    "actorShirtNumber": "20",
    "idMove": 112,
    "move": "Entra al camp",
    "min": 6,
    "sec": 0,
    "period": 2,
    "score": "28-18",
    "teamAction": false,
    "timestamp": "20251004202326",
    "licenseId": 1174171,
    "eventUuid": "e5be6ae9-fd50-493c-bb40-0fb9db8d85ee"
  },
  {
    "idTeam": 456402,
    "actorName": "FRANCESC ALVAREZ HEREDIA",
    "actorId": 7485852,
    "actorShirtNumber": "23",
    "idMove": 92,
    "move": "Cistella de 1",
    "min": 6,
    "sec": 0,
    "period": 2,
    "score": "29-18",
    "teamAction": false,
    "timestamp": "20251004202348",
    "licenseId": 1157169,
    "eventUuid": "43b3ead9-3d21-4950-93e9-ed537d6da9aa"
  },
  {
    "idTeam": 456402,
    "actorName": "FRANCESC ALVAREZ HEREDIA",
    "actorId": 7485852,
    "actorShirtNumber": "23",
    "idMove": 96,
    "move": "Intent fallat de 1",
    "min": 6,
    "sec": 0,
    "period": 2,
    "score": "29-18",
    "teamAction": false,
    "timestamp": "20251004202348",
    "licenseId": 1157169,
    "eventUuid": "521fc300-2a83-4c1e-922d-71bfc1655103"
  },
  {
    "idTeam": 456402,
    "actorName": "ALEIX ELENO ESPINA",
    "actorId": 7485848,
    "actorShirtNumber": "14",
    "idMove": 159,
    "move": "Personal, 2a falta",
    "min": 6,
    "sec": 0,
    "period": 2,
    "score": "29-18",
    "teamAction": false,
    "foulNumber": 2,
    "timestamp": "20251004202432",
    "licenseId": 1157163,
    "eventUuid": "762a4d73-4c6d-4b1b-a783-b9949534c960"
  },
  {
    "idTeam": 456402,
    "actorName": "JORDI CALLE VALENCIA",
    "actorId": 71051759600363140,
    "actorShirtNumber": "6",
    "idMove": 115,
    "move": "Surt del camp",
    "min": 6,
    "sec": 0,
    "period": 2,
    "score": "29-18",
    "teamAction": false,
    "timestamp": "20251004202438",
    "licenseId": 1154263,
    "eventUuid": "5596cad3-7a62-42c7-a425-b466c357208e"
  },
  {
    "idTeam": 456402,
    "actorName": "ARNAU CUBERES TORO",
    "actorId": 7485850,
    "actorShirtNumber": "12",
    "idMove": 112,
    "move": "Entra al camp",
    "min": 6,
    "sec": 0,
    "period": 2,
    "score": "29-18",
    "teamAction": false,
    "timestamp": "20251004202438",
    "licenseId": 1157166,
    "eventUuid": "f17998e5-5467-48a7-aa5b-a062454054f3"
  },
  {
    "idTeam": 456403,
    "actorName": "JOAN PUJANTE HOMS",
    "actorId": 7485869,
    "actorShirtNumber": "4",
    "idMove": 115,
    "move": "Surt del camp",
    "min": 5,
    "sec": 0,
    "period": 2,
    "score": "29-18",
    "teamAction": false,
    "timestamp": "20251004202636",
    "licenseId": 1177314,
    "eventUuid": "fba4f4c9-ade7-46ac-9af2-a57d7dd6027c"
  },
  {
    "idTeam": 456403,
    "actorName": "VICTOR RODRIGUEZ SANCHEZ",
    "actorId": 7485868,
    "actorShirtNumber": "20",
    "idMove": 115,
    "move": "Surt del camp",
    "min": 5,
    "sec": 0,
    "period": 2,
    "score": "29-18",
    "teamAction": false,
    "timestamp": "20251004202636",
    "licenseId": 1174171,
    "eventUuid": "7e001871-af19-41b0-bb8d-3104642a8d6a"
  },
  {
    "idTeam": 456403,
    "actorName": "MARTÍ SÁNCHEZ LORENTE",
    "actorId": 7485865,
    "actorShirtNumber": "9",
    "idMove": 112,
    "move": "Entra al camp",
    "min": 5,
    "sec": 0,
    "period": 2,
    "score": "29-18",
    "teamAction": false,
    "timestamp": "20251004202636",
    "licenseId": 1172976,
    "eventUuid": "dc7b689b-cf17-47e5-abca-45a6038c5590"
  },
  {
    "idTeam": 456403,
    "actorName": "MARC VILARDELL GARCIA",
    "actorId": 7485860,
    "actorShirtNumber": "23",
    "idMove": 112,
    "move": "Entra al camp",
    "min": 5,
    "sec": 0,
    "period": 2,
    "score": "29-18",
    "teamAction": false,
    "timestamp": "20251004202636",
    "licenseId": 1172967,
    "eventUuid": "25796af7-776c-4a20-bf32-f6fc93789f9e"
  },
  {
    "idTeam": 456403,
    "actorName": "MARTÍ SÁNCHEZ LORENTE",
    "actorId": 7485865,
    "actorShirtNumber": "9",
    "idMove": 93,
    "move": "Cistella de 2",
    "min": 5,
    "sec": 0,
    "period": 2,
    "score": "29-20",
    "teamAction": false,
    "timestamp": "20251004202703",
    "licenseId": 1172976,
    "eventUuid": "e3289ca4-4f27-4719-a508-cee3fcc938b6"
  },
  {
    "idTeam": 456402,
    "actorName": "CESC MONTER PALAU",
    "actorId": 7485849,
    "actorShirtNumber": "18",
    "idMove": 93,
    "move": "Cistella de 2",
    "min": 4,
    "sec": 0,
    "period": 2,
    "score": "31-20",
    "teamAction": false,
    "timestamp": "20251004202721",
    "licenseId": 1157164,
    "eventUuid": "0572d2d5-a187-4b54-880d-d888d7034a67"
  },
  {
    "idTeam": 456402,
    "actorName": "FRANCESC ALVAREZ HEREDIA",
    "actorId": 7485852,
    "actorShirtNumber": "23",
    "idMove": 161,
    "move": "Personal 2 tirs lliures, 2a falta",
    "min": 4,
    "sec": 0,
    "period": 2,
    "score": "31-20",
    "teamAction": false,
    "foulNumber": 2,
    "timestamp": "20251004202732",
    "licenseId": 1157169,
    "eventUuid": "fb249751-1b57-461d-b579-6bc6ca6bf679"
  },
  {
    "idTeam": 456403,
    "actorName": "ALEX VALERO GIL",
    "actorId": 7485859,
    "actorShirtNumber": "89",
    "idMove": 96,
    "move": "Intent fallat de 1",
    "min": 4,
    "sec": 0,
    "period": 2,
    "score": "31-20",
    "teamAction": false,
    "timestamp": "20251004202743",
    "licenseId": 1166232,
    "eventUuid": "e5f42374-2704-452f-8a4d-167922cba946"
  },
  {
    "idTeam": 456403,
    "actorName": "ALEX VALERO GIL",
    "actorId": 7485859,
    "actorShirtNumber": "89",
    "idMove": 96,
    "move": "Intent fallat de 1",
    "min": 4,
    "sec": 0,
    "period": 2,
    "score": "31-20",
    "teamAction": false,
    "timestamp": "20251004202743",
    "licenseId": 1166232,
    "eventUuid": "a87b9828-b000-4834-bd74-5ca0a98b530d"
  },
  {
    "idTeam": 456402,
    "actorName": "FRANCESC ALVAREZ HEREDIA",
    "actorId": 7485852,
    "actorShirtNumber": "23",
    "idMove": 159,
    "move": "Personal, 3a falta",
    "min": 4,
    "sec": 0,
    "period": 2,
    "score": "31-20",
    "teamAction": false,
    "foulNumber": 3,
    "timestamp": "20251004202914",
    "licenseId": 1157169,
    "eventUuid": "de870a9b-e4b1-44e2-bbcf-4d5d89d1a106"
  },
  {
    "idTeam": 456402,
    "actorName": "FRANCESC ALVAREZ HEREDIA",
    "actorId": 7485852,
    "actorShirtNumber": "23",
    "idMove": 115,
    "move": "Surt del camp",
    "min": 3,
    "sec": 0,
    "period": 2,
    "score": "31-20",
    "teamAction": false,
    "timestamp": "20251004202945",
    "licenseId": 1157169,
    "eventUuid": "13b4de3b-7186-4b85-9fd6-72f06d8ce570"
  },
  {
    "idTeam": 456402,
    "actorName": "MARC ELENO ESPINA",
    "actorId": 71051759600204400,
    "actorShirtNumber": "20",
    "idMove": 112,
    "move": "Entra al camp",
    "min": 3,
    "sec": 0,
    "period": 2,
    "score": "31-20",
    "teamAction": false,
    "timestamp": "20251004202945",
    "licenseId": 1154262,
    "eventUuid": "1de17f93-74f1-4e14-914a-17d4ff0092d7"
  },
  {
    "idTeam": 456403,
    "actorName": "MARTÍ SÁNCHEZ LORENTE",
    "actorId": 7485865,
    "actorShirtNumber": "9",
    "idMove": 93,
    "move": "Cistella de 2",
    "min": 3,
    "sec": 0,
    "period": 2,
    "score": "31-22",
    "teamAction": false,
    "timestamp": "20251004203017",
    "licenseId": 1172976,
    "eventUuid": "b28adfcd-4be5-4f5c-ae55-efbef2878e2f"
  },
  {
    "idTeam": 456402,
    "actorName": "JOAN MARC PUJOL QUINGA",
    "actorId": 7485856,
    "actorShirtNumber": "88",
    "idMove": 115,
    "move": "Surt del camp",
    "min": 2,
    "sec": 0,
    "period": 2,
    "score": "31-22",
    "teamAction": false,
    "timestamp": "20251004203047",
    "licenseId": 1192245,
    "eventUuid": "d4c18821-52f6-4a45-9a6d-d71ecc92ca27"
  },
  {
    "idTeam": 456402,
    "actorName": "DILAN SALAZAR MAYORGA",
    "actorId": 7485853,
    "actorShirtNumber": "77",
    "idMove": 112,
    "move": "Entra al camp",
    "min": 2,
    "sec": 0,
    "period": 2,
    "score": "31-22",
    "teamAction": false,
    "timestamp": "20251004203047",
    "licenseId": 1158309,
    "eventUuid": "dfab8872-1ebf-4277-8a73-ff7c8bee4535"
  },
  {
    "idTeam": 456403,
    "actorName": "MARTÍ SÁNCHEZ LORENTE",
    "actorId": 7485865,
    "actorShirtNumber": "9",
    "idMove": 115,
    "move": "Surt del camp",
    "min": 2,
    "sec": 0,
    "period": 2,
    "score": "31-22",
    "teamAction": false,
    "timestamp": "20251004203047",
    "licenseId": 1172976,
    "eventUuid": "55cbf912-f614-4d7f-8d2c-2423eb7ae221"
  },
  {
    "idTeam": 456403,
    "actorName": "JOAN PUJANTE HOMS",
    "actorId": 7485869,
    "actorShirtNumber": "4",
    "idMove": 112,
    "move": "Entra al camp",
    "min": 2,
    "sec": 0,
    "period": 2,
    "score": "31-22",
    "teamAction": false,
    "timestamp": "20251004203047",
    "licenseId": 1177314,
    "eventUuid": "146b5ec6-8449-4b0a-b2d1-8ac8863d0f3e"
  },
  {
    "idTeam": 456402,
    "actorName": "CESC MONTER PALAU",
    "actorId": 7485849,
    "actorShirtNumber": "18",
    "idMove": 161,
    "move": "Personal 2 tirs lliures, 1a falta",
    "min": 2,
    "sec": 0,
    "period": 2,
    "score": "31-22",
    "teamAction": false,
    "foulNumber": 1,
    "timestamp": "20251004203122",
    "licenseId": 1157164,
    "eventUuid": "c5df2cbb-3c53-499b-82c5-59d6e5c2d09a"
  },
  {
    "idTeam": 456403,
    "actorName": "ALEX VALERO GIL",
    "actorId": 7485859,
    "actorShirtNumber": "89",
    "idMove": 96,
    "move": "Intent fallat de 1",
    "min": 2,
    "sec": 0,
    "period": 2,
    "score": "31-22",
    "teamAction": false,
    "timestamp": "20251004203135",
    "licenseId": 1166232,
    "eventUuid": "eecee7cc-bf02-499e-9229-a29db51f26d1"
  },
  {
    "idTeam": 456403,
    "actorName": "ALEX VALERO GIL",
    "actorId": 7485859,
    "actorShirtNumber": "89",
    "idMove": 96,
    "move": "Intent fallat de 1",
    "min": 2,
    "sec": 0,
    "period": 2,
    "score": "31-22",
    "teamAction": false,
    "timestamp": "20251004203136",
    "licenseId": 1166232,
    "eventUuid": "a127fda4-247e-4a20-908d-87bfcabed931"
  },
  {
    "idTeam": 456402,
    "actorName": "ALEIX ELENO ESPINA",
    "actorId": 7485848,
    "actorShirtNumber": "14",
    "idMove": 161,
    "move": "Personal 2 tirs lliures, 3a falta",
    "min": 2,
    "sec": 0,
    "period": 2,
    "score": "31-22",
    "teamAction": false,
    "foulNumber": 3,
    "timestamp": "20251004203211",
    "licenseId": 1157163,
    "eventUuid": "71307141-dcd1-4fa7-baf2-91f74fd3eddf"
  },
  {
    "idTeam": 456402,
    "actorName": "ALEIX ELENO ESPINA",
    "actorId": 7485848,
    "actorShirtNumber": "14",
    "idMove": 115,
    "move": "Surt del camp",
    "min": 2,
    "sec": 0,
    "period": 2,
    "score": "31-22",
    "teamAction": false,
    "timestamp": "20251004203219",
    "licenseId": 1157163,
    "eventUuid": "c558363d-1e01-4198-96c9-51639c553a14"
  },
  {
    "idTeam": 456402,
    "actorName": "FRANCESC ALVAREZ HEREDIA",
    "actorId": 7485852,
    "actorShirtNumber": "23",
    "idMove": 112,
    "move": "Entra al camp",
    "min": 2,
    "sec": 0,
    "period": 2,
    "score": "31-22",
    "teamAction": false,
    "timestamp": "20251004203219",
    "licenseId": 1157169,
    "eventUuid": "ef428a20-a5bd-4bb6-90cf-60ced15f8505"
  },
  {
    "idTeam": 456403,
    "actorName": "MARC VILARDELL GARCIA",
    "actorId": 7485860,
    "actorShirtNumber": "23",
    "idMove": 96,
    "move": "Intent fallat de 1",
    "min": 2,
    "sec": 0,
    "period": 2,
    "score": "31-22",
    "teamAction": false,
    "timestamp": "20251004203230",
    "licenseId": 1172967,
    "eventUuid": "9091c55c-ab9d-4470-8ab5-99a64ce8ad08"
  },
  {
    "idTeam": 456403,
    "actorName": "MARC VILARDELL GARCIA",
    "actorId": 7485860,
    "actorShirtNumber": "23",
    "idMove": 96,
    "move": "Intent fallat de 1",
    "min": 2,
    "sec": 0,
    "period": 2,
    "score": "31-22",
    "teamAction": false,
    "timestamp": "20251004203230",
    "licenseId": 1172967,
    "eventUuid": "b273076d-a043-4d75-8230-4aace3b71467"
  },
  {
    "idTeam": 456403,
    "actorName": "MARC VILARDELL GARCIA",
    "actorId": 7485860,
    "actorShirtNumber": "23",
    "idMove": 93,
    "move": "Cistella de 2",
    "min": 1,
    "sec": 0,
    "period": 2,
    "score": "31-24",
    "teamAction": false,
    "timestamp": "20251004203249",
    "licenseId": 1172967,
    "eventUuid": "0039191f-fa24-437e-9a11-5b9eb92676d0"
  },
  {
    "idTeam": 456403,
    "actorName": "MARIO GALLEGO TOLEDANO",
    "actorId": 7485862,
    "actorShirtNumber": "7",
    "idMove": 161,
    "move": "Personal 2 tirs lliures, 2a falta",
    "min": 1,
    "sec": 0,
    "period": 2,
    "score": "31-24",
    "teamAction": false,
    "foulNumber": 2,
    "timestamp": "20251004203403",
    "licenseId": 1172972,
    "eventUuid": "2ffdd6c1-5ca3-489d-b5b7-1997b4f3857a"
  },
  {
    "idTeam": 456403,
    "actorName": "ALEX VALERO GIL",
    "actorId": 7485859,
    "actorShirtNumber": "89",
    "idMove": 115,
    "move": "Surt del camp",
    "min": 1,
    "sec": 0,
    "period": 2,
    "score": "31-24",
    "teamAction": false,
    "timestamp": "20251004203416",
    "licenseId": 1166232,
    "eventUuid": "b7458ac4-4bf4-4a87-9751-d8ca988ec7ea"
  },
  {
    "idTeam": 456403,
    "actorName": "MARTÍ SÁNCHEZ LORENTE",
    "actorId": 7485865,
    "actorShirtNumber": "9",
    "idMove": 112,
    "move": "Entra al camp",
    "min": 1,
    "sec": 0,
    "period": 2,
    "score": "31-24",
    "teamAction": false,
    "timestamp": "20251004203416",
    "licenseId": 1172976,
    "eventUuid": "46580fe8-44a7-424b-8dcf-ca8dab4adf16"
  },
  {
    "idTeam": 456402,
    "actorName": "CESC MONTER PALAU",
    "actorId": 7485849,
    "actorShirtNumber": "18",
    "idMove": 92,
    "move": "Cistella de 1",
    "min": 1,
    "sec": 0,
    "period": 2,
    "score": "32-24",
    "teamAction": false,
    "timestamp": "20251004203425",
    "licenseId": 1157164,
    "eventUuid": "794d17c1-d2d7-4f44-9e4c-2c9b4912b6f8"
  },
  {
    "idTeam": 456402,
    "actorName": "CESC MONTER PALAU",
    "actorId": 7485849,
    "actorShirtNumber": "18",
    "idMove": 96,
    "move": "Intent fallat de 1",
    "min": 1,
    "sec": 0,
    "period": 2,
    "score": "32-24",
    "teamAction": false,
    "timestamp": "20251004203425",
    "licenseId": 1157164,
    "eventUuid": "5463ea5d-ee53-4400-9e5b-91eb0687a341"
  },
  {
    "idTeam": 456403,
    "actorName": "MARC VILARDELL GARCIA",
    "actorId": 7485860,
    "actorShirtNumber": "23",
    "idMove": 162,
    "move": "Personal 3 tirs lliures, 1a falta",
    "min": 0,
    "sec": 0,
    "period": 2,
    "score": "32-24",
    "teamAction": false,
    "foulNumber": 1,
    "timestamp": "20251004203536",
    "licenseId": 1172967,
    "eventUuid": "6c60913e-72a2-405b-be7d-702ccf35f771"
  },
  {
    "idTeam": 456402,
    "actorName": "MARC ELENO ESPINA",
    "actorId": 71051759600204400,
    "actorShirtNumber": "20",
    "idMove": 96,
    "move": "Intent fallat de 1",
    "min": 0,
    "sec": 0,
    "period": 2,
    "score": "32-24",
    "teamAction": false,
    "timestamp": "20251004203548",
    "licenseId": 1154262,
    "eventUuid": "800cd074-9003-4462-a127-c644e2980a5c"
  },
  {
    "idTeam": 456402,
    "actorName": "MARC ELENO ESPINA",
    "actorId": 71051759600204400,
    "actorShirtNumber": "20",
    "idMove": 96,
    "move": "Intent fallat de 1",
    "min": 0,
    "sec": 0,
    "period": 2,
    "score": "32-24",
    "teamAction": false,
    "timestamp": "20251004203557",
    "licenseId": 1154262,
    "eventUuid": "216f9082-95e9-40b2-80ce-6bc1174f1d74"
  },
  {
    "idTeam": 456402,
    "actorName": "MARC ELENO ESPINA",
    "actorId": 71051759600204400,
    "actorShirtNumber": "20",
    "idMove": 96,
    "move": "Intent fallat de 1",
    "min": 0,
    "sec": 0,
    "period": 2,
    "score": "32-24",
    "teamAction": false,
    "timestamp": "20251004203608",
    "licenseId": 1154262,
    "eventUuid": "bd9eacce-fd53-4fd9-b414-5bf1b10b804b"
  },
  {
    "idTeam": 456403,
    "actorName": "MARC VILARDELL GARCIA",
    "actorId": 7485860,
    "actorShirtNumber": "23",
    "idMove": 93,
    "move": "Cistella de 2",
    "min": 0,
    "sec": 0,
    "period": 2,
    "score": "32-26",
    "teamAction": false,
    "timestamp": "20251004203620",
    "licenseId": 1172967,
    "eventUuid": "585ba4ca-0ef3-44e3-9995-df21c3c84b67"
  },
  {
    "idTeam": 0,
    "actorName": "",
    "actorId": 0,
    "actorShirtNumber": "",
    "idMove": 116,
    "move": "Final de període",
    "min": 0,
    "sec": 0,
    "period": 2,
    "score": "32-26",
    "teamAction": true,
    "timestamp": "20251004203645",
    "eventUuid": "3c112495-a424-4cf4-9862-cd30a958a6ac"
  },
  {
    "idTeam": 456402,
    "actorName": "DILAN SALAZAR MAYORGA",
    "actorId": 7485853,
    "actorShirtNumber": "77",
    "idMove": 115,
    "move": "Surt del camp",
    "min": 10,
    "sec": 0,
    "period": 3,
    "score": "32-26",
    "teamAction": false,
    "timestamp": "20251004204534",
    "licenseId": 1158309,
    "eventUuid": "1b67a6e6-1e59-47af-a1f9-87a929afbb12"
  },
  {
    "idTeam": 456402,
    "actorName": "MARC ELENO ESPINA",
    "actorId": 71051759600204400,
    "actorShirtNumber": "20",
    "idMove": 115,
    "move": "Surt del camp",
    "min": 10,
    "sec": 0,
    "period": 3,
    "score": "32-26",
    "teamAction": false,
    "timestamp": "20251004204534",
    "licenseId": 1154262,
    "eventUuid": "e0c07d7e-cc38-467b-8fe9-4a42ea4b9438"
  },
  {
    "idTeam": 456402,
    "actorName": "JOAN MARC PUJOL QUINGA",
    "actorId": 7485856,
    "actorShirtNumber": "88",
    "idMove": 112,
    "move": "Entra al camp",
    "min": 10,
    "sec": 0,
    "period": 3,
    "score": "32-26",
    "teamAction": false,
    "timestamp": "20251004204534",
    "licenseId": 1192245,
    "eventUuid": "419dc278-7a00-4012-9606-5052e76bfad7"
  },
  {
    "idTeam": 456402,
    "actorName": "ALEIX ELENO ESPINA",
    "actorId": 7485848,
    "actorShirtNumber": "14",
    "idMove": 112,
    "move": "Entra al camp",
    "min": 10,
    "sec": 0,
    "period": 3,
    "score": "32-26",
    "teamAction": false,
    "timestamp": "20251004204534",
    "licenseId": 1157163,
    "eventUuid": "8da03777-4231-4f22-8c23-717d4b9edd28"
  },
  {
    "idTeam": 456403,
    "actorName": "JOEL ARMINDO ROCHA CREUS",
    "actorId": 7485863,
    "actorShirtNumber": "3",
    "idMove": 115,
    "move": "Surt del camp",
    "min": 10,
    "sec": 0,
    "period": 3,
    "score": "32-26",
    "teamAction": false,
    "timestamp": "20251004204534",
    "licenseId": 1172974,
    "eventUuid": "bb354a78-87c8-41ca-880d-0093e7db55f4"
  },
  {
    "idTeam": 456403,
    "actorName": "ALEX VALERO GIL",
    "actorId": 7485859,
    "actorShirtNumber": "89",
    "idMove": 112,
    "move": "Entra al camp",
    "min": 10,
    "sec": 0,
    "period": 3,
    "score": "32-26",
    "teamAction": false,
    "timestamp": "20251004204534",
    "licenseId": 1166232,
    "eventUuid": "e1abcfe7-44c0-4aa8-868f-14a56ca64636"
  },
  {
    "idTeam": 456403,
    "actorName": "MARTÍ SÁNCHEZ LORENTE",
    "actorId": 7485865,
    "actorShirtNumber": "9",
    "idMove": 93,
    "move": "Cistella de 2",
    "min": 9,
    "sec": 0,
    "period": 3,
    "score": "32-28",
    "teamAction": false,
    "timestamp": "20251004204801",
    "licenseId": 1172976,
    "eventUuid": "ef3c835a-6463-476b-860a-4cd2b7496bdb"
  },
  {
    "idTeam": 456403,
    "actorName": "MARTÍ SÁNCHEZ LORENTE",
    "actorId": 7485865,
    "actorShirtNumber": "9",
    "idMove": 93,
    "move": "Cistella de 2",
    "min": 8,
    "sec": 0,
    "period": 3,
    "score": "32-30",
    "teamAction": false,
    "timestamp": "20251004204821",
    "licenseId": 1172976,
    "eventUuid": "2b30dd0f-4cad-4c0a-8171-982a06681ebb"
  },
  {
    "idTeam": 456402,
    "actorName": "CESC MONTER PALAU",
    "actorId": 7485849,
    "actorShirtNumber": "18",
    "idMove": 93,
    "move": "Cistella de 2",
    "min": 6,
    "sec": 0,
    "period": 3,
    "score": "34-30",
    "teamAction": false,
    "timestamp": "20251004205030",
    "licenseId": 1157164,
    "eventUuid": "a49ad037-f31d-45ec-8502-9b2ed9f67c1c"
  },
  {
    "idTeam": 456402,
    "actorName": "ARNAU CUBERES TORO",
    "actorId": 7485850,
    "actorShirtNumber": "12",
    "idMove": 93,
    "move": "Cistella de 2",
    "min": 6,
    "sec": 0,
    "period": 3,
    "score": "36-30",
    "teamAction": false,
    "timestamp": "20251004205057",
    "licenseId": 1157166,
    "eventUuid": "4126d5f4-81f0-4351-ade9-d3b71841dfb3"
  },
  {
    "idTeam": 456402,
    "actorName": "ALEIX ELENO ESPINA",
    "actorId": 7485848,
    "actorShirtNumber": "14",
    "idMove": 115,
    "move": "Surt del camp",
    "min": 5,
    "sec": 0,
    "period": 3,
    "score": "36-30",
    "teamAction": false,
    "timestamp": "20251004205211",
    "licenseId": 1157163,
    "eventUuid": "4d9cbd6f-00d4-472a-b37f-80e16a736f59"
  },
  {
    "idTeam": 456402,
    "actorName": "DILAN SALAZAR MAYORGA",
    "actorId": 7485853,
    "actorShirtNumber": "77",
    "idMove": 112,
    "move": "Entra al camp",
    "min": 5,
    "sec": 0,
    "period": 3,
    "score": "36-30",
    "teamAction": false,
    "timestamp": "20251004205211",
    "licenseId": 1158309,
    "eventUuid": "cf420a9c-f5e8-4467-898e-1983c9bbbd6c"
  },
  {
    "idTeam": 456403,
    "actorName": "MARIO GALLEGO TOLEDANO",
    "actorId": 7485862,
    "actorShirtNumber": "7",
    "idMove": 115,
    "move": "Surt del camp",
    "min": 5,
    "sec": 0,
    "period": 3,
    "score": "36-30",
    "teamAction": false,
    "timestamp": "20251004205211",
    "licenseId": 1172972,
    "eventUuid": "bb0da708-79cc-48b8-9636-d6dc7c9eb82a"
  },
  {
    "idTeam": 456403,
    "actorName": "JOEL ARMINDO ROCHA CREUS",
    "actorId": 7485863,
    "actorShirtNumber": "3",
    "idMove": 112,
    "move": "Entra al camp",
    "min": 5,
    "sec": 0,
    "period": 3,
    "score": "36-30",
    "teamAction": false,
    "timestamp": "20251004205211",
    "licenseId": 1172974,
    "eventUuid": "80598705-5b9b-4dd7-8eef-e852ea6d5058"
  },
  {
    "idTeam": 456402,
    "actorName": "JOAN MARC PUJOL QUINGA",
    "actorId": 7485856,
    "actorShirtNumber": "88",
    "idMove": 93,
    "move": "Cistella de 2",
    "min": 4,
    "sec": 0,
    "period": 3,
    "score": "38-30",
    "teamAction": false,
    "timestamp": "20251004205427",
    "licenseId": 1192245,
    "eventUuid": "1df68367-2738-45bd-81c7-69aae1a7d6b3"
  },
  {
    "idTeam": 456402,
    "actorName": "JOAN MARC PUJOL QUINGA",
    "actorId": 7485856,
    "actorShirtNumber": "88",
    "idMove": 115,
    "move": "Surt del camp",
    "min": 4,
    "sec": 0,
    "period": 3,
    "score": "38-30",
    "teamAction": false,
    "timestamp": "20251004205542",
    "licenseId": 1192245,
    "eventUuid": "00036372-ec5d-4182-adba-c8d802d9316b"
  },
  {
    "idTeam": 456402,
    "actorName": "MARC ELENO ESPINA",
    "actorId": 71051759600204400,
    "actorShirtNumber": "20",
    "idMove": 112,
    "move": "Entra al camp",
    "min": 4,
    "sec": 0,
    "period": 3,
    "score": "38-30",
    "teamAction": false,
    "timestamp": "20251004205542",
    "licenseId": 1154262,
    "eventUuid": "01779433-30f4-4f21-bc0b-a6049b810871"
  },
  {
    "idTeam": 456403,
    "actorName": "MARC VILARDELL GARCIA",
    "actorId": 7485860,
    "actorShirtNumber": "23",
    "idMove": 161,
    "move": "Personal 2 tirs lliures, 2a falta",
    "min": 3,
    "sec": 0,
    "period": 3,
    "score": "38-30",
    "teamAction": false,
    "foulNumber": 2,
    "timestamp": "20251004205557",
    "licenseId": 1172967,
    "eventUuid": "04ca7598-1133-40e2-bdae-d648299b627e"
  },
  {
    "idTeam": 456402,
    "actorName": "CESC MONTER PALAU",
    "actorId": 7485849,
    "actorShirtNumber": "18",
    "idMove": 96,
    "move": "Intent fallat de 1",
    "min": 3,
    "sec": 0,
    "period": 3,
    "score": "38-30",
    "teamAction": false,
    "timestamp": "20251004205614",
    "licenseId": 1157164,
    "eventUuid": "65881b9d-fe07-4ed4-86b1-a3476571c78a"
  },
  {
    "idTeam": 456402,
    "actorName": "CESC MONTER PALAU",
    "actorId": 7485849,
    "actorShirtNumber": "18",
    "idMove": 92,
    "move": "Cistella de 1",
    "min": 3,
    "sec": 0,
    "period": 3,
    "score": "39-30",
    "teamAction": false,
    "timestamp": "20251004205614",
    "licenseId": 1157164,
    "eventUuid": "7ebdcabe-13ad-4a7d-bb2d-794926429a7a"
  },
  {
    "idTeam": 456403,
    "actorName": "MARC VILARDELL GARCIA",
    "actorId": 7485860,
    "actorShirtNumber": "23",
    "idMove": 93,
    "move": "Cistella de 2",
    "min": 3,
    "sec": 0,
    "period": 3,
    "score": "39-32",
    "teamAction": false,
    "timestamp": "20251004205715",
    "licenseId": 1172967,
    "eventUuid": "c6c5b66b-982b-4e49-aaba-fb384ed84a15"
  },
  {
    "idTeam": 456403,
    "actorName": "MARTÍ SÁNCHEZ LORENTE",
    "actorId": 7485865,
    "actorShirtNumber": "9",
    "idMove": 94,
    "move": "Cistella de 3",
    "min": 3,
    "sec": 0,
    "period": 3,
    "score": "39-35",
    "teamAction": false,
    "timestamp": "20251004205727",
    "licenseId": 1172976,
    "eventUuid": "d6d1d661-79e2-4943-abbd-c40fff283fc0"
  },
  {
    "idTeam": 456403,
    "actorName": "JOAN PUJANTE HOMS",
    "actorId": 7485869,
    "actorShirtNumber": "4",
    "idMove": 115,
    "move": "Surt del camp",
    "min": 3,
    "sec": 0,
    "period": 3,
    "score": "39-35",
    "teamAction": false,
    "timestamp": "20251004205747",
    "licenseId": 1177314,
    "eventUuid": "e75003bd-6211-4daf-82ef-d5f65c10d6d3"
  },
  {
    "idTeam": 456403,
    "actorName": "MARIO GALLEGO TOLEDANO",
    "actorId": 7485862,
    "actorShirtNumber": "7",
    "idMove": 112,
    "move": "Entra al camp",
    "min": 3,
    "sec": 0,
    "period": 3,
    "score": "39-35",
    "teamAction": false,
    "timestamp": "20251004205747",
    "licenseId": 1172972,
    "eventUuid": "5d6f3279-32bc-4482-b7b9-e1d30596273e"
  },
  {
    "idTeam": 456402,
    "actorName": "FRANCESC ALVAREZ HEREDIA",
    "actorId": 7485852,
    "actorShirtNumber": "23",
    "idMove": 115,
    "move": "Surt del camp",
    "min": 3,
    "sec": 0,
    "period": 3,
    "score": "39-35",
    "teamAction": false,
    "timestamp": "20251004205812",
    "licenseId": 1157169,
    "eventUuid": "075f4c62-6967-4ef7-85f3-964d2526fd9a"
  },
  {
    "idTeam": 456402,
    "actorName": "JORDI CALLE VALENCIA",
    "actorId": 71051759600363140,
    "actorShirtNumber": "6",
    "idMove": 112,
    "move": "Entra al camp",
    "min": 3,
    "sec": 0,
    "period": 3,
    "score": "39-35",
    "teamAction": false,
    "timestamp": "20251004205812",
    "licenseId": 1154263,
    "eventUuid": "1f985cd0-3d07-4a22-85f5-0f21214defda"
  },
  {
    "idTeam": 456402,
    "actorName": "JORDI CALLE VALENCIA",
    "actorId": 71051759600363140,
    "actorShirtNumber": "6",
    "idMove": 115,
    "move": "Surt del camp",
    "min": 2,
    "sec": 0,
    "period": 3,
    "score": "39-35",
    "teamAction": false,
    "timestamp": "20251004205940",
    "licenseId": 1154263,
    "eventUuid": "5fe9cf59-6c22-446c-9793-ddeb0a06d7f7"
  },
  {
    "idTeam": 456402,
    "actorName": "ALEIX ELENO ESPINA",
    "actorId": 7485848,
    "actorShirtNumber": "14",
    "idMove": 112,
    "move": "Entra al camp",
    "min": 2,
    "sec": 0,
    "period": 3,
    "score": "39-35",
    "teamAction": false,
    "timestamp": "20251004205940",
    "licenseId": 1157163,
    "eventUuid": "cfb3284d-23a6-4e37-964b-3888585ddde4"
  },
  {
    "idTeam": 456402,
    "actorName": "MARC ELENO ESPINA",
    "actorId": 71051759600204400,
    "actorShirtNumber": "20",
    "idMove": 93,
    "move": "Cistella de 2",
    "min": 1,
    "sec": 0,
    "period": 3,
    "score": "41-35",
    "teamAction": false,
    "timestamp": "20251004210040",
    "licenseId": 1154262,
    "eventUuid": "566e2e71-47a0-4a91-8467-634efe7775c8"
  },
  {
    "idTeam": 456402,
    "actorName": "ARNAU CUBERES TORO",
    "actorId": 7485850,
    "actorShirtNumber": "12",
    "idMove": 159,
    "move": "Personal, 1a falta",
    "min": 1,
    "sec": 0,
    "period": 3,
    "score": "41-35",
    "teamAction": false,
    "foulNumber": 1,
    "timestamp": "20251004210059",
    "licenseId": 1157166,
    "eventUuid": "d67b5954-1833-4563-95e2-7dab292981eb"
  },
  {
    "idTeam": 456403,
    "actorName": "MARTÍ SÁNCHEZ LORENTE",
    "actorId": 7485865,
    "actorShirtNumber": "9",
    "idMove": 93,
    "move": "Cistella de 2",
    "min": 1,
    "sec": 0,
    "period": 3,
    "score": "41-37",
    "teamAction": false,
    "timestamp": "20251004210111",
    "licenseId": 1172976,
    "eventUuid": "03549421-8c07-4e96-a284-af7b1b8e0d51"
  },
  {
    "idTeam": 0,
    "actorName": "",
    "actorId": 0,
    "actorShirtNumber": "",
    "idMove": 116,
    "move": "Final de període",
    "min": 0,
    "sec": 0,
    "period": 3,
    "score": "41-37",
    "teamAction": true,
    "timestamp": "20251004210235",
    "eventUuid": "f43a18c4-6e8f-4cf5-ae2c-16bef15c460f"
  },
  {
    "idTeam": 456402,
    "actorName": "MARC ELENO ESPINA",
    "actorId": 71051759600204400,
    "actorShirtNumber": "20",
    "idMove": 115,
    "move": "Surt del camp",
    "min": 10,
    "sec": 0,
    "period": 4,
    "score": "41-37",
    "teamAction": false,
    "timestamp": "20251004210421",
    "licenseId": 1154262,
    "eventUuid": "c05dbf30-7c7c-4db3-b573-e7032787bedb"
  },
  {
    "idTeam": 456402,
    "actorName": "ALEIX ELENO ESPINA",
    "actorId": 7485848,
    "actorShirtNumber": "14",
    "idMove": 115,
    "move": "Surt del camp",
    "min": 10,
    "sec": 0,
    "period": 4,
    "score": "41-37",
    "teamAction": false,
    "timestamp": "20251004210421",
    "licenseId": 1157163,
    "eventUuid": "0f12a66f-106f-4e21-bafe-78dbe1f6e3b7"
  },
  {
    "idTeam": 456402,
    "actorName": "JOAN MARC PUJOL QUINGA",
    "actorId": 7485856,
    "actorShirtNumber": "88",
    "idMove": 112,
    "move": "Entra al camp",
    "min": 10,
    "sec": 0,
    "period": 4,
    "score": "41-37",
    "teamAction": false,
    "timestamp": "20251004210421",
    "licenseId": 1192245,
    "eventUuid": "8d4a1a8d-178c-4b76-80bd-81d090979746"
  },
  {
    "idTeam": 456402,
    "actorName": "FRANCESC ALVAREZ HEREDIA",
    "actorId": 7485852,
    "actorShirtNumber": "23",
    "idMove": 112,
    "move": "Entra al camp",
    "min": 10,
    "sec": 0,
    "period": 4,
    "score": "41-37",
    "teamAction": false,
    "timestamp": "20251004210421",
    "licenseId": 1157169,
    "eventUuid": "643e5ff7-9af3-4847-a8cf-8d26d16bdb39"
  },
  {
    "idTeam": 456403,
    "actorName": "MARC VILARDELL GARCIA",
    "actorId": 7485860,
    "actorShirtNumber": "23",
    "idMove": 115,
    "move": "Surt del camp",
    "min": 10,
    "sec": 0,
    "period": 4,
    "score": "41-37",
    "teamAction": false,
    "timestamp": "20251004210421",
    "licenseId": 1172967,
    "eventUuid": "27aba6e6-8213-4559-a728-cffc53a25efa"
  },
  {
    "idTeam": 456403,
    "actorName": "JOAN PUJANTE HOMS",
    "actorId": 7485869,
    "actorShirtNumber": "4",
    "idMove": 112,
    "move": "Entra al camp",
    "min": 10,
    "sec": 0,
    "period": 4,
    "score": "41-37",
    "teamAction": false,
    "timestamp": "20251004210421",
    "licenseId": 1177314,
    "eventUuid": "dd5f6664-a0d7-4953-acf1-22766c3af7fb"
  },
  {
    "idTeam": 456402,
    "actorName": "DILAN SALAZAR MAYORGA",
    "actorId": 7485853,
    "actorShirtNumber": "77",
    "idMove": 93,
    "move": "Cistella de 2",
    "min": 9,
    "sec": 0,
    "period": 4,
    "score": "43-37",
    "teamAction": false,
    "timestamp": "20251004210500",
    "licenseId": 1158309,
    "eventUuid": "c5c27d58-bafb-4173-8787-c690fe2ad5ed"
  },
  {
    "idTeam": 456403,
    "actorName": "JOEL ARMINDO ROCHA CREUS",
    "actorId": 7485863,
    "actorShirtNumber": "3",
    "idMove": 93,
    "move": "Cistella de 2",
    "min": 9,
    "sec": 0,
    "period": 4,
    "score": "43-39",
    "teamAction": false,
    "timestamp": "20251004210511",
    "licenseId": 1172974,
    "eventUuid": "11e05991-c153-409f-b8f9-8ca60334e19e"
  },
  {
    "idTeam": 456403,
    "actorName": "JOEL ARMINDO ROCHA CREUS",
    "actorId": 7485863,
    "actorShirtNumber": "3",
    "idMove": 161,
    "move": "Personal 2 tirs lliures, 2a falta",
    "min": 9,
    "sec": 0,
    "period": 4,
    "score": "43-39",
    "teamAction": false,
    "foulNumber": 2,
    "timestamp": "20251004210603",
    "licenseId": 1172974,
    "eventUuid": "ed31e57e-ebef-4fbd-8b50-cfdab196f1e3"
  },
  {
    "idTeam": 456402,
    "actorName": "DILAN SALAZAR MAYORGA",
    "actorId": 7485853,
    "actorShirtNumber": "77",
    "idMove": 115,
    "move": "Surt del camp",
    "min": 9,
    "sec": 0,
    "period": 4,
    "score": "43-39",
    "teamAction": false,
    "timestamp": "20251004210618",
    "licenseId": 1158309,
    "eventUuid": "e61144b3-5797-4c8d-a34f-3a1527192aec"
  },
  {
    "idTeam": 456402,
    "actorName": "ALEIX ELENO ESPINA",
    "actorId": 7485848,
    "actorShirtNumber": "14",
    "idMove": 112,
    "move": "Entra al camp",
    "min": 9,
    "sec": 0,
    "period": 4,
    "score": "43-39",
    "teamAction": false,
    "timestamp": "20251004210618",
    "licenseId": 1157163,
    "eventUuid": "500ca763-3bc2-4ff1-bc29-88a27bdbb72c"
  },
  {
    "idTeam": 456402,
    "actorName": "CESC MONTER PALAU",
    "actorId": 7485849,
    "actorShirtNumber": "18",
    "idMove": 96,
    "move": "Intent fallat de 1",
    "min": 8,
    "sec": 0,
    "period": 4,
    "score": "43-39",
    "teamAction": false,
    "timestamp": "20251004210652",
    "licenseId": 1157164,
    "eventUuid": "61959da5-7b84-4d83-9684-51b7ff37ccfe"
  },
  {
    "idTeam": 456402,
    "actorName": "CESC MONTER PALAU",
    "actorId": 7485849,
    "actorShirtNumber": "18",
    "idMove": 92,
    "move": "Cistella de 1",
    "min": 8,
    "sec": 0,
    "period": 4,
    "score": "44-39",
    "teamAction": false,
    "timestamp": "20251004210653",
    "licenseId": 1157164,
    "eventUuid": "365d0a2c-265a-40ee-83ea-d21ca45ac089"
  },
  {
    "idTeam": 456403,
    "actorName": "JOEL ARMINDO ROCHA CREUS",
    "actorId": 7485863,
    "actorShirtNumber": "3",
    "idMove": 166,
    "move": "Antiesportiva 2 tirs lliures, 3a falta",
    "min": 8,
    "sec": 0,
    "period": 4,
    "score": "44-39",
    "teamAction": false,
    "foulNumber": 3,
    "timestamp": "20251004210809",
    "licenseId": 1172974,
    "eventUuid": "59c3ff15-b1bd-45eb-a42e-680d5eeaa58b"
  },
  {
    "idTeam": 456402,
    "actorName": "CESC MONTER PALAU",
    "actorId": 7485849,
    "actorShirtNumber": "18",
    "idMove": 96,
    "move": "Intent fallat de 1",
    "min": 8,
    "sec": 0,
    "period": 4,
    "score": "44-39",
    "teamAction": false,
    "timestamp": "20251004210818",
    "licenseId": 1157164,
    "eventUuid": "a7a281d9-9fee-4e10-ba1f-b89de8d24f31"
  },
  {
    "idTeam": 456402,
    "actorName": "CESC MONTER PALAU",
    "actorId": 7485849,
    "actorShirtNumber": "18",
    "idMove": 92,
    "move": "Cistella de 1",
    "min": 8,
    "sec": 0,
    "period": 4,
    "score": "45-39",
    "teamAction": false,
    "timestamp": "20251004210818",
    "licenseId": 1157164,
    "eventUuid": "f0f2b9d5-4025-46f7-8bdc-1aea9021e259"
  },
  {
    "idTeam": 456402,
    "actorName": "FRANCESC ALVAREZ HEREDIA",
    "actorId": 7485852,
    "actorShirtNumber": "23",
    "idMove": 93,
    "move": "Cistella de 2",
    "min": 8,
    "sec": 0,
    "period": 4,
    "score": "47-39",
    "teamAction": false,
    "timestamp": "20251004210900",
    "licenseId": 1157169,
    "eventUuid": "ab82245b-8566-4609-9682-acc1571cfd2c"
  },
  {
    "idTeam": 456402,
    "actorName": "JOAN MARC PUJOL QUINGA",
    "actorId": 7485856,
    "actorShirtNumber": "88",
    "idMove": 93,
    "move": "Cistella de 2",
    "min": 8,
    "sec": 0,
    "period": 4,
    "score": "49-39",
    "teamAction": false,
    "timestamp": "20251004210929",
    "licenseId": 1192245,
    "eventUuid": "37a830b2-43ee-4ab7-8f56-bbc02e8ed29b"
  },
  {
    "idTeam": 456402,
    "actorName": "ALEIX ELENO ESPINA",
    "actorId": 7485848,
    "actorShirtNumber": "14",
    "idMove": 93,
    "move": "Cistella de 2",
    "min": 7,
    "sec": 0,
    "period": 4,
    "score": "51-39",
    "teamAction": false,
    "timestamp": "20251004210951",
    "licenseId": 1157163,
    "eventUuid": "f33707bf-1132-48ac-8e44-0561460638ee"
  },
  {
    "idTeam": 456402,
    "actorName": "ALEIX ELENO ESPINA",
    "actorId": 7485848,
    "actorShirtNumber": "14",
    "idMove": 93,
    "move": "Cistella de 2",
    "min": 7,
    "sec": 0,
    "period": 4,
    "score": "53-39",
    "teamAction": false,
    "timestamp": "20251004211015",
    "licenseId": 1157163,
    "eventUuid": "79e07c67-820f-49ad-a838-2b8ed5613a4f"
  },
  {
    "idTeam": 456403,
    "actorName": "SANT QUIRZE BÀSQUET CLUB",
    "actorId": 0,
    "actorShirtNumber": "",
    "idMove": 113,
    "move": "Temps mort",
    "min": 7,
    "sec": 0,
    "period": 4,
    "score": "53-39",
    "teamAction": true,
    "timestamp": "20251004211112",
    "eventUuid": "7ed53a18-eba4-474e-9315-8b620841fd40"
  },
  {
    "idTeam": 456402,
    "actorName": "CESC MONTER PALAU",
    "actorId": 7485849,
    "actorShirtNumber": "18",
    "idMove": 159,
    "move": "Personal, 2a falta",
    "min": 7,
    "sec": 0,
    "period": 4,
    "score": "53-39",
    "teamAction": false,
    "foulNumber": 2,
    "timestamp": "20251004211131",
    "licenseId": 1157164,
    "eventUuid": "d9c7b637-7b78-4369-85ce-194034eabc90"
  },
  {
    "idTeam": 456402,
    "actorName": "ARNAU CUBERES TORO",
    "actorId": 7485850,
    "actorShirtNumber": "12",
    "idMove": 159,
    "move": "Personal, 2a falta",
    "min": 7,
    "sec": 0,
    "period": 4,
    "score": "53-39",
    "teamAction": false,
    "foulNumber": 2,
    "timestamp": "20251004211210",
    "licenseId": 1157166,
    "eventUuid": "750f1d4e-217c-490d-b86e-46181c1b83dd"
  },
  {
    "idTeam": 456403,
    "actorName": "MARTÍ SÁNCHEZ LORENTE",
    "actorId": 7485865,
    "actorShirtNumber": "9",
    "idMove": 93,
    "move": "Cistella de 2",
    "min": 7,
    "sec": 0,
    "period": 4,
    "score": "53-41",
    "teamAction": false,
    "timestamp": "20251004211222",
    "licenseId": 1172976,
    "eventUuid": "14c4a70d-b743-4d44-8946-e791c24448fd"
  },
  {
    "idTeam": 456402,
    "actorName": "JOAN MARC PUJOL QUINGA",
    "actorId": 7485856,
    "actorShirtNumber": "88",
    "idMove": 115,
    "move": "Surt del camp",
    "min": 7,
    "sec": 0,
    "period": 4,
    "score": "53-41",
    "teamAction": false,
    "timestamp": "20251004211310",
    "licenseId": 1192245,
    "eventUuid": "335d5e1f-3681-4bda-b419-e7e25e626122"
  },
  {
    "idTeam": 456402,
    "actorName": "MARC ELENO ESPINA",
    "actorId": 71051759600204400,
    "actorShirtNumber": "20",
    "idMove": 112,
    "move": "Entra al camp",
    "min": 7,
    "sec": 0,
    "period": 4,
    "score": "53-41",
    "teamAction": false,
    "timestamp": "20251004211310",
    "licenseId": 1154262,
    "eventUuid": "d1f72821-8e3d-4afc-b69a-8f0b68f6ac0f"
  },
  {
    "idTeam": 456402,
    "actorName": "ARNAU CUBERES TORO",
    "actorId": 7485850,
    "actorShirtNumber": "12",
    "idMove": 93,
    "move": "Cistella de 2",
    "min": 5,
    "sec": 0,
    "period": 4,
    "score": "55-41",
    "teamAction": false,
    "timestamp": "20251004211344",
    "licenseId": 1157166,
    "eventUuid": "0b90b374-216f-467a-875d-116f594cf608"
  },
  {
    "idTeam": 456403,
    "actorName": "MARTÍ SÁNCHEZ LORENTE",
    "actorId": 7485865,
    "actorShirtNumber": "9",
    "idMove": 160,
    "move": "Personal 1 tir lliure, 2a falta",
    "min": 5,
    "sec": 0,
    "period": 4,
    "score": "55-41",
    "teamAction": false,
    "foulNumber": 2,
    "timestamp": "20251004211347",
    "licenseId": 1172976,
    "eventUuid": "6673beb5-5c95-4ee0-8d2d-5d1ceba8f9fc"
  },
  {
    "idTeam": 456402,
    "actorName": "ARNAU CUBERES TORO",
    "actorId": 7485850,
    "actorShirtNumber": "12",
    "idMove": 96,
    "move": "Intent fallat de 1",
    "min": 5,
    "sec": 0,
    "period": 4,
    "score": "55-41",
    "teamAction": false,
    "timestamp": "20251004211358",
    "licenseId": 1157166,
    "eventUuid": "61ac708d-4024-46b3-8674-7102dd9cd3e8"
  },
  {
    "idTeam": 456402,
    "actorName": "CESC MONTER PALAU",
    "actorId": 7485849,
    "actorShirtNumber": "18",
    "idMove": 93,
    "move": "Cistella de 2",
    "min": 5,
    "sec": 0,
    "period": 4,
    "score": "57-41",
    "teamAction": false,
    "timestamp": "20251004211407",
    "licenseId": 1157164,
    "eventUuid": "98be748c-232e-43d4-9cb8-5b2038c278c7"
  },
  {
    "idTeam": 456403,
    "actorName": "MARTÍ SÁNCHEZ LORENTE",
    "actorId": 7485865,
    "actorShirtNumber": "9",
    "idMove": 93,
    "move": "Cistella de 2",
    "min": 5,
    "sec": 0,
    "period": 4,
    "score": "57-43",
    "teamAction": false,
    "timestamp": "20251004211415",
    "licenseId": 1172976,
    "eventUuid": "accfe851-03fe-4e74-833f-959293fb2f1e"
  },
  {
    "idTeam": 456403,
    "actorName": "MARTÍ SÁNCHEZ LORENTE",
    "actorId": 7485865,
    "actorShirtNumber": "9",
    "idMove": 115,
    "move": "Surt del camp",
    "min": 5,
    "sec": 0,
    "period": 4,
    "score": "57-43",
    "teamAction": false,
    "timestamp": "20251004211426",
    "licenseId": 1172976,
    "eventUuid": "bab647f8-adbc-4f62-a5eb-a380677451b6"
  },
  {
    "idTeam": 456403,
    "actorName": "MARC VILARDELL GARCIA",
    "actorId": 7485860,
    "actorShirtNumber": "23",
    "idMove": 112,
    "move": "Entra al camp",
    "min": 5,
    "sec": 0,
    "period": 4,
    "score": "57-43",
    "teamAction": false,
    "timestamp": "20251004211426",
    "licenseId": 1172967,
    "eventUuid": "e2ace65c-e58b-47e0-a11c-1c587919ad15"
  },
  {
    "idTeam": 456402,
    "actorName": "CESC MONTER PALAU",
    "actorId": 7485849,
    "actorShirtNumber": "18",
    "idMove": 159,
    "move": "Personal, 3a falta",
    "min": 4,
    "sec": 0,
    "period": 4,
    "score": "57-43",
    "teamAction": false,
    "foulNumber": 3,
    "timestamp": "20251004211456",
    "licenseId": 1157164,
    "eventUuid": "49fbdf7f-3523-4398-a6a3-209ed7e4b47a"
  },
  {
    "idTeam": 456403,
    "actorName": "JOEL ARMINDO ROCHA CREUS",
    "actorId": 7485863,
    "actorShirtNumber": "3",
    "idMove": 115,
    "move": "Surt del camp",
    "min": 4,
    "sec": 0,
    "period": 4,
    "score": "57-43",
    "teamAction": false,
    "timestamp": "20251004211458",
    "licenseId": 1172974,
    "eventUuid": "b42d5f57-6d80-48c8-9643-5d669aa52989"
  },
  {
    "idTeam": 456403,
    "actorName": "MARTÍ SÁNCHEZ LORENTE",
    "actorId": 7485865,
    "actorShirtNumber": "9",
    "idMove": 112,
    "move": "Entra al camp",
    "min": 4,
    "sec": 0,
    "period": 4,
    "score": "57-43",
    "teamAction": false,
    "timestamp": "20251004211458",
    "licenseId": 1172976,
    "eventUuid": "22c8eea6-0c2e-4d7a-bf26-29eed1d10b33"
  },
  {
    "idTeam": 456402,
    "actorName": "CESC MONTER PALAU",
    "actorId": 7485849,
    "actorShirtNumber": "18",
    "idMove": 93,
    "move": "Cistella de 2",
    "min": 4,
    "sec": 0,
    "period": 4,
    "score": "59-43",
    "teamAction": false,
    "timestamp": "20251004211536",
    "licenseId": 1157164,
    "eventUuid": "1c36a36a-1ce1-40a7-b558-17443b23bf3b"
  },
  {
    "idTeam": 456403,
    "actorName": "MARIO GALLEGO TOLEDANO",
    "actorId": 7485862,
    "actorShirtNumber": "7",
    "idMove": 160,
    "move": "Personal 1 tir lliure, 3a falta",
    "min": 4,
    "sec": 0,
    "period": 4,
    "score": "59-43",
    "teamAction": false,
    "foulNumber": 3,
    "timestamp": "20251004211540",
    "licenseId": 1172972,
    "eventUuid": "5b3361f5-80b8-4244-afab-f3a9bfe6549f"
  },
  {
    "idTeam": 456402,
    "actorName": "CESC MONTER PALAU",
    "actorId": 7485849,
    "actorShirtNumber": "18",
    "idMove": 92,
    "move": "Cistella de 1",
    "min": 4,
    "sec": 0,
    "period": 4,
    "score": "60-43",
    "teamAction": false,
    "timestamp": "20251004211551",
    "licenseId": 1157164,
    "eventUuid": "5d621307-0c19-43d9-b4aa-75456e6a9ee6"
  },
  {
    "idTeam": 456403,
    "actorName": "MARIO GALLEGO TOLEDANO",
    "actorId": 7485862,
    "actorShirtNumber": "7",
    "idMove": 161,
    "move": "Personal 2 tirs lliures, 4a falta",
    "min": 4,
    "sec": 0,
    "period": 4,
    "score": "60-43",
    "teamAction": false,
    "foulNumber": 4,
    "timestamp": "20251004211604",
    "licenseId": 1172972,
    "eventUuid": "313f9df4-f470-4680-b558-4f395c428b23"
  },
  {
    "idTeam": 456402,
    "actorName": "CESC MONTER PALAU",
    "actorId": 7485849,
    "actorShirtNumber": "18",
    "idMove": 92,
    "move": "Cistella de 1",
    "min": 4,
    "sec": 0,
    "period": 4,
    "score": "61-43",
    "teamAction": false,
    "timestamp": "20251004211621",
    "licenseId": 1157164,
    "eventUuid": "49a8fa18-0fa5-4adc-a067-4be1262325a8"
  },
  {
    "idTeam": 456402,
    "actorName": "CESC MONTER PALAU",
    "actorId": 7485849,
    "actorShirtNumber": "18",
    "idMove": 96,
    "move": "Intent fallat de 1",
    "min": 4,
    "sec": 0,
    "period": 4,
    "score": "61-43",
    "teamAction": false,
    "timestamp": "20251004211621",
    "licenseId": 1157164,
    "eventUuid": "86afb5fb-8646-4690-81d0-39ef2b0c23a3"
  },
  {
    "idTeam": 456402,
    "actorName": "CESC MONTER PALAU",
    "actorId": 7485849,
    "actorShirtNumber": "18",
    "idMove": 115,
    "move": "Surt del camp",
    "min": 3,
    "sec": 0,
    "period": 4,
    "score": "61-43",
    "teamAction": false,
    "timestamp": "20251004211711",
    "licenseId": 1157164,
    "eventUuid": "239c4a57-4d35-4cc7-94c7-67c4f3d4efe9"
  },
  {
    "idTeam": 456402,
    "actorName": "DILAN SALAZAR MAYORGA",
    "actorId": 7485853,
    "actorShirtNumber": "77",
    "idMove": 112,
    "move": "Entra al camp",
    "min": 3,
    "sec": 0,
    "period": 4,
    "score": "61-43",
    "teamAction": false,
    "timestamp": "20251004211711",
    "licenseId": 1158309,
    "eventUuid": "505cae85-8d54-4a50-b342-7fe3494b63b3"
  },
  {
    "idTeam": 456402,
    "actorName": "MARC ELENO ESPINA",
    "actorId": 71051759600204400,
    "actorShirtNumber": "20",
    "idMove": 159,
    "move": "Personal, 2a falta",
    "min": 3,
    "sec": 0,
    "period": 4,
    "score": "61-43",
    "teamAction": false,
    "foulNumber": 2,
    "timestamp": "20251004211757",
    "licenseId": 1154262,
    "eventUuid": "e8e4be33-58a1-4fc6-ae8c-df2522a111c0"
  },
  {
    "idTeam": 456402,
    "actorName": "MARC ELENO ESPINA",
    "actorId": 71051759600204400,
    "actorShirtNumber": "20",
    "idMove": 93,
    "move": "Cistella de 2",
    "min": 3,
    "sec": 0,
    "period": 4,
    "score": "63-43",
    "teamAction": false,
    "timestamp": "20251004211834",
    "licenseId": 1154262,
    "eventUuid": "a349e9eb-1155-4353-9159-d6cc9d97d48d"
  },
  {
    "idTeam": 456403,
    "actorName": "MARIO GALLEGO TOLEDANO",
    "actorId": 7485862,
    "actorShirtNumber": "7",
    "idMove": 115,
    "move": "Surt del camp",
    "min": 3,
    "sec": 0,
    "period": 4,
    "score": "63-43",
    "teamAction": false,
    "timestamp": "20251004211900",
    "licenseId": 1172972,
    "eventUuid": "44e5288e-2a05-4329-9df4-a6392d840757"
  },
  {
    "idTeam": 456403,
    "actorName": "JOEL ARMINDO ROCHA CREUS",
    "actorId": 7485863,
    "actorShirtNumber": "3",
    "idMove": 112,
    "move": "Entra al camp",
    "min": 3,
    "sec": 0,
    "period": 4,
    "score": "63-43",
    "teamAction": false,
    "timestamp": "20251004211900",
    "licenseId": 1172974,
    "eventUuid": "38a08314-6430-45c2-bb83-21614e581c85"
  },
  {
    "idTeam": 456402,
    "actorName": "ALEIX ELENO ESPINA",
    "actorId": 7485848,
    "actorShirtNumber": "14",
    "idMove": 161,
    "move": "Personal 2 tirs lliures, 4a falta",
    "min": 3,
    "sec": 0,
    "period": 4,
    "score": "63-43",
    "teamAction": false,
    "foulNumber": 4,
    "timestamp": "20251004211959",
    "licenseId": 1157163,
    "eventUuid": "d5d3ba22-f52b-4f9b-a8c3-9d6bd595e783"
  },
  {
    "idTeam": 456403,
    "actorName": "JOAN PUJANTE HOMS",
    "actorId": 7485869,
    "actorShirtNumber": "4",
    "idMove": 96,
    "move": "Intent fallat de 1",
    "min": 3,
    "sec": 0,
    "period": 4,
    "score": "63-43",
    "teamAction": false,
    "timestamp": "20251004212009",
    "licenseId": 1177314,
    "eventUuid": "6daaba3d-4ae7-48ae-91c7-72823bbc6034"
  },
  {
    "idTeam": 456403,
    "actorName": "JOAN PUJANTE HOMS",
    "actorId": 7485869,
    "actorShirtNumber": "4",
    "idMove": 96,
    "move": "Intent fallat de 1",
    "min": 3,
    "sec": 0,
    "period": 4,
    "score": "63-43",
    "teamAction": false,
    "timestamp": "20251004212009",
    "licenseId": 1177314,
    "eventUuid": "bdf275ce-7687-4c4e-9f4e-534251a6c355"
  },
  {
    "idTeam": 456402,
    "actorName": "FRANCESC ALVAREZ HEREDIA",
    "actorId": 7485852,
    "actorShirtNumber": "23",
    "idMove": 93,
    "move": "Cistella de 2",
    "min": 3,
    "sec": 0,
    "period": 4,
    "score": "65-43",
    "teamAction": false,
    "timestamp": "20251004212038",
    "licenseId": 1157169,
    "eventUuid": "7009b506-bee3-418f-b2ba-10df37bfcab5"
  },
  {
    "idTeam": 456403,
    "actorName": "ALEX VALERO GIL",
    "actorId": 7485859,
    "actorShirtNumber": "89",
    "idMove": 93,
    "move": "Cistella de 2",
    "min": 1,
    "sec": 0,
    "period": 4,
    "score": "65-45",
    "teamAction": false,
    "timestamp": "20251004212106",
    "licenseId": 1166232,
    "eventUuid": "b23ad534-08a8-4d38-8430-225a1e08998f"
  },
  {
    "idTeam": 456403,
    "actorName": "MARC VILARDELL GARCIA",
    "actorId": 7485860,
    "actorShirtNumber": "23",
    "idMove": 93,
    "move": "Cistella de 2",
    "min": 1,
    "sec": 0,
    "period": 4,
    "score": "65-47",
    "teamAction": false,
    "timestamp": "20251004212135",
    "licenseId": 1172967,
    "eventUuid": "8503d28d-7637-4ea5-a00d-d4168a946585"
  },
  {
    "idTeam": 456402,
    "actorName": "ALEIX ELENO ESPINA",
    "actorId": 7485848,
    "actorShirtNumber": "14",
    "idMove": 93,
    "move": "Cistella de 2",
    "min": 1,
    "sec": 0,
    "period": 4,
    "score": "67-47",
    "teamAction": false,
    "timestamp": "20251004212154",
    "licenseId": 1157163,
    "eventUuid": "35a81b1f-8a4b-4ccc-867e-90eb3daaca25"
  },
  {
    "idTeam": 456402,
    "actorName": "MARC ELENO ESPINA",
    "actorId": 71051759600204400,
    "actorShirtNumber": "20",
    "idMove": 93,
    "move": "Cistella de 2",
    "min": 0,
    "sec": 0,
    "period": 4,
    "score": "69-47",
    "teamAction": false,
    "timestamp": "20251004212259",
    "licenseId": 1154262,
    "eventUuid": "00d0f9d0-395a-45a8-8b45-b50a645e14de"
  },
  {
    "idTeam": 456402,
    "actorName": "DILAN SALAZAR MAYORGA",
    "actorId": 7485853,
    "actorShirtNumber": "77",
    "idMove": 161,
    "move": "Personal 2 tirs lliures, 2a falta",
    "min": 0,
    "sec": 0,
    "period": 4,
    "score": "69-47",
    "teamAction": false,
    "foulNumber": 2,
    "timestamp": "20251004212306",
    "licenseId": 1158309,
    "eventUuid": "ab87aa95-639f-4af8-a7ed-10240e199195"
  },
  {
    "idTeam": 456403,
    "actorName": "JOEL ARMINDO ROCHA CREUS",
    "actorId": 7485863,
    "actorShirtNumber": "3",
    "idMove": 92,
    "move": "Cistella de 1",
    "min": 0,
    "sec": 0,
    "period": 4,
    "score": "69-48",
    "teamAction": false,
    "timestamp": "20251004212317",
    "licenseId": 1172974,
    "eventUuid": "f0a9d4c2-a242-4751-b64f-4e869d20be10"
  },
  {
    "idTeam": 456403,
    "actorName": "JOEL ARMINDO ROCHA CREUS",
    "actorId": 7485863,
    "actorShirtNumber": "3",
    "idMove": 92,
    "move": "Cistella de 1",
    "min": 0,
    "sec": 0,
    "period": 4,
    "score": "69-49",
    "teamAction": false,
    "timestamp": "20251004212317",
    "licenseId": 1172974,
    "eventUuid": "52036384-9092-4a3d-901a-a6d282cc7a76"
  },
  {
    "idTeam": 0,
    "actorName": "",
    "actorId": 0,
    "actorShirtNumber": "",
    "idMove": 116,
    "move": "Final de període",
    "min": 0,
    "sec": 0,
    "period": 4,
    "score": "69-49",
    "teamAction": true,
    "timestamp": "20251004212358",
    "eventUuid": "c6e7999e-572b-4fa5-855d-0a0a079b674b"
  }
]