[
  {
    "idTeam": 481314,
    "actorName": "ARAN BUTINK ROJAS",
    "actorId": 8168872,
    "actorShirtNumber": "1",
    "idMove": 178,
    "move": "Salt guanyat",
    "min": 6,
    "sec": 0,
    "period": 1,
    "score": "0-0",
    "teamAction": false,
    "timestamp": "20251116091633",
    "licenseId": 1165921,
    "eventUuid": "8fc15d51-4651-43b5-96b1-c0ffdfec2317"
  },
  {
    "idTeam": 481315,
    "actorName": "SALVADOR FERNANDEZ GRANT",
    "actorId": 8169684,
    "actorShirtNumber": "18",
    "idMove": 179,
    "move": "Salt perdut",
    "min": 6,
    "sec": 0,
    "period": 1,
    "score": "0-0",
    "teamAction": false,
    "timestamp": "20251116091633",
    "licenseId": 1147408,
    "eventUuid": "a90a7c57-a851-4921-b2bc-030e05525af2"
  },
  {
    "idTeam": 481314,
    "actorName": "ARAN BUTINK ROJAS",
    "actorId": 8168872,
    "actorShirtNumber": "1",
    "idMove": 93,
    "move": "Cistella de 2",
    "min": 5,
    "sec": 39,
    "period": 1,
    "score": "2-0",
    "teamAction": false,
    "timestamp": "20251116091740",
    "licenseId": 1165921,
    "eventUuid": "be54ac61-7567-49ce-88f7-bc717c051f4a"
  },
  {
    "idTeam": 481314,
    "actorName": "GERARD ALSINA GINESTA",
    "actorId": 8168879,
    "actorShirtNumber": "8",
    "idMove": 93,
    "move": "Cistella de 2",
    "min": 4,
    "sec": 17,
    "period": 1,
    "score": "4-0",
    "teamAction": false,
    "timestamp": "20251116091901",
    "licenseId": 1165928,
    "eventUuid": "8ba73b22-2d94-40c6-a66b-6512e3822931"
  },
  {
    "idTeam": 481315,
    "actorName": "BIEL GUZMAN TORRAS",
    "actorId": 8169688,
    "actorShirtNumber": "17",
    "idMove": 159,
    "move": "Personal, 1a falta",
    "min": 1,
    "sec": 16,
    "period": 1,
    "score": "4-0",
    "teamAction": false,
    "foulNumber": 1,
    "timestamp": "20251116092217",
    "licenseId": 1162343,
    "eventUuid": "faba2c2f-3093-4997-8eb0-27799e8e441a"
  },
  {
    "idTeam": 481314,
    "actorName": "ARAN BUTINK ROJAS",
    "actorId": 8168872,
    "actorShirtNumber": "1",
    "idMove": 93,
    "move": "Cistella de 2",
    "min": 0,
    "sec": 46,
    "period": 1,
    "score": "6-0",
    "teamAction": false,
    "timestamp": "20251116092248",
    "licenseId": 1165921,
    "eventUuid": "77edc5b2-8e05-465e-8e48-26878ac05f26"
  },
  {
    "idTeam": 481315,
    "actorName": "SALVADOR FERNANDEZ GRANT",
    "actorId": 8169684,
    "actorShirtNumber": "18",
    "idMove": 160,
    "move": "Personal 1 tir lliure, 1a falta",
    "min": 0,
    "sec": 46,
    "period": 1,
    "score": "6-0",
    "teamAction": false,
    "foulNumber": 1,
    "timestamp": "20251116092256",
    "licenseId": 1147408,
    "eventUuid": "1c20b9df-3f01-4cfd-9780-111b8bbd873d"
  },
  {
    "idTeam": 481314,
    "actorName": "ARAN BUTINK ROJAS",
    "actorId": 8168872,
    "actorShirtNumber": "1",
    "idMove": 92,
    "move": "Cistella de 1",
    "min": 0,
    "sec": 46,
    "period": 1,
    "score": "7-0",
    "teamAction": false,
    "timestamp": "20251116092308",
    "licenseId": 1165921,
    "eventUuid": "680cdaf3-fb0b-4b19-9aed-a890cfbfbabb"
  },
  {
    "idTeam": 0,
    "actorName": "",
    "actorId": 0,
    "actorShirtNumber": "",
    "idMove": 116,
    "move": "Final de període",
    "min": 0,
    "sec": 0,
    "period": 1,
    "score": "7-0",
    "teamAction": true,
    "timestamp": "20251116092420",
    "eventUuid": "b6ec707d-84cf-48ca-8b35-21809f3d40f3"
  },
  {
    "idTeam": 481314,
    "actorName": "ARAN BUTINK ROJAS",
    "actorId": 8168872,
    "actorShirtNumber": "1",
    "idMove": 115,
    "move": "Surt del camp",
    "min": 6,
    "sec": 0,
    "period": 2,
    "score": "0-0",
    "teamAction": false,
    "timestamp": "20251116092420",
    "licenseId": 1165921,
    "eventUuid": "49d7e90c-4ee8-4527-8f93-06ded7df9999"
  },
  {
    "idTeam": 481314,
    "actorName": "GERARD ALSINA GINESTA",
    "actorId": 8168879,
    "actorShirtNumber": "8",
    "idMove": 115,
    "move": "Surt del camp",
    "min": 6,
    "sec": 0,
    "period": 2,
    "score": "0-0",
    "teamAction": false,
    "timestamp": "20251116092420",
    "licenseId": 1165928,
    "eventUuid": "2f7702d0-0fc9-4d26-87af-1dd9dbb45849"
  },
  {
    "idTeam": 481314,
    "actorName": "TRAVIS ROJO CORBERA",
    "actorId": 8168875,
    "actorShirtNumber": "10",
    "idMove": 115,
    "move": "Surt del camp",
    "min": 6,
    "sec": 0,
    "period": 2,
    "score": "0-0",
    "teamAction": false,
    "timestamp": "20251116092420",
    "licenseId": 1165924,
    "eventUuid": "8b9b17c4-ca54-4718-9f83-a2a19f507c70"
  },
  {
    "idTeam": 481314,
    "actorName": "POL GENÉ PALAÍN",
    "actorId": 8168874,
    "actorShirtNumber": "13",
    "idMove": 115,
    "move": "Surt del camp",
    "min": 6,
    "sec": 0,
    "period": 2,
    "score": "0-0",
    "teamAction": false,
    "timestamp": "20251116092420",
    "licenseId": 1165923,
    "eventUuid": "4f70ec1f-298b-45d2-830b-6a0d4bed1dfa"
  },
  {
    "idTeam": 481314,
    "actorName": "JAVIER CASADO MORA",
    "actorId": 8168880,
    "actorShirtNumber": "17",
    "idMove": 115,
    "move": "Surt del camp",
    "min": 6,
    "sec": 0,
    "period": 2,
    "score": "0-0",
    "teamAction": false,
    "timestamp": "20251116092420",
    "licenseId": 1165929,
    "eventUuid": "9c087550-663e-45eb-90d0-764a681c39ed"
  },
  {
    "idTeam": 481314,
    "actorName": "PABLO GAEL BRONCHAL TORRES",
    "actorId": 8168877,
    "actorShirtNumber": "24",
    "idMove": 112,
    "move": "Entra al camp",
    "min": 6,
    "sec": 0,
    "period": 2,
    "score": "0-0",
    "teamAction": false,
    "timestamp": "20251116092420",
    "licenseId": 1165926,
    "eventUuid": "d65d5b25-b894-4ded-ae6c-ef7c042e7fee"
  },
  {
    "idTeam": 481314,
    "actorName": "XAVIER CATALAN VENTOSO",
    "actorId": 8168882,
    "actorShirtNumber": "15",
    "idMove": 112,
    "move": "Entra al camp",
    "min": 6,
    "sec": 0,
    "period": 2,
    "score": "0-0",
    "teamAction": false,
    "timestamp": "20251116092420",
    "licenseId": 1181289,
    "eventUuid": "181f46f8-76ca-45a7-ab66-d09cee6f7734"
  },
  {
    "idTeam": 481314,
    "actorName": "RAPHAEL RODIER MICHEL",
    "actorId": 8168873,
    "actorShirtNumber": "12",
    "idMove": 112,
    "move": "Entra al camp",
    "min": 6,
    "sec": 0,
    "period": 2,
    "score": "0-0",
    "teamAction": false,
    "timestamp": "20251116092420",
    "licenseId": 1165922,
    "eventUuid": "4740d775-2a08-4707-a333-f37f138a82c9"
  },
  {
    "idTeam": 481314,
    "actorName": "SERGI CALAF ROCA",
    "actorId": 8168876,
    "actorShirtNumber": "3",
    "idMove": 112,
    "move": "Entra al camp",
    "min": 6,
    "sec": 0,
    "period": 2,
    "score": "0-0",
    "teamAction": false,
    "timestamp": "20251116092420",
    "licenseId": 1165925,
    "eventUuid": "d5a29274-550c-4a8f-8cb8-84ad02a7d825"
  },
  {
    "idTeam": 481314,
    "actorName": "NIL PASCUAL GUILLÓ",
    "actorId": 8168883,
    "actorShirtNumber": "7",
    "idMove": 112,
    "move": "Entra al camp",
    "min": 6,
    "sec": 0,
    "period": 2,
    "score": "0-0",
    "teamAction": false,
    "timestamp": "20251116092420",
    "licenseId": 1207035,
    "eventUuid": "fab7811b-ed74-4110-b1a2-75c938ffef8f"
  },
  {
    "idTeam": 481315,
    "actorName": "SALVADOR FERNANDEZ GRANT",
    "actorId": 8169684,
    "actorShirtNumber": "18",
    "idMove": 115,
    "move": "Surt del camp",
    "min": 6,
    "sec": 0,
    "period": 2,
    "score": "0-0",
    "teamAction": false,
    "timestamp": "20251116092420",
    "licenseId": 1147408,
    "eventUuid": "128badd0-0f07-4a5a-a205-1fb19abc9ea2"
  },
  {
    "idTeam": 481315,
    "actorName": "JAN ERROZ NOVELL",
    "actorId": 8169680,
    "actorShirtNumber": "21",
    "idMove": 115,
    "move": "Surt del camp",
    "min": 6,
    "sec": 0,
    "period": 2,
    "score": "0-0",
    "teamAction": false,
    "timestamp": "20251116092420",
    "licenseId": 1147404,
    "eventUuid": "b5d90d6b-c4ff-4017-9af4-7a47927da53f"
  },
  {
    "idTeam": 481315,
    "actorName": "ORIOL DE OLANO CAMPRUBÍ",
    "actorId": 8169683,
    "actorShirtNumber": "41",
    "idMove": 115,
    "move": "Surt del camp",
    "min": 6,
    "sec": 0,
    "period": 2,
    "score": "0-0",
    "teamAction": false,
    "timestamp": "20251116092420",
    "licenseId": 1147407,
    "eventUuid": "300a97d2-f945-4fa1-89d4-63f78a02db03"
  },
  {
    "idTeam": 481315,
    "actorName": "BIEL ROGES LEZCANO",
    "actorId": 8169681,
    "actorShirtNumber": "51",
    "idMove": 115,
    "move": "Surt del camp",
    "min": 6,
    "sec": 0,
    "period": 2,
    "score": "0-0",
    "teamAction": false,
    "timestamp": "20251116092420",
    "licenseId": 1147405,
    "eventUuid": "f522d0d7-2169-4ab7-b24e-28c43255394d"
  },
  {
    "idTeam": 481315,
    "actorName": "DENIZ INALER",
    "actorId": 8169686,
    "actorShirtNumber": "10",
    "idMove": 112,
    "move": "Entra al camp",
    "min": 6,
    "sec": 0,
    "period": 2,
    "score": "0-0",
    "teamAction": false,
    "timestamp": "20251116092420",
    "licenseId": 1157963,
    "eventUuid": "6a9c0705-06b1-45c4-878c-508f9c428ff0"
  },
  {
    "idTeam": 481315,
    "actorName": "ROC ROBERT CORBI",
    "actorId": 8169682,
    "actorShirtNumber": "2",
    "idMove": 112,
    "move": "Entra al camp",
    "min": 6,
    "sec": 0,
    "period": 2,
    "score": "0-0",
    "teamAction": false,
    "timestamp": "20251116092420",
    "licenseId": 1147406,
    "eventUuid": "2ee4134a-374f-4593-9fae-ac72aef2df71"
  },
  {
    "idTeam": 481315,
    "actorName": "OLIVER COMA DE HERRALDE",
    "actorId": 8169679,
    "actorShirtNumber": "19",
    "idMove": 112,
    "move": "Entra al camp",
    "min": 6,
    "sec": 0,
    "period": 2,
    "score": "0-0",
    "teamAction": false,
    "timestamp": "20251116092420",
    "licenseId": 1147403,
    "eventUuid": "957f3f4c-be8a-4a73-9787-74e252d04e20"
  },
  {
    "idTeam": 481315,
    "actorName": "NIEL GIRAL FERRARONS",
    "actorId": 8169687,
    "actorShirtNumber": "6",
    "idMove": 112,
    "move": "Entra al camp",
    "min": 6,
    "sec": 0,
    "period": 2,
    "score": "0-0",
    "teamAction": false,
    "timestamp": "20251116092420",
    "licenseId": 1158003,
    "eventUuid": "cb6b7d56-3cf2-4dc1-8d83-7bea48e60f05"
  },
  {
    "idTeam": 481315,
    "actorName": "NIEL GIRAL FERRARONS",
    "actorId": 8169687,
    "actorShirtNumber": "6",
    "idMove": 93,
    "move": "Cistella de 2",
    "min": 5,
    "sec": 33,
    "period": 2,
    "score": "0-2",
    "teamAction": false,
    "timestamp": "20251116092707",
    "licenseId": 1158003,
    "eventUuid": "df1c833f-1709-4b26-b938-045eead79422"
  },
  {
    "idTeam": 481314,
    "actorName": "RAPHAEL RODIER MICHEL",
    "actorId": 8168873,
    "actorShirtNumber": "12",
    "idMove": 93,
    "move": "Cistella de 2",
    "min": 4,
    "sec": 36,
    "period": 2,
    "score": "2-2",
    "teamAction": false,
    "timestamp": "20251116092804",
    "licenseId": 1165922,
    "eventUuid": "ebdb0878-da5c-445e-a760-e011b0334394"
  },
  {
    "idTeam": 481315,
    "actorName": "NIEL GIRAL FERRARONS",
    "actorId": 8169687,
    "actorShirtNumber": "6",
    "idMove": 161,
    "move": "Personal 2 tirs lliures, 1a falta",
    "min": 3,
    "sec": 31,
    "period": 2,
    "score": "2-2",
    "teamAction": false,
    "foulNumber": 1,
    "timestamp": "20251116092909",
    "licenseId": 1158003,
    "eventUuid": "7badd1fc-6019-4ba4-9504-b4e302fe0625"
  },
  {
    "idTeam": 481315,
    "actorName": "NIEL GIRAL FERRARONS",
    "actorId": 8169687,
    "actorShirtNumber": "6",
    "idMove": 96,
    "move": "Intent fallat de 1",
    "min": 3,
    "sec": 24,
    "period": 2,
    "score": "2-2",
    "teamAction": false,
    "timestamp": "20251116092926",
    "licenseId": 1158003,
    "eventUuid": "128a8efa-4d1b-4c53-9b5f-ee3e9449f587"
  },
  {
    "idTeam": 481315,
    "actorName": "NIEL GIRAL FERRARONS",
    "actorId": 8169687,
    "actorShirtNumber": "6",
    "idMove": 96,
    "move": "Intent fallat de 1",
    "min": 3,
    "sec": 24,
    "period": 2,
    "score": "2-2",
    "teamAction": false,
    "timestamp": "20251116092940",
    "licenseId": 1158003,
    "eventUuid": "8e8a09a7-5909-4165-a67d-7005439b2f4e"
  },
  {
    "idTeam": 481315,
    "actorName": "BIEL GUZMAN TORRAS",
    "actorId": 8169688,
    "actorShirtNumber": "17",
    "idMove": 93,
    "move": "Cistella de 2",
    "min": 3,
    "sec": 8,
    "period": 2,
    "score": "2-4",
    "teamAction": false,
    "timestamp": "20251116092957",
    "licenseId": 1162343,
    "eventUuid": "7b5ba8d8-f514-4c31-ab67-d42af8bf0efa"
  },
  {
    "idTeam": 481314,
    "actorName": "NIL PASCUAL GUILLÓ",
    "actorId": 8168883,
    "actorShirtNumber": "7",
    "idMove": 160,
    "move": "Personal 1 tir lliure, 1a falta",
    "min": 2,
    "sec": 41,
    "period": 2,
    "score": "2-4",
    "teamAction": false,
    "foulNumber": 1,
    "timestamp": "20251116093024",
    "licenseId": 1207035,
    "eventUuid": "b39acf1a-e3e6-4510-8a6e-1288828dd5d2"
  },
  {
    "idTeam": 481315,
    "actorName": "NIEL GIRAL FERRARONS",
    "actorId": 8169687,
    "actorShirtNumber": "6",
    "idMove": 96,
    "move": "Intent fallat de 1",
    "min": 2,
    "sec": 30,
    "period": 2,
    "score": "2-4",
    "teamAction": false,
    "timestamp": "20251116093100",
    "licenseId": 1158003,
    "eventUuid": "bc350db1-0a37-4a68-b496-80604dd914a6"
  },
  {
    "idTeam": 481315,
    "actorName": "ROC ROBERT CORBI",
    "actorId": 8169682,
    "actorShirtNumber": "2",
    "idMove": 93,
    "move": "Cistella de 2",
    "min": 2,
    "sec": 12,
    "period": 2,
    "score": "2-6",
    "teamAction": false,
    "timestamp": "20251116093120",
    "licenseId": 1147406,
    "eventUuid": "e601ef16-7095-416e-b8ce-fa68f22ba513"
  },
  {
    "idTeam": 481314,
    "actorName": "NIL PASCUAL GUILLÓ",
    "actorId": 8168883,
    "actorShirtNumber": "7",
    "idMove": 93,
    "move": "Cistella de 2",
    "min": 0,
    "sec": 59,
    "period": 2,
    "score": "4-6",
    "teamAction": false,
    "timestamp": "20251116093233",
    "licenseId": 1207035,
    "eventUuid": "16ff1f06-a381-444b-9d2a-1d52fd3c2407"
  },
  {
    "idTeam": 481314,
    "actorName": "NIL PASCUAL GUILLÓ",
    "actorId": 8168883,
    "actorShirtNumber": "7",
    "idMove": 94,
    "move": "Cistella de 3",
    "min": 0,
    "sec": 47,
    "period": 2,
    "score": "7-6",
    "teamAction": false,
    "timestamp": "20251116093245",
    "licenseId": 1207035,
    "eventUuid": "0aa1a444-3b37-4dbb-ab69-d1160854761b"
  },
  {
    "idTeam": 481314,
    "actorName": "XAVIER CATALAN VENTOSO",
    "actorId": 8168882,
    "actorShirtNumber": "15",
    "idMove": 159,
    "move": "Personal, 1a falta",
    "min": 0,
    "sec": 17,
    "period": 2,
    "score": "7-6",
    "teamAction": false,
    "foulNumber": 1,
    "timestamp": "20251116093315",
    "licenseId": 1181289,
    "eventUuid": "92d37cee-706f-4962-97e1-cacb6d944b0f"
  },
  {
    "idTeam": 481315,
    "actorName": "OLIVER COMA DE HERRALDE",
    "actorId": 8169679,
    "actorShirtNumber": "19",
    "idMove": 159,
    "move": "Personal, 1a falta",
    "min": 0,
    "sec": 0,
    "period": 2,
    "score": "7-6",
    "teamAction": false,
    "foulNumber": 1,
    "timestamp": "20251116093335",
    "licenseId": 1147403,
    "eventUuid": "2ddf4ab6-d233-42ab-b91c-e14c73b3c6ce"
  },
  {
    "idTeam": 481314,
    "actorName": "SERGI CALAF ROCA",
    "actorId": 8168876,
    "actorShirtNumber": "3",
    "idMove": 93,
    "move": "Cistella de 2",
    "min": 0,
    "sec": 0,
    "period": 2,
    "score": "9-6",
    "teamAction": false,
    "timestamp": "20251116093348",
    "licenseId": 1165925,
    "eventUuid": "5c4ea373-f191-4e5e-a13c-3e1248299205"
  },
  {
    "idTeam": 481315,
    "actorName": "NIEL GIRAL FERRARONS",
    "actorId": 8169687,
    "actorShirtNumber": "6",
    "idMove": 93,
    "move": "Cistella de 2",
    "min": 0,
    "sec": 0,
    "period": 2,
    "score": "9-8",
    "teamAction": false,
    "timestamp": "20251116093414",
    "licenseId": 1158003,
    "eventUuid": "ac92c68b-6fb5-4325-9efe-9c241cb990c4"
  },
  {
    "idTeam": 0,
    "actorName": "",
    "actorId": 0,
    "actorShirtNumber": "",
    "idMove": 116,
    "move": "Final de període",
    "min": 0,
    "sec": 0,
    "period": 2,
    "score": "9-8",
    "teamAction": true,
    "timestamp": "20251116093426",
    "eventUuid": "b322f46d-a5a6-4a9a-b714-411e417a09d0"
  },
  {
    "idTeam": 481314,
    "actorName": "PABLO GAEL BRONCHAL TORRES",
    "actorId": 8168877,
    "actorShirtNumber": "24",
    "idMove": 115,
    "move": "Surt del camp",
    "min": 6,
    "sec": 0,
    "period": 3,
    "score": "0-0",
    "teamAction": false,
    "timestamp": "20251116093426",
    "licenseId": 1165926,
    "eventUuid": "073612d1-df3d-4e98-80df-5d9ae8f20988"
  },
  {
    "idTeam": 481314,
    "actorName": "XAVIER CATALAN VENTOSO",
    "actorId": 8168882,
    "actorShirtNumber": "15",
    "idMove": 115,
    "move": "Surt del camp",
    "min": 6,
    "sec": 0,
    "period": 3,
    "score": "0-0",
    "teamAction": false,
    "timestamp": "20251116093426",
    "licenseId": 1181289,
    "eventUuid": "827ca565-7626-4ce9-8f02-ca16245fa6f3"
  },
  {
    "idTeam": 481314,
    "actorName": "RAPHAEL RODIER MICHEL",
    "actorId": 8168873,
    "actorShirtNumber": "12",
    "idMove": 115,
    "move": "Surt del camp",
    "min": 6,
    "sec": 0,
    "period": 3,
    "score": "0-0",
    "teamAction": false,
    "timestamp": "20251116093426",
    "licenseId": 1165922,
    "eventUuid": "dcee04a0-7ff9-48f9-b471-f0d60c4bdcb8"
  },
  {
    "idTeam": 481314,
    "actorName": "SERGI CALAF ROCA",
    "actorId": 8168876,
    "actorShirtNumber": "3",
    "idMove": 115,
    "move": "Surt del camp",
    "min": 6,
    "sec": 0,
    "period": 3,
    "score": "0-0",
    "teamAction": false,
    "timestamp": "20251116093426",
    "licenseId": 1165925,
    "eventUuid": "7ba29af3-2e64-4901-a3c9-489025a40516"
  },
  {
    "idTeam": 481314,
    "actorName": "NIL PASCUAL GUILLÓ",
    "actorId": 8168883,
    "actorShirtNumber": "7",
    "idMove": 115,
    "move": "Surt del camp",
    "min": 6,
    "sec": 0,
    "period": 3,
    "score": "0-0",
    "teamAction": false,
    "timestamp": "20251116093426",
    "licenseId": 1207035,
    "eventUuid": "7f8a3fc7-f4f9-4a7f-bba6-e60872303cc1"
  },
  {
    "idTeam": 481314,
    "actorName": "GERARD ALSINA GINESTA",
    "actorId": 8168879,
    "actorShirtNumber": "8",
    "idMove": 112,
    "move": "Entra al camp",
    "min": 6,
    "sec": 0,
    "period": 3,
    "score": "0-0",
    "teamAction": false,
    "timestamp": "20251116093426",
    "licenseId": 1165928,
    "eventUuid": "ec74668b-dc75-4fca-9ac4-903fce324734"
  },
  {
    "idTeam": 481314,
    "actorName": "JAVIER CASADO MORA",
    "actorId": 8168880,
    "actorShirtNumber": "17",
    "idMove": 112,
    "move": "Entra al camp",
    "min": 6,
    "sec": 0,
    "period": 3,
    "score": "0-0",
    "teamAction": false,
    "timestamp": "20251116093426",
    "licenseId": 1165929,
    "eventUuid": "5a81dae5-1d21-4333-83c3-f03db71f2071"
  },
  {
    "idTeam": 481314,
    "actorName": "POL GENÉ PALAÍN",
    "actorId": 8168874,
    "actorShirtNumber": "13",
    "idMove": 112,
    "move": "Entra al camp",
    "min": 6,
    "sec": 0,
    "period": 3,
    "score": "0-0",
    "teamAction": false,
    "timestamp": "20251116093426",
    "licenseId": 1165923,
    "eventUuid": "15d4773d-dcf2-4594-ba61-ea052cebfd64"
  },
  {
    "idTeam": 481314,
    "actorName": "TRAVIS ROJO CORBERA",
    "actorId": 8168875,
    "actorShirtNumber": "10",
    "idMove": 112,
    "move": "Entra al camp",
    "min": 6,
    "sec": 0,
    "period": 3,
    "score": "0-0",
    "teamAction": false,
    "timestamp": "20251116093426",
    "licenseId": 1165924,
    "eventUuid": "aef5282c-7bc5-4283-a3d3-646673d9485f"
  },
  {
    "idTeam": 481314,
    "actorName": "ARAN BUTINK ROJAS",
    "actorId": 8168872,
    "actorShirtNumber": "1",
    "idMove": 112,
    "move": "Entra al camp",
    "min": 6,
    "sec": 0,
    "period": 3,
    "score": "0-0",
    "teamAction": false,
    "timestamp": "20251116093426",
    "licenseId": 1165921,
    "eventUuid": "2bccfeb9-0c53-4161-b883-b7e33bd4a10c"
  },
  {
    "idTeam": 481315,
    "actorName": "BIEL GUZMAN TORRAS",
    "actorId": 8169688,
    "actorShirtNumber": "17",
    "idMove": 115,
    "move": "Surt del camp",
    "min": 6,
    "sec": 0,
    "period": 3,
    "score": "0-0",
    "teamAction": false,
    "timestamp": "20251116093426",
    "licenseId": 1162343,
    "eventUuid": "41cc3e83-8613-46a7-9cf2-ffb06b0e5f47"
  },
  {
    "idTeam": 481315,
    "actorName": "ROC ROBERT CORBI",
    "actorId": 8169682,
    "actorShirtNumber": "2",
    "idMove": 115,
    "move": "Surt del camp",
    "min": 6,
    "sec": 0,
    "period": 3,
    "score": "0-0",
    "teamAction": false,
    "timestamp": "20251116093426",
    "licenseId": 1147406,
    "eventUuid": "add9d589-452e-4cf4-8ee3-9304debab80c"
  },
  {
    "idTeam": 481315,
    "actorName": "OLIVER COMA DE HERRALDE",
    "actorId": 8169679,
    "actorShirtNumber": "19",
    "idMove": 115,
    "move": "Surt del camp",
    "min": 6,
    "sec": 0,
    "period": 3,
    "score": "0-0",
    "teamAction": false,
    "timestamp": "20251116093426",
    "licenseId": 1147403,
    "eventUuid": "e7f8490e-cb61-42cc-8437-5895e96afed1"
  },
  {
    "idTeam": 481315,
    "actorName": "NIEL GIRAL FERRARONS",
    "actorId": 8169687,
    "actorShirtNumber": "6",
    "idMove": 115,
    "move": "Surt del camp",
    "min": 6,
    "sec": 0,
    "period": 3,
    "score": "0-0",
    "teamAction": false,
    "timestamp": "20251116093426",
    "licenseId": 1158003,
    "eventUuid": "7b7235e6-586c-4adc-ba0a-3dac68a45d80"
  },
  {
    "idTeam": 481315,
    "actorName": "SALVADOR FERNANDEZ GRANT",
    "actorId": 8169684,
    "actorShirtNumber": "18",
    "idMove": 112,
    "move": "Entra al camp",
    "min": 6,
    "sec": 0,
    "period": 3,
    "score": "0-0",
    "teamAction": false,
    "timestamp": "20251116093426",
    "licenseId": 1147408,
    "eventUuid": "11e9120a-900d-4d16-a47f-bfc0fd4113be"
  },
  {
    "idTeam": 481315,
    "actorName": "ORIOL DE OLANO CAMPRUBÍ",
    "actorId": 8169683,
    "actorShirtNumber": "41",
    "idMove": 112,
    "move": "Entra al camp",
    "min": 6,
    "sec": 0,
    "period": 3,
    "score": "0-0",
    "teamAction": false,
    "timestamp": "20251116093426",
    "licenseId": 1147407,
    "eventUuid": "5b661bd2-6276-4a06-b119-fba70ab8a598"
  },
  {
    "idTeam": 481315,
    "actorName": "BIEL ROGES LEZCANO",
    "actorId": 8169681,
    "actorShirtNumber": "51",
    "idMove": 112,
    "move": "Entra al camp",
    "min": 6,
    "sec": 0,
    "period": 3,
    "score": "0-0",
    "teamAction": false,
    "timestamp": "20251116093426",
    "licenseId": 1147405,
    "eventUuid": "af7d5c41-e9b9-40bf-ac98-0fd6e6a5267e"
  },
  {
    "idTeam": 481315,
    "actorName": "JAN ERROZ NOVELL",
    "actorId": 8169680,
    "actorShirtNumber": "21",
    "idMove": 112,
    "move": "Entra al camp",
    "min": 6,
    "sec": 0,
    "period": 3,
    "score": "0-0",
    "teamAction": false,
    "timestamp": "20251116093426",
    "licenseId": 1147404,
    "eventUuid": "3bda3d40-8ea7-446f-add8-37db13200e97"
  },
  {
    "idTeam": 481314,
    "actorName": "JAVIER CASADO MORA",
    "actorId": 8168880,
    "actorShirtNumber": "17",
    "idMove": 93,
    "move": "Cistella de 2",
    "min": 5,
    "sec": 22,
    "period": 3,
    "score": "2-0",
    "teamAction": false,
    "timestamp": "20251116093720",
    "licenseId": 1165929,
    "eventUuid": "2fdb0f4f-0aa5-4c51-83dd-14d3efb249c7"
  },
  {
    "idTeam": 481315,
    "actorName": "ESCOLAPIS SARRIÀ",
    "actorId": 0,
    "actorShirtNumber": "",
    "idMove": 113,
    "move": "Temps mort",
    "min": 4,
    "sec": 48,
    "period": 3,
    "score": "2-0",
    "teamAction": true,
    "timestamp": "20251116093759",
    "eventUuid": "3f50b1b7-c736-456d-9631-50a263ab12bb"
  },
  {
    "idTeam": 481314,
    "actorName": "POL GENÉ PALAÍN",
    "actorId": 8168874,
    "actorShirtNumber": "13",
    "idMove": 93,
    "move": "Cistella de 2",
    "min": 4,
    "sec": 1,
    "period": 3,
    "score": "4-0",
    "teamAction": false,
    "timestamp": "20251116094019",
    "licenseId": 1165923,
    "eventUuid": "6d97997c-4c85-407e-9358-279e18b4f886"
  },
  {
    "idTeam": 481315,
    "actorName": "DENIZ INALER",
    "actorId": 8169686,
    "actorShirtNumber": "10",
    "idMove": 93,
    "move": "Cistella de 2",
    "min": 3,
    "sec": 38,
    "period": 3,
    "score": "4-2",
    "teamAction": false,
    "timestamp": "20251116094043",
    "licenseId": 1157963,
    "eventUuid": "7b9a669d-5a3e-44a1-8414-43788de74674"
  },
  {
    "idTeam": 481315,
    "actorName": "JAN ERROZ NOVELL",
    "actorId": 8169680,
    "actorShirtNumber": "21",
    "idMove": 159,
    "move": "Personal, 1a falta",
    "min": 2,
    "sec": 48,
    "period": 3,
    "score": "4-2",
    "teamAction": false,
    "foulNumber": 1,
    "timestamp": "20251116094132",
    "licenseId": 1147404,
    "eventUuid": "2ba516d4-1001-45c0-876c-8126751019fb"
  },
  {
    "idTeam": 481314,
    "actorName": "POL GENÉ PALAÍN",
    "actorId": 8168874,
    "actorShirtNumber": "13",
    "idMove": 161,
    "move": "Personal 2 tirs lliures, 1a falta",
    "min": 2,
    "sec": 4,
    "period": 3,
    "score": "4-2",
    "teamAction": false,
    "foulNumber": 1,
    "timestamp": "20251116094217",
    "licenseId": 1165923,
    "eventUuid": "7822820c-a59e-4af8-b9a7-19901eb2b922"
  },
  {
    "idTeam": 481315,
    "actorName": "DENIZ INALER",
    "actorId": 8169686,
    "actorShirtNumber": "10",
    "idMove": 96,
    "move": "Intent fallat de 1",
    "min": 2,
    "sec": 0,
    "period": 3,
    "score": "4-2",
    "teamAction": false,
    "timestamp": "20251116094233",
    "licenseId": 1157963,
    "eventUuid": "59fcf0c7-3d88-493b-bb11-ebc7d35ded48"
  },
  {
    "idTeam": 481315,
    "actorName": "DENIZ INALER",
    "actorId": 8169686,
    "actorShirtNumber": "10",
    "idMove": 92,
    "move": "Cistella de 1",
    "min": 2,
    "sec": 0,
    "period": 3,
    "score": "4-3",
    "teamAction": false,
    "timestamp": "20251116094244",
    "licenseId": 1157963,
    "eventUuid": "aef857da-e1d4-4f8c-8715-f55e5e04a8a8"
  },
  {
    "idTeam": 481315,
    "actorName": "BIEL ROGES LEZCANO",
    "actorId": 8169681,
    "actorShirtNumber": "51",
    "idMove": 93,
    "move": "Cistella de 2",
    "min": 1,
    "sec": 32,
    "period": 3,
    "score": "4-5",
    "teamAction": false,
    "timestamp": "20251116094315",
    "licenseId": 1147405,
    "eventUuid": "767c5ebf-984a-42da-b801-430ec23bf661"
  },
  {
    "idTeam": 481314,
    "actorName": "TRAVIS ROJO CORBERA",
    "actorId": 8168875,
    "actorShirtNumber": "10",
    "idMove": 93,
    "move": "Cistella de 2",
    "min": 1,
    "sec": 4,
    "period": 3,
    "score": "6-5",
    "teamAction": false,
    "timestamp": "20251116094343",
    "licenseId": 1165924,
    "eventUuid": "ac85b009-d036-4e06-921a-3adec2115f75"
  },
  {
    "idTeam": 481314,
    "actorName": "POL GENÉ PALAÍN",
    "actorId": 8168874,
    "actorShirtNumber": "13",
    "idMove": 93,
    "move": "Cistella de 2",
    "min": 0,
    "sec": 38,
    "period": 3,
    "score": "8-5",
    "teamAction": false,
    "timestamp": "20251116094409",
    "licenseId": 1165923,
    "eventUuid": "8e54f13a-9876-4441-bd53-6552b801b43b"
  },
  {
    "idTeam": 481314,
    "actorName": "POL GENÉ PALAÍN",
    "actorId": 8168874,
    "actorShirtNumber": "13",
    "idMove": 93,
    "move": "Cistella de 2",
    "min": 0,
    "sec": 4,
    "period": 3,
    "score": "10-5",
    "teamAction": false,
    "timestamp": "20251116094442",
    "licenseId": 1165923,
    "eventUuid": "34f68840-2b45-4fda-aaa9-c625869e4da8"
  },
  {
    "idTeam": 0,
    "actorName": "",
    "actorId": 0,
    "actorShirtNumber": "",
    "idMove": 116,
    "move": "Final de període",
    "min": 0,
    "sec": 0,
    "period": 3,
    "score": "10-5",
    "teamAction": true,
    "timestamp": "20251116094450",
    "eventUuid": "33a600b7-de1f-4661-9ca5-c60d12da4b8b"
  },
  {
    "idTeam": 481314,
    "actorName": "GERARD ALSINA GINESTA",
    "actorId": 8168879,
    "actorShirtNumber": "8",
    "idMove": 115,
    "move": "Surt del camp",
    "min": 6,
    "sec": 0,
    "period": 4,
    "score": "0-0",
    "teamAction": false,
    "timestamp": "20251116094450",
    "licenseId": 1165928,
    "eventUuid": "222d5871-2510-4728-8f6d-369dd49ab6ff"
  },
  {
    "idTeam": 481314,
    "actorName": "POL GENÉ PALAÍN",
    "actorId": 8168874,
    "actorShirtNumber": "13",
    "idMove": 115,
    "move": "Surt del camp",
    "min": 6,
    "sec": 0,
    "period": 4,
    "score": "0-0",
    "teamAction": false,
    "timestamp": "20251116094450",
    "licenseId": 1165923,
    "eventUuid": "f69a3d6e-2f2f-475d-a52d-53de666bf0eb"
  },
  {
    "idTeam": 481314,
    "actorName": "TRAVIS ROJO CORBERA",
    "actorId": 8168875,
    "actorShirtNumber": "10",
    "idMove": 115,
    "move": "Surt del camp",
    "min": 6,
    "sec": 0,
    "period": 4,
    "score": "0-0",
    "teamAction": false,
    "timestamp": "20251116094450",
    "licenseId": 1165924,
    "eventUuid": "e17ab068-6a06-4f63-976e-fe3151cdd902"
  },
  {
    "idTeam": 481314,
    "actorName": "ARAN BUTINK ROJAS",
    "actorId": 8168872,
    "actorShirtNumber": "1",
    "idMove": 115,
    "move": "Surt del camp",
    "min": 6,
    "sec": 0,
    "period": 4,
    "score": "0-0",
    "teamAction": false,
    "timestamp": "20251116094450",
    "licenseId": 1165921,
    "eventUuid": "d71cf744-d76a-45f3-a79c-c740eda316b6"
  },
  {
    "idTeam": 481314,
    "actorName": "PABLO GAEL BRONCHAL TORRES",
    "actorId": 8168877,
    "actorShirtNumber": "24",
    "idMove": 112,
    "move": "Entra al camp",
    "min": 6,
    "sec": 0,
    "period": 4,
    "score": "0-0",
    "teamAction": false,
    "timestamp": "20251116094450",
    "licenseId": 1165926,
    "eventUuid": "3b00910b-fa3c-4f1c-b5b9-bb998bf514a7"
  },
  {
    "idTeam": 481314,
    "actorName": "RAPHAEL RODIER MICHEL",
    "actorId": 8168873,
    "actorShirtNumber": "12",
    "idMove": 112,
    "move": "Entra al camp",
    "min": 6,
    "sec": 0,
    "period": 4,
    "score": "0-0",
    "teamAction": false,
    "timestamp": "20251116094450",
    "licenseId": 1165922,
    "eventUuid": "3223a406-d806-4761-b5b3-8a5b2f59a8b8"
  },
  {
    "idTeam": 481314,
    "actorName": "SERGI CALAF ROCA",
    "actorId": 8168876,
    "actorShirtNumber": "3",
    "idMove": 112,
    "move": "Entra al camp",
    "min": 6,
    "sec": 0,
    "period": 4,
    "score": "0-0",
    "teamAction": false,
    "timestamp": "20251116094450",
    "licenseId": 1165925,
    "eventUuid": "f1c5a765-b4bd-47a8-a3fc-1bf1535e38ab"
  },
  {
    "idTeam": 481314,
    "actorName": "NIL PASCUAL GUILLÓ",
    "actorId": 8168883,
    "actorShirtNumber": "7",
    "idMove": 112,
    "move": "Entra al camp",
    "min": 6,
    "sec": 0,
    "period": 4,
    "score": "0-0",
    "teamAction": false,
    "timestamp": "20251116094450",
    "licenseId": 1207035,
    "eventUuid": "a63a41f1-91c7-4460-b7b9-c4b297b0aaea"
  },
  {
    "idTeam": 481315,
    "actorName": "SALVADOR FERNANDEZ GRANT",
    "actorId": 8169684,
    "actorShirtNumber": "18",
    "idMove": 115,
    "move": "Surt del camp",
    "min": 6,
    "sec": 0,
    "period": 4,
    "score": "0-0",
    "teamAction": false,
    "timestamp": "20251116094450",
    "licenseId": 1147408,
    "eventUuid": "1ea4295d-9a01-4289-9ddb-ea92e6ab8c69"
  },
  {
    "idTeam": 481315,
    "actorName": "DENIZ INALER",
    "actorId": 8169686,
    "actorShirtNumber": "10",
    "idMove": 115,
    "move": "Surt del camp",
    "min": 6,
    "sec": 0,
    "period": 4,
    "score": "0-0",
    "teamAction": false,
    "timestamp": "20251116094450",
    "licenseId": 1157963,
    "eventUuid": "7a7829fd-2862-44f0-aab2-49d2b5a01888"
  },
  {
    "idTeam": 481315,
    "actorName": "ORIOL DE OLANO CAMPRUBÍ",
    "actorId": 8169683,
    "actorShirtNumber": "41",
    "idMove": 115,
    "move": "Surt del camp",
    "min": 6,
    "sec": 0,
    "period": 4,
    "score": "0-0",
    "teamAction": false,
    "timestamp": "20251116094450",
    "licenseId": 1147407,
    "eventUuid": "360498ae-6aea-41a7-b99e-da43e2243569"
  },
  {
    "idTeam": 481315,
    "actorName": "BIEL ROGES LEZCANO",
    "actorId": 8169681,
    "actorShirtNumber": "51",
    "idMove": 115,
    "move": "Surt del camp",
    "min": 6,
    "sec": 0,
    "period": 4,
    "score": "0-0",
    "teamAction": false,
    "timestamp": "20251116094450",
    "licenseId": 1147405,
    "eventUuid": "02871751-8ef1-4732-b338-ea80076722d4"
  },
  {
    "idTeam": 481315,
    "actorName": "ROC ROBERT CORBI",
    "actorId": 8169682,
    "actorShirtNumber": "2",
    "idMove": 112,
    "move": "Entra al camp",
    "min": 6,
    "sec": 0,
    "period": 4,
    "score": "0-0",
    "teamAction": false,
    "timestamp": "20251116094450",
    "licenseId": 1147406,
    "eventUuid": "fa90ebbb-ee63-4cdb-b100-c7761ce38d97"
  },
  {
    "idTeam": 481315,
    "actorName": "OLIVER COMA DE HERRALDE",
    "actorId": 8169679,
    "actorShirtNumber": "19",
    "idMove": 112,
    "move": "Entra al camp",
    "min": 6,
    "sec": 0,
    "period": 4,
    "score": "0-0",
    "teamAction": false,
    "timestamp": "20251116094450",
    "licenseId": 1147403,
    "eventUuid": "4b89e8f3-6e94-474f-9010-c292739ea393"
  },
  {
    "idTeam": 481315,
    "actorName": "BIEL GUZMAN TORRAS",
    "actorId": 8169688,
    "actorShirtNumber": "17",
    "idMove": 112,
    "move": "Entra al camp",
    "min": 6,
    "sec": 0,
    "period": 4,
    "score": "0-0",
    "teamAction": false,
    "timestamp": "20251116094450",
    "licenseId": 1162343,
    "eventUuid": "f777dd6a-1e2a-42a1-b042-dcf2ac23dfdc"
  },
  {
    "idTeam": 481315,
    "actorName": "NIEL GIRAL FERRARONS",
    "actorId": 8169687,
    "actorShirtNumber": "6",
    "idMove": 112,
    "move": "Entra al camp",
    "min": 6,
    "sec": 0,
    "period": 4,
    "score": "0-0",
    "teamAction": false,
    "timestamp": "20251116094450",
    "licenseId": 1158003,
    "eventUuid": "c2da5187-a660-4e23-ac57-37304aad73f4"
  },
  {
    "idTeam": 481314,
    "actorName": "NIL PASCUAL GUILLÓ",
    "actorId": 8168883,
    "actorShirtNumber": "7",
    "idMove": 178,
    "move": "Salt guanyat",
    "min": 6,
    "sec": 0,
    "period": 4,
    "score": "0-0",
    "teamAction": false,
    "timestamp": "20251116094718",
    "licenseId": 1207035,
    "eventUuid": "520a33af-9436-4bcf-947d-ba5504623f5c"
  },
  {
    "idTeam": 481315,
    "actorName": "NIEL GIRAL FERRARONS",
    "actorId": 8169687,
    "actorShirtNumber": "6",
    "idMove": 179,
    "move": "Salt perdut",
    "min": 6,
    "sec": 0,
    "period": 4,
    "score": "0-0",
    "teamAction": false,
    "timestamp": "20251116094718",
    "licenseId": 1158003,
    "eventUuid": "f91b7bb5-ced8-4c26-b036-b4579c3c2f98"
  },
  {
    "idTeam": 481315,
    "actorName": "BIEL GUZMAN TORRAS",
    "actorId": 8169688,
    "actorShirtNumber": "17",
    "idMove": 161,
    "move": "Personal 2 tirs lliures, 2a falta",
    "min": 4,
    "sec": 29,
    "period": 4,
    "score": "0-0",
    "teamAction": false,
    "foulNumber": 2,
    "timestamp": "20251116094859",
    "licenseId": 1162343,
    "eventUuid": "b637fe93-4f05-4d59-906f-89d62ef26c3e"
  },
  {
    "idTeam": 481314,
    "actorName": "SERGI CALAF ROCA",
    "actorId": 8168876,
    "actorShirtNumber": "3",
    "idMove": 92,
    "move": "Cistella de 1",
    "min": 4,
    "sec": 14,
    "period": 4,
    "score": "1-0",
    "teamAction": false,
    "timestamp": "20251116094916",
    "licenseId": 1165925,
    "eventUuid": "82418882-48ef-4fc4-84f8-91325b1192dc"
  },
  {
    "idTeam": 481314,
    "actorName": "SERGI CALAF ROCA",
    "actorId": 8168876,
    "actorShirtNumber": "3",
    "idMove": 92,
    "move": "Cistella de 1",
    "min": 4,
    "sec": 14,
    "period": 4,
    "score": "2-0",
    "teamAction": false,
    "timestamp": "20251116094928",
    "licenseId": 1165925,
    "eventUuid": "7f45cf3b-c48f-450b-bf52-61b89107e8cd"
  },
  {
    "idTeam": 481314,
    "actorName": "NIL PASCUAL GUILLÓ",
    "actorId": 8168883,
    "actorShirtNumber": "7",
    "idMove": 537,
    "move": "Falta tècnica 1 tir lliure, 2a falta",
    "min": 4,
    "sec": 10,
    "period": 4,
    "score": "2-0",
    "teamAction": false,
    "foulNumber": 2,
    "timestamp": "20251116094946",
    "licenseId": 1207035,
    "eventUuid": "7921e38e-ec12-4bc7-8a33-658a15ab0a77"
  },
  {
    "idTeam": 481315,
    "actorName": "OLIVER COMA DE HERRALDE",
    "actorId": 8169679,
    "actorShirtNumber": "19",
    "idMove": 96,
    "move": "Intent fallat de 1",
    "min": 4,
    "sec": 10,
    "period": 4,
    "score": "2-0",
    "teamAction": false,
    "timestamp": "20251116095010",
    "licenseId": 1147403,
    "eventUuid": "d3d000d8-209b-4d36-98c8-6251a150eeb6"
  },
  {
    "idTeam": 481314,
    "actorName": "SERGI CALAF ROCA",
    "actorId": 8168876,
    "actorShirtNumber": "3",
    "idMove": 93,
    "move": "Cistella de 2",
    "min": 3,
    "sec": 42,
    "period": 4,
    "score": "4-0",
    "teamAction": false,
    "timestamp": "20251116095055",
    "licenseId": 1165925,
    "eventUuid": "0aac3df6-4a30-400a-be06-1b5087373626"
  },
  {
    "idTeam": 481314,
    "actorName": "NIL PASCUAL GUILLÓ",
    "actorId": 8168883,
    "actorShirtNumber": "7",
    "idMove": 93,
    "move": "Cistella de 2",
    "min": 3,
    "sec": 19,
    "period": 4,
    "score": "6-0",
    "teamAction": false,
    "timestamp": "20251116095118",
    "licenseId": 1207035,
    "eventUuid": "da6ef63b-ef82-40df-b1b1-84050381c5be"
  },
  {
    "idTeam": 481314,
    "actorName": "JAVIER CASADO MORA",
    "actorId": 8168880,
    "actorShirtNumber": "17",
    "idMove": 159,
    "move": "Personal, 1a falta",
    "min": 3,
    "sec": 3,
    "period": 4,
    "score": "6-0",
    "teamAction": false,
    "foulNumber": 1,
    "timestamp": "20251116095134",
    "licenseId": 1165929,
    "eventUuid": "7f42b06b-ddb3-4b98-8d6d-3c6f2d1aeabc"
  },
  {
    "idTeam": 481315,
    "actorName": "ROC ROBERT CORBI",
    "actorId": 8169682,
    "actorShirtNumber": "2",
    "idMove": 159,
    "move": "Personal, 1a falta",
    "min": 2,
    "sec": 28,
    "period": 4,
    "score": "6-0",
    "teamAction": false,
    "foulNumber": 1,
    "timestamp": "20251116095209",
    "licenseId": 1147406,
    "eventUuid": "acae4944-1afb-4d3b-a62d-98755fe39079"
  },
  {
    "idTeam": 481314,
    "actorName": "SERGI CALAF ROCA",
    "actorId": 8168876,
    "actorShirtNumber": "3",
    "idMove": 93,
    "move": "Cistella de 2",
    "min": 2,
    "sec": 6,
    "period": 4,
    "score": "8-0",
    "teamAction": false,
    "timestamp": "20251116095231",
    "licenseId": 1165925,
    "eventUuid": "5dd5dc73-c115-412e-8d8e-3cb022f0b5c8"
  },
  {
    "idTeam": 481314,
    "actorName": "NIL PASCUAL GUILLÓ",
    "actorId": 8168883,
    "actorShirtNumber": "7",
    "idMove": 93,
    "move": "Cistella de 2",
    "min": 0,
    "sec": 55,
    "period": 4,
    "score": "10-0",
    "teamAction": false,
    "timestamp": "20251116095343",
    "licenseId": 1207035,
    "eventUuid": "b0d1662c-955b-4d88-bd09-e1285027779e"
  },
  {
    "idTeam": 481314,
    "actorName": "NIL PASCUAL GUILLÓ",
    "actorId": 8168883,
    "actorShirtNumber": "7",
    "idMove": 161,
    "move": "Personal 2 tirs lliures, 3a falta",
    "min": 0,
    "sec": 32,
    "period": 4,
    "score": "10-0",
    "teamAction": false,
    "foulNumber": 3,
    "timestamp": "20251116095404",
    "licenseId": 1207035,
    "eventUuid": "edc077eb-79fc-4953-84bb-d644ba985c3b"
  },
  {
    "idTeam": 481315,
    "actorName": "NIEL GIRAL FERRARONS",
    "actorId": 8169687,
    "actorShirtNumber": "6",
    "idMove": 92,
    "move": "Cistella de 1",
    "min": 0,
    "sec": 28,
    "period": 4,
    "score": "10-1",
    "teamAction": false,
    "timestamp": "20251116095422",
    "licenseId": 1158003,
    "eventUuid": "a6d7d6fb-8a41-44d6-8885-b1cd615c71bf"
  },
  {
    "idTeam": 481315,
    "actorName": "NIEL GIRAL FERRARONS",
    "actorId": 8169687,
    "actorShirtNumber": "6",
    "idMove": 96,
    "move": "Intent fallat de 1",
    "min": 0,
    "sec": 28,
    "period": 4,
    "score": "10-1",
    "teamAction": false,
    "timestamp": "20251116095435",
    "licenseId": 1158003,
    "eventUuid": "73800af8-8243-4dae-882a-625050f93417"
  },
  {
    "idTeam": 0,
    "actorName": "",
    "actorId": 0,
    "actorShirtNumber": "",
    "idMove": 116,
    "move": "Final de període",
    "min": 0,
    "sec": 0,
    "period": 4,
    "score": "10-1",
    "teamAction": true,
    "timestamp": "20251116095533",
    "eventUuid": "4f76cef4-8a4d-4bef-872b-635a5c32a8fe"
  },
  {
    "idTeam": 481314,
    "actorName": "PABLO GAEL BRONCHAL TORRES",
    "actorId": 8168877,
    "actorShirtNumber": "24",
    "idMove": 115,
    "move": "Surt del camp",
    "min": 6,
    "sec": 0,
    "period": 5,
    "score": "0-0",
    "teamAction": false,
    "timestamp": "20251116095534",
    "licenseId": 1165926,
    "eventUuid": "af69c97e-b8e8-4911-956d-1f4bba26d433"
  },
  {
    "idTeam": 481314,
    "actorName": "JAVIER CASADO MORA",
    "actorId": 8168880,
    "actorShirtNumber": "17",
    "idMove": 115,
    "move": "Surt del camp",
    "min": 6,
    "sec": 0,
    "period": 5,
    "score": "0-0",
    "teamAction": false,
    "timestamp": "20251116095534",
    "licenseId": 1165929,
    "eventUuid": "acd2f573-2b62-4a0b-9d1c-d0e20273f26d"
  },
  {
    "idTeam": 481314,
    "actorName": "RAPHAEL RODIER MICHEL",
    "actorId": 8168873,
    "actorShirtNumber": "12",
    "idMove": 115,
    "move": "Surt del camp",
    "min": 6,
    "sec": 0,
    "period": 5,
    "score": "0-0",
    "teamAction": false,
    "timestamp": "20251116095534",
    "licenseId": 1165922,
    "eventUuid": "8790c2d9-64f7-428e-bb4f-79d27f0602b4"
  },
  {
    "idTeam": 481314,
    "actorName": "SERGI CALAF ROCA",
    "actorId": 8168876,
    "actorShirtNumber": "3",
    "idMove": 115,
    "move": "Surt del camp",
    "min": 6,
    "sec": 0,
    "period": 5,
    "score": "0-0",
    "teamAction": false,
    "timestamp": "20251116095534",
    "licenseId": 1165925,
    "eventUuid": "43bb9ad5-2223-4836-8999-3d574eb8dd80"
  },
  {
    "idTeam": 481314,
    "actorName": "NIL PASCUAL GUILLÓ",
    "actorId": 8168883,
    "actorShirtNumber": "7",
    "idMove": 115,
    "move": "Surt del camp",
    "min": 6,
    "sec": 0,
    "period": 5,
    "score": "0-0",
    "teamAction": false,
    "timestamp": "20251116095534",
    "licenseId": 1207035,
    "eventUuid": "c93b5a29-a7ba-4cbe-8dc3-64dad83ea8e9"
  },
  {
    "idTeam": 481314,
    "actorName": "XAVIER CATALAN VENTOSO",
    "actorId": 8168882,
    "actorShirtNumber": "15",
    "idMove": 112,
    "move": "Entra al camp",
    "min": 6,
    "sec": 0,
    "period": 5,
    "score": "0-0",
    "teamAction": false,
    "timestamp": "20251116095534",
    "licenseId": 1181289,
    "eventUuid": "322b07c5-4e51-439d-b2b9-8c3aba640d03"
  },
  {
    "idTeam": 481314,
    "actorName": "GERARD ALSINA GINESTA",
    "actorId": 8168879,
    "actorShirtNumber": "8",
    "idMove": 112,
    "move": "Entra al camp",
    "min": 6,
    "sec": 0,
    "period": 5,
    "score": "0-0",
    "teamAction": false,
    "timestamp": "20251116095534",
    "licenseId": 1165928,
    "eventUuid": "33f6f1b1-a285-41d6-aff3-634652a79ac5"
  },
  {
    "idTeam": 481314,
    "actorName": "POL GENÉ PALAÍN",
    "actorId": 8168874,
    "actorShirtNumber": "13",
    "idMove": 112,
    "move": "Entra al camp",
    "min": 6,
    "sec": 0,
    "period": 5,
    "score": "0-0",
    "teamAction": false,
    "timestamp": "20251116095534",
    "licenseId": 1165923,
    "eventUuid": "b093d74a-abc6-4445-a97f-41dac89d1958"
  },
  {
    "idTeam": 481314,
    "actorName": "TRAVIS ROJO CORBERA",
    "actorId": 8168875,
    "actorShirtNumber": "10",
    "idMove": 112,
    "move": "Entra al camp",
    "min": 6,
    "sec": 0,
    "period": 5,
    "score": "0-0",
    "teamAction": false,
    "timestamp": "20251116095534",
    "licenseId": 1165924,
    "eventUuid": "6366c6bc-cea7-40a3-8a0f-d4a129af249d"
  },
  {
    "idTeam": 481314,
    "actorName": "ARAN BUTINK ROJAS",
    "actorId": 8168872,
    "actorShirtNumber": "1",
    "idMove": 112,
    "move": "Entra al camp",
    "min": 6,
    "sec": 0,
    "period": 5,
    "score": "0-0",
    "teamAction": false,
    "timestamp": "20251116095534",
    "licenseId": 1165921,
    "eventUuid": "8b7050c0-64c3-4e23-995d-fed28d2981d5"
  },
  {
    "idTeam": 481315,
    "actorName": "ROC ROBERT CORBI",
    "actorId": 8169682,
    "actorShirtNumber": "2",
    "idMove": 115,
    "move": "Surt del camp",
    "min": 6,
    "sec": 0,
    "period": 5,
    "score": "0-0",
    "teamAction": false,
    "timestamp": "20251116095534",
    "licenseId": 1147406,
    "eventUuid": "a0131e12-84d8-4496-9c51-3c0ebbb459a8"
  },
  {
    "idTeam": 481315,
    "actorName": "BIEL GUZMAN TORRAS",
    "actorId": 8169688,
    "actorShirtNumber": "17",
    "idMove": 115,
    "move": "Surt del camp",
    "min": 6,
    "sec": 0,
    "period": 5,
    "score": "0-0",
    "teamAction": false,
    "timestamp": "20251116095534",
    "licenseId": 1162343,
    "eventUuid": "6bd508a3-2769-4123-801d-16bec21eb55d"
  },
  {
    "idTeam": 481315,
    "actorName": "NIEL GIRAL FERRARONS",
    "actorId": 8169687,
    "actorShirtNumber": "6",
    "idMove": 115,
    "move": "Surt del camp",
    "min": 6,
    "sec": 0,
    "period": 5,
    "score": "0-0",
    "teamAction": false,
    "timestamp": "20251116095534",
    "licenseId": 1158003,
    "eventUuid": "6b13cc8d-aa6f-46da-8c6c-ebab95a5d68c"
  },
  {
    "idTeam": 481315,
    "actorName": "JAN ERROZ NOVELL",
    "actorId": 8169680,
    "actorShirtNumber": "21",
    "idMove": 115,
    "move": "Surt del camp",
    "min": 6,
    "sec": 0,
    "period": 5,
    "score": "0-0",
    "teamAction": false,
    "timestamp": "20251116095534",
    "licenseId": 1147404,
    "eventUuid": "97832625-6c8c-4d99-9e31-f1ea02b0b7c6"
  },
  {
    "idTeam": 481315,
    "actorName": "SALVADOR FERNANDEZ GRANT",
    "actorId": 8169684,
    "actorShirtNumber": "18",
    "idMove": 112,
    "move": "Entra al camp",
    "min": 6,
    "sec": 0,
    "period": 5,
    "score": "0-0",
    "teamAction": false,
    "timestamp": "20251116095534",
    "licenseId": 1147408,
    "eventUuid": "4bfc9a39-317b-42bd-ac6f-32f7f8271358"
  },
  {
    "idTeam": 481315,
    "actorName": "DENIZ INALER",
    "actorId": 8169686,
    "actorShirtNumber": "10",
    "idMove": 112,
    "move": "Entra al camp",
    "min": 6,
    "sec": 0,
    "period": 5,
    "score": "0-0",
    "teamAction": false,
    "timestamp": "20251116095534",
    "licenseId": 1157963,
    "eventUuid": "4e96eff3-27fd-4cbd-9d65-25ef497e278b"
  },
  {
    "idTeam": 481315,
    "actorName": "ORIOL DE OLANO CAMPRUBÍ",
    "actorId": 8169683,
    "actorShirtNumber": "41",
    "idMove": 112,
    "move": "Entra al camp",
    "min": 6,
    "sec": 0,
    "period": 5,
    "score": "0-0",
    "teamAction": false,
    "timestamp": "20251116095534",
    "licenseId": 1147407,
    "eventUuid": "0ec85a36-34e9-4ba2-a4a9-6115c471a83a"
  },
  {
    "idTeam": 481315,
    "actorName": "BIEL ROGES LEZCANO",
    "actorId": 8169681,
    "actorShirtNumber": "51",
    "idMove": 112,
    "move": "Entra al camp",
    "min": 6,
    "sec": 0,
    "period": 5,
    "score": "0-0",
    "teamAction": false,
    "timestamp": "20251116095534",
    "licenseId": 1147405,
    "eventUuid": "aa693d53-a6d8-4c3a-ac64-2ad1d4fbab7b"
  },
  {
    "idTeam": 481315,
    "actorName": "SALVADOR FERNANDEZ GRANT",
    "actorId": 8169684,
    "actorShirtNumber": "18",
    "idMove": 178,
    "move": "Salt guanyat",
    "min": 6,
    "sec": 0,
    "period": 5,
    "score": "0-0",
    "teamAction": false,
    "timestamp": "20251116100011",
    "licenseId": 1147408,
    "eventUuid": "4a64b561-1677-4b50-8601-517a93cfa6f0"
  },
  {
    "idTeam": 481314,
    "actorName": "TRAVIS ROJO CORBERA",
    "actorId": 8168875,
    "actorShirtNumber": "10",
    "idMove": 179,
    "move": "Salt perdut",
    "min": 6,
    "sec": 0,
    "period": 5,
    "score": "0-0",
    "teamAction": false,
    "timestamp": "20251116100011",
    "licenseId": 1165924,
    "eventUuid": "5024a595-ed53-411d-8ae0-547785798965"
  },
  {
    "idTeam": 481314,
    "actorName": "ARAN BUTINK ROJAS",
    "actorId": 8168872,
    "actorShirtNumber": "1",
    "idMove": 93,
    "move": "Cistella de 2",
    "min": 6,
    "sec": 0,
    "period": 5,
    "score": "2-0",
    "teamAction": false,
    "timestamp": "20251116100111",
    "licenseId": 1165921,
    "eventUuid": "699c32d2-289c-4842-a8d5-05b535563f4f"
  },
  {
    "idTeam": 481315,
    "actorName": "SALVADOR FERNANDEZ GRANT",
    "actorId": 8169684,
    "actorShirtNumber": "18",
    "idMove": 93,
    "move": "Cistella de 2",
    "min": 6,
    "sec": 0,
    "period": 5,
    "score": "2-2",
    "teamAction": false,
    "timestamp": "20251116100132",
    "licenseId": 1147408,
    "eventUuid": "6b9b1a51-838c-4b04-9c32-1a17fbec3044"
  },
  {
    "idTeam": 481315,
    "actorName": "SALVADOR FERNANDEZ GRANT",
    "actorId": 8169684,
    "actorShirtNumber": "18",
    "idMove": 161,
    "move": "Personal 2 tirs lliures, 2a falta",
    "min": 6,
    "sec": 0,
    "period": 5,
    "score": "2-2",
    "teamAction": false,
    "foulNumber": 2,
    "timestamp": "20251116100151",
    "licenseId": 1147408,
    "eventUuid": "cea685ee-8fb1-4fa4-8d56-9aa178f2bb84"
  },
  {
    "idTeam": 481314,
    "actorName": "TRAVIS ROJO CORBERA",
    "actorId": 8168875,
    "actorShirtNumber": "10",
    "idMove": 96,
    "move": "Intent fallat de 1",
    "min": 6,
    "sec": 0,
    "period": 5,
    "score": "2-2",
    "teamAction": false,
    "timestamp": "20251116100211",
    "licenseId": 1165924,
    "eventUuid": "7beeae26-6f1a-4cbc-86d9-4896f8ef33c1"
  },
  {
    "idTeam": 481314,
    "actorName": "TRAVIS ROJO CORBERA",
    "actorId": 8168875,
    "actorShirtNumber": "10",
    "idMove": 96,
    "move": "Intent fallat de 1",
    "min": 6,
    "sec": 0,
    "period": 5,
    "score": "2-2",
    "teamAction": false,
    "timestamp": "20251116100220",
    "licenseId": 1165924,
    "eventUuid": "9384f54d-6879-4d02-8310-df73e5f12d31"
  },
  {
    "idTeam": 481314,
    "actorName": "XAVIER CATALAN VENTOSO",
    "actorId": 8168882,
    "actorShirtNumber": "15",
    "idMove": 161,
    "move": "Personal 2 tirs lliures, 2a falta",
    "min": 5,
    "sec": 46,
    "period": 5,
    "score": "2-2",
    "teamAction": false,
    "foulNumber": 2,
    "timestamp": "20251116100236",
    "licenseId": 1181289,
    "eventUuid": "1c48615b-9fac-45bf-b87c-94dd9dae652a"
  },
  {
    "idTeam": 481315,
    "actorName": "BIEL ROGES LEZCANO",
    "actorId": 8169681,
    "actorShirtNumber": "51",
    "idMove": 92,
    "move": "Cistella de 1",
    "min": 5,
    "sec": 35,
    "period": 5,
    "score": "2-3",
    "teamAction": false,
    "timestamp": "20251116100249",
    "licenseId": 1147405,
    "eventUuid": "2b022e68-ab11-4279-926f-2c84a2c08779"
  },
  {
    "idTeam": 481315,
    "actorName": "BIEL ROGES LEZCANO",
    "actorId": 8169681,
    "actorShirtNumber": "51",
    "idMove": 96,
    "move": "Intent fallat de 1",
    "min": 5,
    "sec": 35,
    "period": 5,
    "score": "2-3",
    "teamAction": false,
    "timestamp": "20251116100300",
    "licenseId": 1147405,
    "eventUuid": "73816398-cfbb-4987-b307-33cdbbfcd951"
  },
  {
    "idTeam": 481315,
    "actorName": "DENIZ INALER",
    "actorId": 8169686,
    "actorShirtNumber": "10",
    "idMove": 161,
    "move": "Personal 2 tirs lliures, 1a falta",
    "min": 4,
    "sec": 54,
    "period": 5,
    "score": "2-3",
    "teamAction": false,
    "foulNumber": 1,
    "timestamp": "20251116100343",
    "licenseId": 1157963,
    "eventUuid": "00e06b03-b27e-4595-919c-86778e39a285"
  },
  {
    "idTeam": 481314,
    "actorName": "GERARD ALSINA GINESTA",
    "actorId": 8168879,
    "actorShirtNumber": "8",
    "idMove": 92,
    "move": "Cistella de 1",
    "min": 4,
    "sec": 49,
    "period": 5,
    "score": "3-3",
    "teamAction": false,
    "timestamp": "20251116100405",
    "licenseId": 1165928,
    "eventUuid": "147e380f-10b7-4e65-9e31-cf72aaa6755b"
  },
  {
    "idTeam": 481314,
    "actorName": "GERARD ALSINA GINESTA",
    "actorId": 8168879,
    "actorShirtNumber": "8",
    "idMove": 92,
    "move": "Cistella de 1",
    "min": 4,
    "sec": 49,
    "period": 5,
    "score": "4-3",
    "teamAction": false,
    "timestamp": "20251116100421",
    "licenseId": 1165928,
    "eventUuid": "4d111810-6fda-472d-a603-3ac508110c65"
  },
  {
    "idTeam": 481315,
    "actorName": "BIEL ROGES LEZCANO",
    "actorId": 8169681,
    "actorShirtNumber": "51",
    "idMove": 537,
    "move": "Falta tècnica 1 tir lliure, 1a falta",
    "min": 4,
    "sec": 25,
    "period": 5,
    "score": "4-3",
    "teamAction": false,
    "foulNumber": 1,
    "timestamp": "20251116100446",
    "licenseId": 1147405,
    "eventUuid": "c2fb925b-6bd1-4df0-a6dc-f27034627bc2"
  },
  {
    "idTeam": 481314,
    "actorName": "ARAN BUTINK ROJAS",
    "actorId": 8168872,
    "actorShirtNumber": "1",
    "idMove": 96,
    "move": "Intent fallat de 1",
    "min": 4,
    "sec": 5,
    "period": 5,
    "score": "4-3",
    "teamAction": false,
    "timestamp": "20251116100519",
    "licenseId": 1165921,
    "eventUuid": "57435e1c-dd41-45de-8d59-ffc898d7c927"
  },
  {
    "idTeam": 481315,
    "actorName": "SALVADOR FERNANDEZ GRANT",
    "actorId": 8169684,
    "actorShirtNumber": "18",
    "idMove": 159,
    "move": "Personal, 3a falta",
    "min": 2,
    "sec": 39,
    "period": 5,
    "score": "4-3",
    "teamAction": false,
    "foulNumber": 3,
    "timestamp": "20251116100654",
    "licenseId": 1147408,
    "eventUuid": "42dc7ea3-f723-4fe7-9481-40e1ab806e28"
  },
  {
    "idTeam": 481315,
    "actorName": "DENIZ INALER",
    "actorId": 8169686,
    "actorShirtNumber": "10",
    "idMove": 93,
    "move": "Cistella de 2",
    "min": 2,
    "sec": 0,
    "period": 5,
    "score": "4-5",
    "teamAction": false,
    "timestamp": "20251116100733",
    "licenseId": 1157963,
    "eventUuid": "9a35fe56-ff2c-4f11-8ada-edb964ecb970"
  },
  {
    "idTeam": 481314,
    "actorName": "POL GENÉ PALAÍN",
    "actorId": 8168874,
    "actorShirtNumber": "13",
    "idMove": 93,
    "move": "Cistella de 2",
    "min": 1,
    "sec": 44,
    "period": 5,
    "score": "6-5",
    "teamAction": false,
    "timestamp": "20251116100749",
    "licenseId": 1165923,
    "eventUuid": "b93d374d-7e42-4bce-95c4-5593977268ce"
  },
  {
    "idTeam": 481314,
    "actorName": "POL GENÉ PALAÍN",
    "actorId": 8168874,
    "actorShirtNumber": "13",
    "idMove": 159,
    "move": "Personal, 2a falta",
    "min": 1,
    "sec": 38,
    "period": 5,
    "score": "6-5",
    "teamAction": false,
    "foulNumber": 2,
    "timestamp": "20251116100755",
    "licenseId": 1165923,
    "eventUuid": "fabd5543-d4df-4f6b-a31d-fc135767b30b"
  },
  {
    "idTeam": 481315,
    "actorName": "SALVADOR FERNANDEZ GRANT",
    "actorId": 8169684,
    "actorShirtNumber": "18",
    "idMove": 159,
    "move": "Personal, 4a falta",
    "min": 0,
    "sec": 58,
    "period": 5,
    "score": "6-5",
    "teamAction": false,
    "foulNumber": 4,
    "timestamp": "20251116100835",
    "licenseId": 1147408,
    "eventUuid": "3ff5cc9c-fbd5-4644-b786-07bc6b0ac5be"
  },
  {
    "idTeam": 0,
    "actorName": "",
    "actorId": 0,
    "actorShirtNumber": "",
    "idMove": 116,
    "move": "Final de període",
    "min": 0,
    "sec": 0,
    "period": 5,
    "score": "6-5",
    "teamAction": true,
    "timestamp": "20251116100950",
    "eventUuid": "3121b028-d17a-4266-ab85-7e3419189c1c"
  },
  {
    "idTeam": 481314,
    "actorName": "XAVIER CATALAN VENTOSO",
    "actorId": 8168882,
    "actorShirtNumber": "15",
    "idMove": 115,
    "move": "Surt del camp",
    "min": 6,
    "sec": 0,
    "period": 6,
    "score": "0-0",
    "teamAction": false,
    "timestamp": "20251116100950",
    "licenseId": 1181289,
    "eventUuid": "28242798-f944-4a83-abb6-64fd990e94fb"
  },
  {
    "idTeam": 481314,
    "actorName": "GERARD ALSINA GINESTA",
    "actorId": 8168879,
    "actorShirtNumber": "8",
    "idMove": 115,
    "move": "Surt del camp",
    "min": 6,
    "sec": 0,
    "period": 6,
    "score": "0-0",
    "teamAction": false,
    "timestamp": "20251116100950",
    "licenseId": 1165928,
    "eventUuid": "0ae4e19b-5596-4636-a22d-e5b533445a22"
  },
  {
    "idTeam": 481314,
    "actorName": "POL GENÉ PALAÍN",
    "actorId": 8168874,
    "actorShirtNumber": "13",
    "idMove": 115,
    "move": "Surt del camp",
    "min": 6,
    "sec": 0,
    "period": 6,
    "score": "0-0",
    "teamAction": false,
    "timestamp": "20251116100950",
    "licenseId": 1165923,
    "eventUuid": "2582440b-8ddb-4762-820b-d5574f3e5ca3"
  },
  {
    "idTeam": 481314,
    "actorName": "TRAVIS ROJO CORBERA",
    "actorId": 8168875,
    "actorShirtNumber": "10",
    "idMove": 115,
    "move": "Surt del camp",
    "min": 6,
    "sec": 0,
    "period": 6,
    "score": "0-0",
    "teamAction": false,
    "timestamp": "20251116100950",
    "licenseId": 1165924,
    "eventUuid": "7d91555e-2159-432d-ba46-086078496335"
  },
  {
    "idTeam": 481314,
    "actorName": "ARAN BUTINK ROJAS",
    "actorId": 8168872,
    "actorShirtNumber": "1",
    "idMove": 115,
    "move": "Surt del camp",
    "min": 6,
    "sec": 0,
    "period": 6,
    "score": "0-0",
    "teamAction": false,
    "timestamp": "20251116100950",
    "licenseId": 1165921,
    "eventUuid": "23679b39-feb8-47b1-9132-60364274686d"
  },
  {
    "idTeam": 481314,
    "actorName": "PABLO GAEL BRONCHAL TORRES",
    "actorId": 8168877,
    "actorShirtNumber": "24",
    "idMove": 112,
    "move": "Entra al camp",
    "min": 6,
    "sec": 0,
    "period": 6,
    "score": "0-0",
    "teamAction": false,
    "timestamp": "20251116100950",
    "licenseId": 1165926,
    "eventUuid": "995d8ccb-5fc4-4ce9-9e97-3cb27be1d6fe"
  },
  {
    "idTeam": 481314,
    "actorName": "RAPHAEL RODIER MICHEL",
    "actorId": 8168873,
    "actorShirtNumber": "12",
    "idMove": 112,
    "move": "Entra al camp",
    "min": 6,
    "sec": 0,
    "period": 6,
    "score": "0-0",
    "teamAction": false,
    "timestamp": "20251116100950",
    "licenseId": 1165922,
    "eventUuid": "3a8a5c47-d1c2-4d5b-8cb3-5f8e1a90963f"
  },
  {
    "idTeam": 481314,
    "actorName": "SERGI CALAF ROCA",
    "actorId": 8168876,
    "actorShirtNumber": "3",
    "idMove": 112,
    "move": "Entra al camp",
    "min": 6,
    "sec": 0,
    "period": 6,
    "score": "0-0",
    "teamAction": false,
    "timestamp": "20251116100950",
    "licenseId": 1165925,
    "eventUuid": "4727f4ff-e3a3-4029-be5c-08f54719914c"
  },
  {
    "idTeam": 481314,
    "actorName": "JAVIER CASADO MORA",
    "actorId": 8168880,
    "actorShirtNumber": "17",
    "idMove": 112,
    "move": "Entra al camp",
    "min": 6,
    "sec": 0,
    "period": 6,
    "score": "0-0",
    "teamAction": false,
    "timestamp": "20251116100950",
    "licenseId": 1165929,
    "eventUuid": "27a75c8d-47d7-4e42-9cfd-82f41d250ab8"
  },
  {
    "idTeam": 481314,
    "actorName": "NIL PASCUAL GUILLÓ",
    "actorId": 8168883,
    "actorShirtNumber": "7",
    "idMove": 112,
    "move": "Entra al camp",
    "min": 6,
    "sec": 0,
    "period": 6,
    "score": "0-0",
    "teamAction": false,
    "timestamp": "20251116100950",
    "licenseId": 1207035,
    "eventUuid": "c507c351-45fe-48b5-aedb-d9bca18b242e"
  },
  {
    "idTeam": 481315,
    "actorName": "SALVADOR FERNANDEZ GRANT",
    "actorId": 8169684,
    "actorShirtNumber": "18",
    "idMove": 115,
    "move": "Surt del camp",
    "min": 6,
    "sec": 0,
    "period": 6,
    "score": "0-0",
    "teamAction": false,
    "timestamp": "20251116100950",
    "licenseId": 1147408,
    "eventUuid": "cebb7401-69fe-4798-b0dc-9840a36f7554"
  },
  {
    "idTeam": 481315,
    "actorName": "OLIVER COMA DE HERRALDE",
    "actorId": 8169679,
    "actorShirtNumber": "19",
    "idMove": 115,
    "move": "Surt del camp",
    "min": 6,
    "sec": 0,
    "period": 6,
    "score": "0-0",
    "teamAction": false,
    "timestamp": "20251116100950",
    "licenseId": 1147403,
    "eventUuid": "45a03b66-f56d-4ba3-9a0a-7e4aa4994924"
  },
  {
    "idTeam": 481315,
    "actorName": "DENIZ INALER",
    "actorId": 8169686,
    "actorShirtNumber": "10",
    "idMove": 115,
    "move": "Surt del camp",
    "min": 6,
    "sec": 0,
    "period": 6,
    "score": "0-0",
    "teamAction": false,
    "timestamp": "20251116100950",
    "licenseId": 1157963,
    "eventUuid": "620e1700-23fb-4358-b7ab-0d0868407959"
  },
  {
    "idTeam": 481315,
    "actorName": "ORIOL DE OLANO CAMPRUBÍ",
    "actorId": 8169683,
    "actorShirtNumber": "41",
    "idMove": 115,
    "move": "Surt del camp",
    "min": 6,
    "sec": 0,
    "period": 6,
    "score": "0-0",
    "teamAction": false,
    "timestamp": "20251116100950",
    "licenseId": 1147407,
    "eventUuid": "9869cb4d-0974-4c6e-a5f5-96034f12b238"
  },
  {
    "idTeam": 481315,
    "actorName": "ROC ROBERT CORBI",
    "actorId": 8169682,
    "actorShirtNumber": "2",
    "idMove": 112,
    "move": "Entra al camp",
    "min": 6,
    "sec": 0,
    "period": 6,
    "score": "0-0",
    "teamAction": false,
    "timestamp": "20251116100950",
    "licenseId": 1147406,
    "eventUuid": "9b96204b-5f12-4cbc-86de-2ef3e88c2786"
  },
  {
    "idTeam": 481315,
    "actorName": "BIEL GUZMAN TORRAS",
    "actorId": 8169688,
    "actorShirtNumber": "17",
    "idMove": 112,
    "move": "Entra al camp",
    "min": 6,
    "sec": 0,
    "period": 6,
    "score": "0-0",
    "teamAction": false,
    "timestamp": "20251116100950",
    "licenseId": 1162343,
    "eventUuid": "65e092dc-0ab4-4ae0-826b-7c3a77320fe6"
  },
  {
    "idTeam": 481315,
    "actorName": "NIEL GIRAL FERRARONS",
    "actorId": 8169687,
    "actorShirtNumber": "6",
    "idMove": 112,
    "move": "Entra al camp",
    "min": 6,
    "sec": 0,
    "period": 6,
    "score": "0-0",
    "teamAction": false,
    "timestamp": "20251116100950",
    "licenseId": 1158003,
    "eventUuid": "d3b01b8a-905d-4ee9-83ad-7b412b078d6f"
  },
  {
    "idTeam": 481315,
    "actorName": "JAN ERROZ NOVELL",
    "actorId": 8169680,
    "actorShirtNumber": "21",
    "idMove": 112,
    "move": "Entra al camp",
    "min": 6,
    "sec": 0,
    "period": 6,
    "score": "0-0",
    "teamAction": false,
    "timestamp": "20251116100950",
    "licenseId": 1147404,
    "eventUuid": "65f77c94-3f64-4b87-9691-4225c7e832d6"
  },
  {
    "idTeam": 481315,
    "actorName": "NIEL GIRAL FERRARONS",
    "actorId": 8169687,
    "actorShirtNumber": "6",
    "idMove": 178,
    "move": "Salt guanyat",
    "min": 6,
    "sec": 0,
    "period": 6,
    "score": "0-0",
    "teamAction": false,
    "timestamp": "20251116101144",
    "licenseId": 1158003,
    "eventUuid": "b5df905c-2b04-4baa-9be9-37087490e6a7"
  },
  {
    "idTeam": 481314,
    "actorName": "NIL PASCUAL GUILLÓ",
    "actorId": 8168883,
    "actorShirtNumber": "7",
    "idMove": 179,
    "move": "Salt perdut",
    "min": 6,
    "sec": 0,
    "period": 6,
    "score": "0-0",
    "teamAction": false,
    "timestamp": "20251116101144",
    "licenseId": 1207035,
    "eventUuid": "32ed17f0-dcdb-41ae-8903-e652f1b4a1ee"
  },
  {
    "idTeam": 481314,
    "actorName": "RAPHAEL RODIER MICHEL",
    "actorId": 8168873,
    "actorShirtNumber": "12",
    "idMove": 167,
    "move": "Antiesportiva 3 tirs lliures, 1a falta",
    "min": 6,
    "sec": 0,
    "period": 6,
    "score": "0-0",
    "teamAction": false,
    "foulNumber": 1,
    "timestamp": "20251116101245",
    "licenseId": 1165922,
    "eventUuid": "fe177e61-36a4-4abe-86e6-c89eb6bb5d89"
  },
  {
    "idTeam": 481315,
    "actorName": "ROC ROBERT CORBI",
    "actorId": 8169682,
    "actorShirtNumber": "2",
    "idMove": 96,
    "move": "Intent fallat de 1",
    "min": 6,
    "sec": 0,
    "period": 6,
    "score": "0-0",
    "teamAction": false,
    "timestamp": "20251116101312",
    "licenseId": 1147406,
    "eventUuid": "d972e9cd-e93f-4f25-928d-2ba4ab492e72"
  },
  {
    "idTeam": 481315,
    "actorName": "ROC ROBERT CORBI",
    "actorId": 8169682,
    "actorShirtNumber": "2",
    "idMove": 96,
    "move": "Intent fallat de 1",
    "min": 6,
    "sec": 0,
    "period": 6,
    "score": "0-0",
    "teamAction": false,
    "timestamp": "20251116101328",
    "licenseId": 1147406,
    "eventUuid": "09d7d702-b904-478d-bcfa-69bf5843c5e7"
  },
  {
    "idTeam": 481315,
    "actorName": "ROC ROBERT CORBI",
    "actorId": 8169682,
    "actorShirtNumber": "2",
    "idMove": 96,
    "move": "Intent fallat de 1",
    "min": 6,
    "sec": 0,
    "period": 6,
    "score": "0-0",
    "teamAction": false,
    "timestamp": "20251116101342",
    "licenseId": 1147406,
    "eventUuid": "4a2cf77c-f770-4504-a167-3c6f42d1cff8"
  },
  {
    "idTeam": 481315,
    "actorName": "NIEL GIRAL FERRARONS",
    "actorId": 8169687,
    "actorShirtNumber": "6",
    "idMove": 159,
    "move": "Personal, 2a falta",
    "min": 5,
    "sec": 28,
    "period": 6,
    "score": "0-0",
    "teamAction": false,
    "foulNumber": 2,
    "timestamp": "20251116101419",
    "licenseId": 1158003,
    "eventUuid": "b85e3cf5-f1d8-4a5f-8845-197995ce414e"
  },
  {
    "idTeam": 481314,
    "actorName": "PABLO GAEL BRONCHAL TORRES",
    "actorId": 8168877,
    "actorShirtNumber": "24",
    "idMove": 93,
    "move": "Cistella de 2",
    "min": 5,
    "sec": 1,
    "period": 6,
    "score": "2-0",
    "teamAction": false,
    "timestamp": "20251116101447",
    "licenseId": 1165926,
    "eventUuid": "94e3e8eb-2ee1-42ff-8dc7-fc8d95f65fc6"
  },
  {
    "idTeam": 481314,
    "actorName": "RAPHAEL RODIER MICHEL",
    "actorId": 8168873,
    "actorShirtNumber": "12",
    "idMove": 159,
    "move": "Personal, 2a falta",
    "min": 4,
    "sec": 7,
    "period": 6,
    "score": "2-0",
    "teamAction": false,
    "foulNumber": 2,
    "timestamp": "20251116101540",
    "licenseId": 1165922,
    "eventUuid": "4454187f-d588-41a6-97b7-bae0f68f872b"
  },
  {
    "idTeam": 481314,
    "actorName": "NIL PASCUAL GUILLÓ",
    "actorId": 8168883,
    "actorShirtNumber": "7",
    "idMove": 161,
    "move": "Personal 2 tirs lliures, 4a falta",
    "min": 3,
    "sec": 5,
    "period": 6,
    "score": "2-0",
    "teamAction": false,
    "foulNumber": 4,
    "timestamp": "20251116101642",
    "licenseId": 1207035,
    "eventUuid": "28a6d435-e5d1-449a-ac2d-e35a1e95cf61"
  },
  {
    "idTeam": 481315,
    "actorName": "NIEL GIRAL FERRARONS",
    "actorId": 8169687,
    "actorShirtNumber": "6",
    "idMove": 96,
    "move": "Intent fallat de 1",
    "min": 2,
    "sec": 50,
    "period": 6,
    "score": "2-0",
    "teamAction": false,
    "timestamp": "20251116101659",
    "licenseId": 1158003,
    "eventUuid": "fe243683-dd42-4181-946e-ff46b5ade1ec"
  },
  {
    "idTeam": 481315,
    "actorName": "NIEL GIRAL FERRARONS",
    "actorId": 8169687,
    "actorShirtNumber": "6",
    "idMove": 92,
    "move": "Cistella de 1",
    "min": 2,
    "sec": 50,
    "period": 6,
    "score": "2-1",
    "teamAction": false,
    "timestamp": "20251116101723",
    "licenseId": 1158003,
    "eventUuid": "640a483d-f400-4592-a99e-53abb0dd5392"
  },
  {
    "idTeam": 481314,
    "actorName": "VEDRUNA GRÀCIA NEGRE",
    "actorId": 0,
    "actorShirtNumber": "",
    "idMove": 113,
    "move": "Temps mort",
    "min": 2,
    "sec": 49,
    "period": 6,
    "score": "2-1",
    "teamAction": true,
    "timestamp": "20251116101726",
    "eventUuid": "3f02e1fb-3571-473c-aaea-475fae488571"
  },
  {
    "idTeam": 481315,
    "actorName": "NIEL GIRAL FERRARONS",
    "actorId": 8169687,
    "actorShirtNumber": "6",
    "idMove": 161,
    "move": "Personal 2 tirs lliures, 3a falta",
    "min": 1,
    "sec": 41,
    "period": 6,
    "score": "2-1",
    "teamAction": false,
    "foulNumber": 3,
    "timestamp": "20251116102010",
    "licenseId": 1158003,
    "eventUuid": "ed29f042-ec68-43c2-8170-869a7302577f"
  },
  {
    "idTeam": 481314,
    "actorName": "JAVIER CASADO MORA",
    "actorId": 8168880,
    "actorShirtNumber": "17",
    "idMove": 96,
    "move": "Intent fallat de 1",
    "min": 1,
    "sec": 36,
    "period": 6,
    "score": "2-1",
    "teamAction": false,
    "timestamp": "20251116102037",
    "licenseId": 1165929,
    "eventUuid": "3bb9e817-112e-40fb-94d6-23adf5ae0c9b"
  },
  {
    "idTeam": 481314,
    "actorName": "JAVIER CASADO MORA",
    "actorId": 8168880,
    "actorShirtNumber": "17",
    "idMove": 96,
    "move": "Intent fallat de 1",
    "min": 1,
    "sec": 36,
    "period": 6,
    "score": "2-1",
    "teamAction": false,
    "timestamp": "20251116102041",
    "licenseId": 1165929,
    "eventUuid": "4c7db376-9c2d-4a5d-b210-d0da28817e52"
  },
  {
    "idTeam": 481314,
    "actorName": "PABLO GAEL BRONCHAL TORRES",
    "actorId": 8168877,
    "actorShirtNumber": "24",
    "idMove": 93,
    "move": "Cistella de 2",
    "min": 1,
    "sec": 30,
    "period": 6,
    "score": "4-1",
    "teamAction": false,
    "timestamp": "20251116102050",
    "licenseId": 1165926,
    "eventUuid": "51c0e5e0-dd51-41e8-bbf6-632513a2aefe"
  },
  {
    "idTeam": 481314,
    "actorName": "PABLO GAEL BRONCHAL TORRES",
    "actorId": 8168877,
    "actorShirtNumber": "24",
    "idMove": 93,
    "move": "Cistella de 2",
    "min": 0,
    "sec": 56,
    "period": 6,
    "score": "6-1",
    "teamAction": false,
    "timestamp": "20251116102123",
    "licenseId": 1165926,
    "eventUuid": "eec4871c-bcb6-4337-8ee3-ea13f668ee8e"
  },
  {
    "idTeam": 481315,
    "actorName": "NIEL GIRAL FERRARONS",
    "actorId": 8169687,
    "actorShirtNumber": "6",
    "idMove": 161,
    "move": "Personal 2 tirs lliures, 4a falta",
    "min": 0,
    "sec": 32,
    "period": 6,
    "score": "6-1",
    "teamAction": false,
    "foulNumber": 4,
    "timestamp": "20251116102148",
    "licenseId": 1158003,
    "eventUuid": "c550a610-8a39-43db-9696-2c188359b5e4"
  },
  {
    "idTeam": 481314,
    "actorName": "NIL PASCUAL GUILLÓ",
    "actorId": 8168883,
    "actorShirtNumber": "7",
    "idMove": 96,
    "move": "Intent fallat de 1",
    "min": 0,
    "sec": 21,
    "period": 6,
    "score": "6-1",
    "teamAction": false,
    "timestamp": "20251116102215",
    "licenseId": 1207035,
    "eventUuid": "974816ca-76d6-438a-b4ce-61138c63d1bd"
  },
  {
    "idTeam": 481314,
    "actorName": "NIL PASCUAL GUILLÓ",
    "actorId": 8168883,
    "actorShirtNumber": "7",
    "idMove": 96,
    "move": "Intent fallat de 1",
    "min": 0,
    "sec": 21,
    "period": 6,
    "score": "6-1",
    "teamAction": false,
    "timestamp": "20251116102223",
    "licenseId": 1207035,
    "eventUuid": "3f04a51d-a649-4dc5-88b0-bcd153833d55"
  },
  {
    "idTeam": 0,
    "actorName": "",
    "actorId": 0,
    "actorShirtNumber": "",
    "idMove": 116,
    "move": "Final de període",
    "min": 0,
    "sec": 0,
    "period": 6,
    "score": "6-1",
    "teamAction": true,
    "timestamp": "20251116102308",
    "eventUuid": "b4a4f2c9-211b-484e-87c3-6fe7b1f38bdb"
  },
  {
    "idTeam": 481314,
    "actorName": "PABLO GAEL BRONCHAL TORRES",
    "actorId": 8168877,
    "actorShirtNumber": "24",
    "idMove": 115,
    "move": "Surt del camp",
    "min": 6,
    "sec": 0,
    "period": 7,
    "score": "0-0",
    "teamAction": false,
    "timestamp": "20251116102442",
    "licenseId": 1165926,
    "eventUuid": "5be65647-08c5-4f78-98f8-bdfd67e5e22f"
  },
  {
    "idTeam": 481314,
    "actorName": "RAPHAEL RODIER MICHEL",
    "actorId": 8168873,
    "actorShirtNumber": "12",
    "idMove": 115,
    "move": "Surt del camp",
    "min": 6,
    "sec": 0,
    "period": 7,
    "score": "0-0",
    "teamAction": false,
    "timestamp": "20251116102442",
    "licenseId": 1165922,
    "eventUuid": "68ccbabe-b829-4978-943c-bd7f72623332"
  },
  {
    "idTeam": 481314,
    "actorName": "SERGI CALAF ROCA",
    "actorId": 8168876,
    "actorShirtNumber": "3",
    "idMove": 115,
    "move": "Surt del camp",
    "min": 6,
    "sec": 0,
    "period": 7,
    "score": "0-0",
    "teamAction": false,
    "timestamp": "20251116102442",
    "licenseId": 1165925,
    "eventUuid": "b7dc2476-f352-438f-905e-b0441061fbd1"
  },
  {
    "idTeam": 481314,
    "actorName": "JAVIER CASADO MORA",
    "actorId": 8168880,
    "actorShirtNumber": "17",
    "idMove": 115,
    "move": "Surt del camp",
    "min": 6,
    "sec": 0,
    "period": 7,
    "score": "0-0",
    "teamAction": false,
    "timestamp": "20251116102442",
    "licenseId": 1165929,
    "eventUuid": "60c04c07-0cae-46e2-9dd7-5fa07f0cab29"
  },
  {
    "idTeam": 481314,
    "actorName": "NIL PASCUAL GUILLÓ",
    "actorId": 8168883,
    "actorShirtNumber": "7",
    "idMove": 115,
    "move": "Surt del camp",
    "min": 6,
    "sec": 0,
    "period": 7,
    "score": "0-0",
    "teamAction": false,
    "timestamp": "20251116102442",
    "licenseId": 1207035,
    "eventUuid": "1633f263-1f55-4184-bb4e-c1437a0d635e"
  },
  {
    "idTeam": 481314,
    "actorName": "XAVIER CATALAN VENTOSO",
    "actorId": 8168882,
    "actorShirtNumber": "15",
    "idMove": 112,
    "move": "Entra al camp",
    "min": 6,
    "sec": 0,
    "period": 7,
    "score": "0-0",
    "teamAction": false,
    "timestamp": "20251116102442",
    "licenseId": 1181289,
    "eventUuid": "0b42d764-210f-4f80-83ce-084602344bc6"
  },
  {
    "idTeam": 481314,
    "actorName": "GERARD ALSINA GINESTA",
    "actorId": 8168879,
    "actorShirtNumber": "8",
    "idMove": 112,
    "move": "Entra al camp",
    "min": 6,
    "sec": 0,
    "period": 7,
    "score": "0-0",
    "teamAction": false,
    "timestamp": "20251116102442",
    "licenseId": 1165928,
    "eventUuid": "bccd005b-30c2-4678-aa9b-09c82f9d2a89"
  },
  {
    "idTeam": 481314,
    "actorName": "POL GENÉ PALAÍN",
    "actorId": 8168874,
    "actorShirtNumber": "13",
    "idMove": 112,
    "move": "Entra al camp",
    "min": 6,
    "sec": 0,
    "period": 7,
    "score": "0-0",
    "teamAction": false,
    "timestamp": "20251116102442",
    "licenseId": 1165923,
    "eventUuid": "bb6bba3f-d228-4f76-8f26-7fc9c8cdaf07"
  },
  {
    "idTeam": 481314,
    "actorName": "TRAVIS ROJO CORBERA",
    "actorId": 8168875,
    "actorShirtNumber": "10",
    "idMove": 112,
    "move": "Entra al camp",
    "min": 6,
    "sec": 0,
    "period": 7,
    "score": "0-0",
    "teamAction": false,
    "timestamp": "20251116102442",
    "licenseId": 1165924,
    "eventUuid": "9b5f60fd-72d6-4af8-b632-3ec0f49250f2"
  },
  {
    "idTeam": 481314,
    "actorName": "ARAN BUTINK ROJAS",
    "actorId": 8168872,
    "actorShirtNumber": "1",
    "idMove": 112,
    "move": "Entra al camp",
    "min": 6,
    "sec": 0,
    "period": 7,
    "score": "0-0",
    "teamAction": false,
    "timestamp": "20251116102442",
    "licenseId": 1165921,
    "eventUuid": "d8f7a0c7-cf60-4b6c-af89-cfd6eaf4a2bf"
  },
  {
    "idTeam": 481315,
    "actorName": "BIEL GUZMAN TORRAS",
    "actorId": 8169688,
    "actorShirtNumber": "17",
    "idMove": 115,
    "move": "Surt del camp",
    "min": 6,
    "sec": 0,
    "period": 7,
    "score": "0-0",
    "teamAction": false,
    "timestamp": "20251116102442",
    "licenseId": 1162343,
    "eventUuid": "9144cb17-80fc-4f3f-b1d5-cf72154ed610"
  },
  {
    "idTeam": 481315,
    "actorName": "NIEL GIRAL FERRARONS",
    "actorId": 8169687,
    "actorShirtNumber": "6",
    "idMove": 115,
    "move": "Surt del camp",
    "min": 6,
    "sec": 0,
    "period": 7,
    "score": "0-0",
    "teamAction": false,
    "timestamp": "20251116102442",
    "licenseId": 1158003,
    "eventUuid": "7aff0956-edd4-40ff-acc4-cf5b038ea5c1"
  },
  {
    "idTeam": 481315,
    "actorName": "JAN ERROZ NOVELL",
    "actorId": 8169680,
    "actorShirtNumber": "21",
    "idMove": 115,
    "move": "Surt del camp",
    "min": 6,
    "sec": 0,
    "period": 7,
    "score": "0-0",
    "teamAction": false,
    "timestamp": "20251116102442",
    "licenseId": 1147404,
    "eventUuid": "e5646230-141f-4b4a-96b0-93d4747cae7f"
  },
  {
    "idTeam": 481315,
    "actorName": "BIEL ROGES LEZCANO",
    "actorId": 8169681,
    "actorShirtNumber": "51",
    "idMove": 115,
    "move": "Surt del camp",
    "min": 6,
    "sec": 0,
    "period": 7,
    "score": "0-0",
    "teamAction": false,
    "timestamp": "20251116102442",
    "licenseId": 1147405,
    "eventUuid": "f2c810ff-b074-4cef-a2fe-4d144f571633"
  },
  {
    "idTeam": 481315,
    "actorName": "SALVADOR FERNANDEZ GRANT",
    "actorId": 8169684,
    "actorShirtNumber": "18",
    "idMove": 112,
    "move": "Entra al camp",
    "min": 6,
    "sec": 0,
    "period": 7,
    "score": "0-0",
    "teamAction": false,
    "timestamp": "20251116102442",
    "licenseId": 1147408,
    "eventUuid": "2140d843-f62a-4035-afd9-5bc8230aa82f"
  },
  {
    "idTeam": 481315,
    "actorName": "DENIZ INALER",
    "actorId": 8169686,
    "actorShirtNumber": "10",
    "idMove": 112,
    "move": "Entra al camp",
    "min": 6,
    "sec": 0,
    "period": 7,
    "score": "0-0",
    "teamAction": false,
    "timestamp": "20251116102442",
    "licenseId": 1157963,
    "eventUuid": "51f689da-1188-4eec-9f06-dad9df3f533a"
  },
  {
    "idTeam": 481315,
    "actorName": "ORIOL DE OLANO CAMPRUBÍ",
    "actorId": 8169683,
    "actorShirtNumber": "41",
    "idMove": 112,
    "move": "Entra al camp",
    "min": 6,
    "sec": 0,
    "period": 7,
    "score": "0-0",
    "teamAction": false,
    "timestamp": "20251116102442",
    "licenseId": 1147407,
    "eventUuid": "aa5c9679-fda8-49ec-a5a1-d4040237a33e"
  },
  {
    "idTeam": 481315,
    "actorName": "OLIVER COMA DE HERRALDE",
    "actorId": 8169679,
    "actorShirtNumber": "19",
    "idMove": 112,
    "move": "Entra al camp",
    "min": 6,
    "sec": 0,
    "period": 7,
    "score": "0-0",
    "teamAction": false,
    "timestamp": "20251116102442",
    "licenseId": 1147403,
    "eventUuid": "14361707-65fa-4f87-9d83-0b1fa5d70c01"
  },
  {
    "idTeam": 481315,
    "actorName": "SALVADOR FERNANDEZ GRANT",
    "actorId": 8169684,
    "actorShirtNumber": "18",
    "idMove": 178,
    "move": "Salt guanyat",
    "min": 6,
    "sec": 0,
    "period": 7,
    "score": "0-0",
    "teamAction": false,
    "timestamp": "20251116102522",
    "licenseId": 1147408,
    "eventUuid": "f3f3ca95-3ecb-4d01-9772-646cfe78e34c"
  },
  {
    "idTeam": 481314,
    "actorName": "TRAVIS ROJO CORBERA",
    "actorId": 8168875,
    "actorShirtNumber": "10",
    "idMove": 179,
    "move": "Salt perdut",
    "min": 6,
    "sec": 0,
    "period": 7,
    "score": "0-0",
    "teamAction": false,
    "timestamp": "20251116102522",
    "licenseId": 1165924,
    "eventUuid": "61ac85c7-cdb2-4e9d-97ac-369bd96a0ab1"
  },
  {
    "idTeam": 481314,
    "actorName": "ARAN BUTINK ROJAS",
    "actorId": 8168872,
    "actorShirtNumber": "1",
    "idMove": 93,
    "move": "Cistella de 2",
    "min": 5,
    "sec": 47,
    "period": 7,
    "score": "2-0",
    "teamAction": false,
    "timestamp": "20251116102541",
    "licenseId": 1165921,
    "eventUuid": "2ea6ca23-49f8-4aed-aee4-e6d0380a04b2"
  },
  {
    "idTeam": 481314,
    "actorName": "GERARD ALSINA GINESTA",
    "actorId": 8168879,
    "actorShirtNumber": "8",
    "idMove": 93,
    "move": "Cistella de 2",
    "min": 5,
    "sec": 10,
    "period": 7,
    "score": "4-0",
    "teamAction": false,
    "timestamp": "20251116102618",
    "licenseId": 1165928,
    "eventUuid": "c590b382-89ce-4e08-b2d8-ec3bbbad907c"
  },
  {
    "idTeam": 481315,
    "actorName": "OLIVER COMA DE HERRALDE",
    "actorId": 8169679,
    "actorShirtNumber": "19",
    "idMove": 93,
    "move": "Cistella de 2",
    "min": 4,
    "sec": 38,
    "period": 7,
    "score": "4-2",
    "teamAction": false,
    "timestamp": "20251116102650",
    "licenseId": 1147403,
    "eventUuid": "6efb2e2a-4240-4219-8f14-ea0f09592abe"
  },
  {
    "idTeam": 481315,
    "actorName": "ROC ROBERT CORBI",
    "actorId": 8169682,
    "actorShirtNumber": "2",
    "idMove": 161,
    "move": "Personal 2 tirs lliures, 2a falta",
    "min": 2,
    "sec": 56,
    "period": 7,
    "score": "4-2",
    "teamAction": false,
    "foulNumber": 2,
    "timestamp": "20251116102833",
    "licenseId": 1147406,
    "eventUuid": "f7a6627b-f93d-4012-8204-e9bbb12d983b"
  },
  {
    "idTeam": 481314,
    "actorName": "GERARD ALSINA GINESTA",
    "actorId": 8168879,
    "actorShirtNumber": "8",
    "idMove": 96,
    "move": "Intent fallat de 1",
    "min": 2,
    "sec": 49,
    "period": 7,
    "score": "4-2",
    "teamAction": false,
    "timestamp": "20251116102843",
    "licenseId": 1165928,
    "eventUuid": "dd6b2c25-4db8-4d0a-9be6-cc9747c804d4"
  },
  {
    "idTeam": 481314,
    "actorName": "GERARD ALSINA GINESTA",
    "actorId": 8168879,
    "actorShirtNumber": "8",
    "idMove": 92,
    "move": "Cistella de 1",
    "min": 2,
    "sec": 49,
    "period": 7,
    "score": "5-2",
    "teamAction": false,
    "timestamp": "20251116102903",
    "licenseId": 1165928,
    "eventUuid": "fb87fe8d-2e6c-476f-8f72-b772e1c765df"
  },
  {
    "idTeam": 481315,
    "actorName": "ORIOL DE OLANO CAMPRUBÍ",
    "actorId": 8169683,
    "actorShirtNumber": "41",
    "idMove": 93,
    "move": "Cistella de 2",
    "min": 2,
    "sec": 32,
    "period": 7,
    "score": "5-4",
    "teamAction": false,
    "timestamp": "20251116102922",
    "licenseId": 1147407,
    "eventUuid": "3f37cfb8-dab9-4b15-832d-bf9e10969b77"
  },
  {
    "idTeam": 481315,
    "actorName": "DENIZ INALER",
    "actorId": 8169686,
    "actorShirtNumber": "10",
    "idMove": 161,
    "move": "Personal 2 tirs lliures, 2a falta",
    "min": 1,
    "sec": 41,
    "period": 7,
    "score": "5-4",
    "teamAction": false,
    "foulNumber": 2,
    "timestamp": "20251116103013",
    "licenseId": 1157963,
    "eventUuid": "b4df7140-3e64-434c-a537-2295496e78de"
  },
  {
    "idTeam": 481314,
    "actorName": "XAVIER CATALAN VENTOSO",
    "actorId": 8168882,
    "actorShirtNumber": "15",
    "idMove": 96,
    "move": "Intent fallat de 1",
    "min": 1,
    "sec": 37,
    "period": 7,
    "score": "5-4",
    "teamAction": false,
    "timestamp": "20251116103048",
    "licenseId": 1181289,
    "eventUuid": "b0884cb5-73ef-4679-b1da-eeac297ea44f"
  },
  {
    "idTeam": 481314,
    "actorName": "XAVIER CATALAN VENTOSO",
    "actorId": 8168882,
    "actorShirtNumber": "15",
    "idMove": 96,
    "move": "Intent fallat de 1",
    "min": 1,
    "sec": 37,
    "period": 7,
    "score": "5-4",
    "teamAction": false,
    "timestamp": "20251116103104",
    "licenseId": 1181289,
    "eventUuid": "2f559f93-3168-424b-aa98-accd67d0b1d4"
  },
  {
    "idTeam": 481314,
    "actorName": "ARAN BUTINK ROJAS",
    "actorId": 8168872,
    "actorShirtNumber": "1",
    "idMove": 159,
    "move": "Personal, 1a falta",
    "min": 1,
    "sec": 24,
    "period": 7,
    "score": "5-4",
    "teamAction": false,
    "foulNumber": 1,
    "timestamp": "20251116103119",
    "licenseId": 1165921,
    "eventUuid": "d0770c9b-71b9-49a3-b885-9793832150af"
  },
  {
    "idTeam": 0,
    "actorName": "",
    "actorId": 0,
    "actorShirtNumber": "",
    "idMove": 116,
    "move": "Final de període",
    "min": 0,
    "sec": 0,
    "period": 7,
    "score": "5-4",
    "teamAction": true,
    "timestamp": "20251116103406",
    "eventUuid": "eab5fe54-8c4d-4b37-948f-6f63521cb706"
  },
  {
    "idTeam": 481314,
    "actorName": "XAVIER CATALAN VENTOSO",
    "actorId": 8168882,
    "actorShirtNumber": "15",
    "idMove": 115,
    "move": "Surt del camp",
    "min": 6,
    "sec": 0,
    "period": 8,
    "score": "0-0",
    "teamAction": false,
    "timestamp": "20251116103406",
    "licenseId": 1181289,
    "eventUuid": "0ec5c2ef-8c64-4f63-9260-ad2d1305ea97"
  },
  {
    "idTeam": 481314,
    "actorName": "GERARD ALSINA GINESTA",
    "actorId": 8168879,
    "actorShirtNumber": "8",
    "idMove": 115,
    "move": "Surt del camp",
    "min": 6,
    "sec": 0,
    "period": 8,
    "score": "0-0",
    "teamAction": false,
    "timestamp": "20251116103406",
    "licenseId": 1165928,
    "eventUuid": "0a3ac226-0a5c-4dda-bc78-d765f4386604"
  },
  {
    "idTeam": 481314,
    "actorName": "TRAVIS ROJO CORBERA",
    "actorId": 8168875,
    "actorShirtNumber": "10",
    "idMove": 115,
    "move": "Surt del camp",
    "min": 6,
    "sec": 0,
    "period": 8,
    "score": "0-0",
    "teamAction": false,
    "timestamp": "20251116103406",
    "licenseId": 1165924,
    "eventUuid": "63707b44-3a64-4b5a-a474-9a0c5c8da748"
  },
  {
    "idTeam": 481314,
    "actorName": "ARAN BUTINK ROJAS",
    "actorId": 8168872,
    "actorShirtNumber": "1",
    "idMove": 115,
    "move": "Surt del camp",
    "min": 6,
    "sec": 0,
    "period": 8,
    "score": "0-0",
    "teamAction": false,
    "timestamp": "20251116103406",
    "licenseId": 1165921,
    "eventUuid": "41776ebf-98bc-498e-8a35-99cdebfb08ec"
  },
  {
    "idTeam": 481314,
    "actorName": "PABLO GAEL BRONCHAL TORRES",
    "actorId": 8168877,
    "actorShirtNumber": "24",
    "idMove": 112,
    "move": "Entra al camp",
    "min": 6,
    "sec": 0,
    "period": 8,
    "score": "0-0",
    "teamAction": false,
    "timestamp": "20251116103406",
    "licenseId": 1165926,
    "eventUuid": "688de9d2-195a-4e81-aba4-d852a5887e7c"
  },
  {
    "idTeam": 481314,
    "actorName": "RAPHAEL RODIER MICHEL",
    "actorId": 8168873,
    "actorShirtNumber": "12",
    "idMove": 112,
    "move": "Entra al camp",
    "min": 6,
    "sec": 0,
    "period": 8,
    "score": "0-0",
    "teamAction": false,
    "timestamp": "20251116103406",
    "licenseId": 1165922,
    "eventUuid": "6a0a061a-8262-4c58-a71b-16c2c1d0f792"
  },
  {
    "idTeam": 481314,
    "actorName": "SERGI CALAF ROCA",
    "actorId": 8168876,
    "actorShirtNumber": "3",
    "idMove": 112,
    "move": "Entra al camp",
    "min": 6,
    "sec": 0,
    "period": 8,
    "score": "0-0",
    "teamAction": false,
    "timestamp": "20251116103406",
    "licenseId": 1165925,
    "eventUuid": "6d650d66-b6f2-4e3c-a5c2-f525d55814e0"
  },
  {
    "idTeam": 481314,
    "actorName": "NIL PASCUAL GUILLÓ",
    "actorId": 8168883,
    "actorShirtNumber": "7",
    "idMove": 112,
    "move": "Entra al camp",
    "min": 6,
    "sec": 0,
    "period": 8,
    "score": "0-0",
    "teamAction": false,
    "timestamp": "20251116103406",
    "licenseId": 1207035,
    "eventUuid": "06c93c37-7d9e-49bd-81e3-500abad9bf60"
  },
  {
    "idTeam": 481315,
    "actorName": "SALVADOR FERNANDEZ GRANT",
    "actorId": 8169684,
    "actorShirtNumber": "18",
    "idMove": 115,
    "move": "Surt del camp",
    "min": 6,
    "sec": 0,
    "period": 8,
    "score": "0-0",
    "teamAction": false,
    "timestamp": "20251116103406",
    "licenseId": 1147408,
    "eventUuid": "23be852f-e039-4021-8d8e-d6159fb30941"
  },
  {
    "idTeam": 481315,
    "actorName": "OLIVER COMA DE HERRALDE",
    "actorId": 8169679,
    "actorShirtNumber": "19",
    "idMove": 115,
    "move": "Surt del camp",
    "min": 6,
    "sec": 0,
    "period": 8,
    "score": "0-0",
    "teamAction": false,
    "timestamp": "20251116103406",
    "licenseId": 1147403,
    "eventUuid": "ef9271d5-b536-44f7-a5e6-eacd5204a5c8"
  },
  {
    "idTeam": 481315,
    "actorName": "NIEL GIRAL FERRARONS",
    "actorId": 8169687,
    "actorShirtNumber": "6",
    "idMove": 112,
    "move": "Entra al camp",
    "min": 6,
    "sec": 0,
    "period": 8,
    "score": "0-0",
    "teamAction": false,
    "timestamp": "20251116103406",
    "licenseId": 1158003,
    "eventUuid": "16434c31-ee29-4e45-a5ce-995330ee95ec"
  },
  {
    "idTeam": 481315,
    "actorName": "BIEL ROGES LEZCANO",
    "actorId": 8169681,
    "actorShirtNumber": "51",
    "idMove": 112,
    "move": "Entra al camp",
    "min": 6,
    "sec": 0,
    "period": 8,
    "score": "0-0",
    "teamAction": false,
    "timestamp": "20251116103406",
    "licenseId": 1147405,
    "eventUuid": "fb81c056-82cb-48c1-985c-cf9504c8d05c"
  },
  {
    "idTeam": 481315,
    "actorName": "NIEL GIRAL FERRARONS",
    "actorId": 8169687,
    "actorShirtNumber": "6",
    "idMove": 178,
    "move": "Salt guanyat",
    "min": 6,
    "sec": 0,
    "period": 8,
    "score": "0-0",
    "teamAction": false,
    "timestamp": "20251116103558",
    "licenseId": 1158003,
    "eventUuid": "df369acf-f663-4961-b6c3-4d246f7d1f35"
  },
  {
    "idTeam": 481314,
    "actorName": "NIL PASCUAL GUILLÓ",
    "actorId": 8168883,
    "actorShirtNumber": "7",
    "idMove": 179,
    "move": "Salt perdut",
    "min": 6,
    "sec": 0,
    "period": 8,
    "score": "0-0",
    "teamAction": false,
    "timestamp": "20251116103558",
    "licenseId": 1207035,
    "eventUuid": "3651a822-ea86-440e-9206-0a3bc6bcaabf"
  },
  {
    "idTeam": 481315,
    "actorName": "DENIZ INALER",
    "actorId": 8169686,
    "actorShirtNumber": "10",
    "idMove": 93,
    "move": "Cistella de 2",
    "min": 4,
    "sec": 28,
    "period": 8,
    "score": "0-2",
    "teamAction": false,
    "timestamp": "20251116103743",
    "licenseId": 1157963,
    "eventUuid": "e060249f-3c46-4e84-a949-5ddad59580c4"
  },
  {
    "idTeam": 481314,
    "actorName": "POL GENÉ PALAÍN",
    "actorId": 8168874,
    "actorShirtNumber": "13",
    "idMove": 93,
    "move": "Cistella de 2",
    "min": 4,
    "sec": 13,
    "period": 8,
    "score": "2-2",
    "teamAction": false,
    "timestamp": "20251116103758",
    "licenseId": 1165923,
    "eventUuid": "12d24d64-addb-4700-8619-8a8844f0de8d"
  },
  {
    "idTeam": 481315,
    "actorName": "DENIZ INALER",
    "actorId": 8169686,
    "actorShirtNumber": "10",
    "idMove": 115,
    "move": "Surt del camp",
    "min": 3,
    "sec": 38,
    "period": 8,
    "score": "2-2",
    "teamAction": false,
    "timestamp": "20251116103832",
    "licenseId": 1157963,
    "eventUuid": "b789a359-762a-40b2-9b4f-338e7f8e23f0"
  },
  {
    "idTeam": 481315,
    "actorName": "BIEL GUZMAN TORRAS",
    "actorId": 8169688,
    "actorShirtNumber": "17",
    "idMove": 112,
    "move": "Entra al camp",
    "min": 3,
    "sec": 38,
    "period": 8,
    "score": "2-2",
    "teamAction": false,
    "timestamp": "20251116103832",
    "licenseId": 1162343,
    "eventUuid": "30381e00-d4e5-4544-a3a1-535e4f7114f5"
  },
  {
    "idTeam": 481314,
    "actorName": "PABLO GAEL BRONCHAL TORRES",
    "actorId": 8168877,
    "actorShirtNumber": "24",
    "idMove": 159,
    "move": "Personal, 1a falta",
    "min": 2,
    "sec": 47,
    "period": 8,
    "score": "2-2",
    "teamAction": false,
    "foulNumber": 1,
    "timestamp": "20251116103938",
    "licenseId": 1165926,
    "eventUuid": "f2a3f05f-2ede-4444-8a76-4fa4e09d8de1"
  },
  {
    "idTeam": 481314,
    "actorName": "RAPHAEL RODIER MICHEL",
    "actorId": 8168873,
    "actorShirtNumber": "12",
    "idMove": 115,
    "move": "Surt del camp",
    "min": 2,
    "sec": 42,
    "period": 8,
    "score": "2-2",
    "teamAction": false,
    "timestamp": "20251116103944",
    "licenseId": 1165922,
    "eventUuid": "67e922e0-58a3-43ce-b32a-987facb6299a"
  },
  {
    "idTeam": 481314,
    "actorName": "NIL PASCUAL GUILLÓ",
    "actorId": 8168883,
    "actorShirtNumber": "7",
    "idMove": 115,
    "move": "Surt del camp",
    "min": 2,
    "sec": 42,
    "period": 8,
    "score": "2-2",
    "teamAction": false,
    "timestamp": "20251116103944",
    "licenseId": 1207035,
    "eventUuid": "4280887e-e216-4105-885b-d808beedcbc8"
  },
  {
    "idTeam": 481314,
    "actorName": "GERARD ALSINA GINESTA",
    "actorId": 8168879,
    "actorShirtNumber": "8",
    "idMove": 112,
    "move": "Entra al camp",
    "min": 2,
    "sec": 42,
    "period": 8,
    "score": "2-2",
    "teamAction": false,
    "timestamp": "20251116103944",
    "licenseId": 1165928,
    "eventUuid": "23537eaa-3441-44fc-bf2d-cfb2516ca0f9"
  },
  {
    "idTeam": 481314,
    "actorName": "JAVIER CASADO MORA",
    "actorId": 8168880,
    "actorShirtNumber": "17",
    "idMove": 112,
    "move": "Entra al camp",
    "min": 2,
    "sec": 42,
    "period": 8,
    "score": "2-2",
    "teamAction": false,
    "timestamp": "20251116103944",
    "licenseId": 1165929,
    "eventUuid": "58b29b26-2dea-4b00-9ba7-14b20931a4ff"
  },
  {
    "idTeam": 481315,
    "actorName": "ORIOL DE OLANO CAMPRUBÍ",
    "actorId": 8169683,
    "actorShirtNumber": "41",
    "idMove": 115,
    "move": "Surt del camp",
    "min": 2,
    "sec": 42,
    "period": 8,
    "score": "2-2",
    "teamAction": false,
    "timestamp": "20251116103944",
    "licenseId": 1147407,
    "eventUuid": "b5e8b408-4628-4a0d-800b-513540d14dbd"
  },
  {
    "idTeam": 481315,
    "actorName": "SALVADOR FERNANDEZ GRANT",
    "actorId": 8169684,
    "actorShirtNumber": "18",
    "idMove": 112,
    "move": "Entra al camp",
    "min": 2,
    "sec": 42,
    "period": 8,
    "score": "2-2",
    "teamAction": false,
    "timestamp": "20251116103944",
    "licenseId": 1147408,
    "eventUuid": "5ab28e43-8fe4-42a6-a48c-a2c25d02fa5c"
  },
  {
    "idTeam": 481314,
    "actorName": "GERARD ALSINA GINESTA",
    "actorId": 8168879,
    "actorShirtNumber": "8",
    "idMove": 159,
    "move": "Personal, 1a falta",
    "min": 1,
    "sec": 32,
    "period": 8,
    "score": "2-2",
    "teamAction": false,
    "foulNumber": 1,
    "timestamp": "20251116104137",
    "licenseId": 1165928,
    "eventUuid": "16868931-c14c-423b-b1d5-b32cc187ceed"
  },
  {
    "idTeam": 481314,
    "actorName": "POL GENÉ PALAÍN",
    "actorId": 8168874,
    "actorShirtNumber": "13",
    "idMove": 93,
    "move": "Cistella de 2",
    "min": 0,
    "sec": 36,
    "period": 8,
    "score": "4-2",
    "teamAction": false,
    "timestamp": "20251116104242",
    "licenseId": 1165923,
    "eventUuid": "08161802-55b4-4f15-97d9-150e9bfce421"
  },
  {
    "idTeam": 481315,
    "actorName": "ROC ROBERT CORBI",
    "actorId": 8169682,
    "actorShirtNumber": "2",
    "idMove": 159,
    "move": "Personal, 3a falta",
    "min": 0,
    "sec": 0,
    "period": 8,
    "score": "4-2",
    "teamAction": false,
    "foulNumber": 3,
    "timestamp": "20251116104322",
    "licenseId": 1147406,
    "eventUuid": "be7f059c-cffd-47f7-8905-68065ee684f3"
  },
  {
    "idTeam": 481315,
    "actorName": "ROC ROBERT CORBI",
    "actorId": 8169682,
    "actorShirtNumber": "2",
    "idMove": 161,
    "move": "Personal 2 tirs lliures, 4a falta",
    "min": 0,
    "sec": 0,
    "period": 8,
    "score": "4-2",
    "teamAction": false,
    "foulNumber": 4,
    "timestamp": "20251116104334",
    "licenseId": 1147406,
    "eventUuid": "bb3d74d5-8a56-40f3-b915-cb6865b1b18c"
  },
  {
    "idTeam": 481314,
    "actorName": "JAVIER CASADO MORA",
    "actorId": 8168880,
    "actorShirtNumber": "17",
    "idMove": 92,
    "move": "Cistella de 1",
    "min": 0,
    "sec": 0,
    "period": 8,
    "score": "5-2",
    "teamAction": false,
    "timestamp": "20251116104353",
    "licenseId": 1165929,
    "eventUuid": "fdc18e67-7739-4188-82ca-58a390bbf288"
  },
  {
    "idTeam": 481314,
    "actorName": "JAVIER CASADO MORA",
    "actorId": 8168880,
    "actorShirtNumber": "17",
    "idMove": 92,
    "move": "Cistella de 1",
    "min": 0,
    "sec": 0,
    "period": 8,
    "score": "6-2",
    "teamAction": false,
    "timestamp": "20251116104407",
    "licenseId": 1165929,
    "eventUuid": "36de69b1-8ada-428c-9020-79a6efbb007f"
  },
  {
    "idTeam": 0,
    "actorName": "",
    "actorId": 0,
    "actorShirtNumber": "",
    "idMove": 116,
    "move": "Final de període",
    "min": 0,
    "sec": 0,
    "period": 8,
    "score": "6-2",
    "teamAction": true,
    "timestamp": "20251116104452",
    "eventUuid": "2942696d-a626-444d-9f7d-04e1a6de16d8"
  }
]