[
  {
    "idTeam": 500515,
    "actorName": "LORIÉN REINÉS ASCASO",
    "actorId": 8836326,
    "actorShirtNumber": "0",
    "idMove": 178,
    "move": "Salt guanyat",
    "min": 10,
    "sec": 0,
    "period": 1,
    "score": "0-0",
    "teamAction": false,
    "timestamp": "20251220190354",
    "licenseId": 1184905,
    "eventUuid": "0a02a96a-88f8-4dc0-b9c8-ce62dd95d4cb"
  },
  {
    "idTeam": 500514,
    "actorName": "YASSIN AHAIDAR EL MEZRAOUI",
    "actorId": 8836465,
    "actorShirtNumber": "59",
    "idMove": 179,
    "move": "Salt perdut",
    "min": 10,
    "sec": 0,
    "period": 1,
    "score": "0-0",
    "teamAction": false,
    "timestamp": "20251220190354",
    "licenseId": 1186704,
    "eventUuid": "b5a1a61d-8542-4a36-8ea7-be8fc424927c"
  },
  {
    "idTeam": 500514,
    "actorName": "EMILIO IZQUIERDO REINA",
    "actorId": 8836461,
    "actorShirtNumber": "25",
    "idMove": 161,
    "move": "Personal 2 tirs lliures, 1a falta",
    "min": 9,
    "sec": 41,
    "period": 1,
    "score": "0-0",
    "teamAction": false,
    "foulNumber": 1,
    "timestamp": "20251220190606",
    "licenseId": 1190250,
    "eventUuid": "ac2595a0-9021-442e-a6dd-db194c830def"
  },
  {
    "idTeam": 500515,
    "actorName": "FRANCESC ALBIOL SERRA",
    "actorId": 8836333,
    "actorShirtNumber": "16",
    "idMove": 96,
    "move": "Intent fallat de 1",
    "min": 9,
    "sec": 41,
    "period": 1,
    "score": "0-0",
    "teamAction": false,
    "timestamp": "20251220190643",
    "licenseId": 1184910,
    "eventUuid": "bd425b30-d594-4235-add0-8bb70fd31192"
  },
  {
    "idTeam": 500515,
    "actorName": "FRANCESC ALBIOL SERRA",
    "actorId": 8836333,
    "actorShirtNumber": "16",
    "idMove": 92,
    "move": "Cistella de 1",
    "min": 9,
    "sec": 41,
    "period": 1,
    "score": "0-1",
    "teamAction": false,
    "timestamp": "20251220190652",
    "licenseId": 1184910,
    "eventUuid": "092f12bb-dcd6-4151-81cf-924e1859c03f"
  },
  {
    "idTeam": 500515,
    "actorName": "GERARD FERRER GONZÁLEZ",
    "actorId": 8836331,
    "actorShirtNumber": "13",
    "idMove": 93,
    "move": "Cistella de 2",
    "min": 8,
    "sec": 31,
    "period": 1,
    "score": "0-3",
    "teamAction": false,
    "timestamp": "20251220190804",
    "licenseId": 1184909,
    "eventUuid": "210f61b1-d326-484f-a566-cdee751e246d"
  },
  {
    "idTeam": 500515,
    "actorName": "LORIÉN REINÉS ASCASO",
    "actorId": 8836326,
    "actorShirtNumber": "0",
    "idMove": 93,
    "move": "Cistella de 2",
    "min": 8,
    "sec": 15,
    "period": 1,
    "score": "0-5",
    "teamAction": false,
    "timestamp": "20251220190822",
    "licenseId": 1184905,
    "eventUuid": "a22bb644-eb15-4638-8aa5-e94dc3092d6d"
  },
  {
    "idTeam": 500514,
    "actorName": "CLUB BÀSQUET CAN PARELLADA 2",
    "actorId": 0,
    "actorShirtNumber": "",
    "idMove": 113,
    "move": "Temps mort",
    "min": 8,
    "sec": 15,
    "period": 1,
    "score": "0-5",
    "teamAction": true,
    "timestamp": "20251220190829",
    "eventUuid": "29555a09-539d-4022-9b13-0a64f6eccfd8"
  },
  {
    "idTeam": 500514,
    "actorName": "YASSIN AHAIDAR EL MEZRAOUI",
    "actorId": 8836465,
    "actorShirtNumber": "59",
    "idMove": 93,
    "move": "Cistella de 2",
    "min": 7,
    "sec": 20,
    "period": 1,
    "score": "2-5",
    "teamAction": false,
    "timestamp": "20251220191044",
    "licenseId": 1186704,
    "eventUuid": "fef7e8d8-0a35-412a-8c11-d95211f8964c"
  },
  {
    "idTeam": 500515,
    "actorName": "GERARD FERRER GONZÁLEZ",
    "actorId": 8836331,
    "actorShirtNumber": "13",
    "idMove": 94,
    "move": "Cistella de 3",
    "min": 6,
    "sec": 45,
    "period": 1,
    "score": "2-8",
    "teamAction": false,
    "timestamp": "20251220191134",
    "licenseId": 1184909,
    "eventUuid": "e14528ee-4473-4cdc-9035-324668bb380a"
  },
  {
    "idTeam": 500514,
    "actorName": "MARC GAVILAN CEREZO",
    "actorId": 8836455,
    "actorShirtNumber": "5",
    "idMove": 161,
    "move": "Personal 2 tirs lliures, 1a falta",
    "min": 6,
    "sec": 34,
    "period": 1,
    "score": "2-8",
    "teamAction": false,
    "foulNumber": 1,
    "timestamp": "20251220191147",
    "licenseId": 1196508,
    "eventUuid": "ef6f4f11-92df-42d2-a1f1-e0080be79c60"
  },
  {
    "idTeam": 500515,
    "actorName": "LEONARDO ANTONIO ROJAS NÚÑEZ",
    "actorId": 8836328,
    "actorShirtNumber": "4",
    "idMove": 96,
    "move": "Intent fallat de 1",
    "min": 6,
    "sec": 34,
    "period": 1,
    "score": "2-8",
    "teamAction": false,
    "timestamp": "20251220191207",
    "licenseId": 1195274,
    "eventUuid": "f61e375a-b150-4271-9e33-9274cff16a75"
  },
  {
    "idTeam": 500515,
    "actorName": "LEONARDO ANTONIO ROJAS NÚÑEZ",
    "actorId": 8836328,
    "actorShirtNumber": "4",
    "idMove": 92,
    "move": "Cistella de 1",
    "min": 6,
    "sec": 34,
    "period": 1,
    "score": "2-9",
    "teamAction": false,
    "timestamp": "20251220191223",
    "licenseId": 1195274,
    "eventUuid": "b3489632-5c38-4c3b-9535-ba195b3f103a"
  },
  {
    "idTeam": 500515,
    "actorName": "LEONARDO ANTONIO ROJAS NÚÑEZ",
    "actorId": 8836328,
    "actorShirtNumber": "4",
    "idMove": 93,
    "move": "Cistella de 2",
    "min": 6,
    "sec": 17,
    "period": 1,
    "score": "2-11",
    "teamAction": false,
    "timestamp": "20251220191242",
    "licenseId": 1195274,
    "eventUuid": "de71c262-2fd7-4f3c-bb7b-9a4ef10d7679"
  },
  {
    "idTeam": 500514,
    "actorName": "EMILIO IZQUIERDO REINA",
    "actorId": 8836461,
    "actorShirtNumber": "25",
    "idMove": 159,
    "move": "Personal, 2a falta",
    "min": 5,
    "sec": 56,
    "period": 1,
    "score": "2-11",
    "teamAction": false,
    "foulNumber": 2,
    "timestamp": "20251220191304",
    "licenseId": 1190250,
    "eventUuid": "8071fde0-aed8-4c40-be1d-de638596969f"
  },
  {
    "idTeam": 500514,
    "actorName": "EMILIO IZQUIERDO REINA",
    "actorId": 8836461,
    "actorShirtNumber": "25",
    "idMove": 115,
    "move": "Surt del camp",
    "min": 5,
    "sec": 54,
    "period": 1,
    "score": "2-11",
    "teamAction": false,
    "timestamp": "20251220191309",
    "licenseId": 1190250,
    "eventUuid": "395bd75e-b517-4a95-a5c3-dc4dda85a566"
  },
  {
    "idTeam": 500514,
    "actorName": "GUILLEM BABIO DEL AGUILA",
    "actorId": 8836458,
    "actorShirtNumber": "11",
    "idMove": 112,
    "move": "Entra al camp",
    "min": 5,
    "sec": 54,
    "period": 1,
    "score": "2-11",
    "teamAction": false,
    "timestamp": "20251220191309",
    "licenseId": 1190242,
    "eventUuid": "7166c35d-8239-42f8-b99e-07f0bb23dcee"
  },
  {
    "idTeam": 500514,
    "actorName": "MARC GAVILAN CEREZO",
    "actorId": 8836455,
    "actorShirtNumber": "5",
    "idMove": 115,
    "move": "Surt del camp",
    "min": 5,
    "sec": 54,
    "period": 1,
    "score": "2-11",
    "teamAction": false,
    "timestamp": "20251220191316",
    "licenseId": 1196508,
    "eventUuid": "6522fc57-edfe-4b11-98b1-094e2fefdc0e"
  },
  {
    "idTeam": 500514,
    "actorName": "DAVID BENAIGUES OMOREGIE",
    "actorId": 8836460,
    "actorShirtNumber": "14",
    "idMove": 112,
    "move": "Entra al camp",
    "min": 5,
    "sec": 54,
    "period": 1,
    "score": "2-11",
    "teamAction": false,
    "timestamp": "20251220191316",
    "licenseId": 1186712,
    "eventUuid": "4fc8d227-5f41-4c10-afdc-d1bde9f9d603"
  },
  {
    "idTeam": 500515,
    "actorName": "FRANCESC ALBIOL SERRA",
    "actorId": 8836333,
    "actorShirtNumber": "16",
    "idMove": 93,
    "move": "Cistella de 2",
    "min": 4,
    "sec": 46,
    "period": 1,
    "score": "2-13",
    "teamAction": false,
    "timestamp": "20251220191444",
    "licenseId": 1184910,
    "eventUuid": "d556eeb1-d73c-4698-9894-182c21832dc1"
  },
  {
    "idTeam": 500515,
    "actorName": "GERARD FERRER GONZÁLEZ",
    "actorId": 8836331,
    "actorShirtNumber": "13",
    "idMove": 159,
    "move": "Personal, 1a falta",
    "min": 4,
    "sec": 32,
    "period": 1,
    "score": "2-13",
    "teamAction": false,
    "foulNumber": 1,
    "timestamp": "20251220191508",
    "licenseId": 1184909,
    "eventUuid": "8a360c26-67d7-457f-b06f-8d0786c2ef22"
  },
  {
    "idTeam": 500515,
    "actorName": "HÉCTOR CABEZAS AISA",
    "actorId": 8836329,
    "actorShirtNumber": "7",
    "idMove": 115,
    "move": "Surt del camp",
    "min": 4,
    "sec": 32,
    "period": 1,
    "score": "2-13",
    "teamAction": false,
    "timestamp": "20251220191515",
    "licenseId": 1184907,
    "eventUuid": "b27f0a27-6fc9-4094-a795-607c6786c204"
  },
  {
    "idTeam": 500515,
    "actorName": "FRANCESC ALBIOL SERRA",
    "actorId": 8836333,
    "actorShirtNumber": "16",
    "idMove": 115,
    "move": "Surt del camp",
    "min": 4,
    "sec": 32,
    "period": 1,
    "score": "2-13",
    "teamAction": false,
    "timestamp": "20251220191515",
    "licenseId": 1184910,
    "eventUuid": "6874c7f4-ce98-414c-9e89-6ffe5190cedf"
  },
  {
    "idTeam": 500515,
    "actorName": "ASIER SERRATO MENDIOLA",
    "actorId": 8836330,
    "actorShirtNumber": "10",
    "idMove": 112,
    "move": "Entra al camp",
    "min": 4,
    "sec": 32,
    "period": 1,
    "score": "2-13",
    "teamAction": false,
    "timestamp": "20251220191515",
    "licenseId": 1184903,
    "eventUuid": "3d83fbd3-2a91-4e2e-b89f-36def1f01eb0"
  },
  {
    "idTeam": 500515,
    "actorName": "IKER CAPELL DE LA FUENTE",
    "actorId": 8836334,
    "actorShirtNumber": "19",
    "idMove": 112,
    "move": "Entra al camp",
    "min": 4,
    "sec": 32,
    "period": 1,
    "score": "2-13",
    "teamAction": false,
    "timestamp": "20251220191515",
    "licenseId": 1184911,
    "eventUuid": "ebae54cf-9d56-4e16-ba32-cb46aee1fefb"
  },
  {
    "idTeam": 500515,
    "actorName": "LEONARDO ANTONIO ROJAS NÚÑEZ",
    "actorId": 8836328,
    "actorShirtNumber": "4",
    "idMove": 160,
    "move": "Personal 1 tir lliure, 1a falta",
    "min": 4,
    "sec": 17,
    "period": 1,
    "score": "2-13",
    "teamAction": false,
    "foulNumber": 1,
    "timestamp": "20251220191549",
    "licenseId": 1195274,
    "eventUuid": "c1a65c52-1307-4031-997e-41e041f5cba7"
  },
  {
    "idTeam": 500514,
    "actorName": "WEN ZE DONG CHEN",
    "actorId": 8836459,
    "actorShirtNumber": "13",
    "idMove": 93,
    "move": "Cistella de 2",
    "min": 4,
    "sec": 17,
    "period": 1,
    "score": "4-13",
    "teamAction": false,
    "timestamp": "20251220191554",
    "licenseId": 1186707,
    "eventUuid": "5cd176b4-5302-4f61-8e63-a76b260c642f"
  },
  {
    "idTeam": 500514,
    "actorName": "WEN ZE DONG CHEN",
    "actorId": 8836459,
    "actorShirtNumber": "13",
    "idMove": 96,
    "move": "Intent fallat de 1",
    "min": 4,
    "sec": 17,
    "period": 1,
    "score": "4-13",
    "teamAction": false,
    "timestamp": "20251220191607",
    "licenseId": 1186707,
    "eventUuid": "6c04bbef-aa23-48a0-a0cb-12357ad5bbca"
  },
  {
    "idTeam": 500514,
    "actorName": "DAVID BENAIGUES OMOREGIE",
    "actorId": 8836460,
    "actorShirtNumber": "14",
    "idMove": 93,
    "move": "Cistella de 2",
    "min": 3,
    "sec": 31,
    "period": 1,
    "score": "6-13",
    "teamAction": false,
    "timestamp": "20251220191710",
    "licenseId": 1186712,
    "eventUuid": "75408b64-f473-4c7a-a3d9-328a2de78ae1"
  },
  {
    "idTeam": 500515,
    "actorName": "LORIÉN REINÉS ASCASO",
    "actorId": 8836326,
    "actorShirtNumber": "0",
    "idMove": 93,
    "move": "Cistella de 2",
    "min": 2,
    "sec": 42,
    "period": 1,
    "score": "6-15",
    "teamAction": false,
    "timestamp": "20251220191813",
    "licenseId": 1184905,
    "eventUuid": "e8112811-d28c-4f01-93bc-b80b065bfa98"
  },
  {
    "idTeam": 500514,
    "actorName": "WEN ZE DONG CHEN",
    "actorId": 8836459,
    "actorShirtNumber": "13",
    "idMove": 93,
    "move": "Cistella de 2",
    "min": 2,
    "sec": 25,
    "period": 1,
    "score": "8-15",
    "teamAction": false,
    "timestamp": "20251220191830",
    "licenseId": 1186707,
    "eventUuid": "90f65497-b4a1-425e-81c4-318391ec5b6d"
  },
  {
    "idTeam": 500515,
    "actorName": "LEONARDO ANTONIO ROJAS NÚÑEZ",
    "actorId": 8836328,
    "actorShirtNumber": "4",
    "idMove": 94,
    "move": "Cistella de 3",
    "min": 2,
    "sec": 10,
    "period": 1,
    "score": "8-18",
    "teamAction": false,
    "timestamp": "20251220191845",
    "licenseId": 1195274,
    "eventUuid": "ecc55a46-b58f-4615-ad4b-45e236d54315"
  },
  {
    "idTeam": 500514,
    "actorName": "DAVID BENAIGUES OMOREGIE",
    "actorId": 8836460,
    "actorShirtNumber": "14",
    "idMove": 115,
    "move": "Surt del camp",
    "min": 1,
    "sec": 49,
    "period": 1,
    "score": "8-18",
    "teamAction": false,
    "timestamp": "20251220191908",
    "licenseId": 1186712,
    "eventUuid": "03347b11-6ee3-40dc-b108-67e5af4f0fe0"
  },
  {
    "idTeam": 500514,
    "actorName": "MARCOS MARTIN MARTINEZ",
    "actorId": 8836454,
    "actorShirtNumber": "3",
    "idMove": 112,
    "move": "Entra al camp",
    "min": 1,
    "sec": 49,
    "period": 1,
    "score": "8-18",
    "teamAction": false,
    "timestamp": "20251220191908",
    "licenseId": 1201434,
    "eventUuid": "a427d2e5-fd8f-443b-a4dc-177573d8e0e4"
  },
  {
    "idTeam": 500515,
    "actorName": "LORIÉN REINÉS ASCASO",
    "actorId": 8836326,
    "actorShirtNumber": "0",
    "idMove": 115,
    "move": "Surt del camp",
    "min": 1,
    "sec": 49,
    "period": 1,
    "score": "8-18",
    "teamAction": false,
    "timestamp": "20251220191908",
    "licenseId": 1184905,
    "eventUuid": "d19af6b7-f9d1-4741-a150-d29c3d875417"
  },
  {
    "idTeam": 500515,
    "actorName": "LEONARDO ANTONIO ROJAS NÚÑEZ",
    "actorId": 8836328,
    "actorShirtNumber": "4",
    "idMove": 115,
    "move": "Surt del camp",
    "min": 1,
    "sec": 49,
    "period": 1,
    "score": "8-18",
    "teamAction": false,
    "timestamp": "20251220191908",
    "licenseId": 1195274,
    "eventUuid": "0ec398f3-6c7a-45e8-a8fd-afb3dfbeb2f7"
  },
  {
    "idTeam": 500515,
    "actorName": "LUCAS ROSSO RAMOS",
    "actorId": 8836335,
    "actorShirtNumber": "54",
    "idMove": 112,
    "move": "Entra al camp",
    "min": 1,
    "sec": 49,
    "period": 1,
    "score": "8-18",
    "teamAction": false,
    "timestamp": "20251220191908",
    "licenseId": 1209335,
    "eventUuid": "201ea9b6-95b0-4102-91b2-ae3ff6ec1c12"
  },
  {
    "idTeam": 500515,
    "actorName": "FACUNDO LANFRANCONI GALLEGOS",
    "actorId": 8836332,
    "actorShirtNumber": "15",
    "idMove": 112,
    "move": "Entra al camp",
    "min": 1,
    "sec": 49,
    "period": 1,
    "score": "8-18",
    "teamAction": false,
    "timestamp": "20251220191908",
    "licenseId": 1187410,
    "eventUuid": "909e263c-1bb7-46e8-a4a0-753f4f55b53c"
  },
  {
    "idTeam": 500515,
    "actorName": "ASIER SERRATO MENDIOLA",
    "actorId": 8836330,
    "actorShirtNumber": "10",
    "idMove": 94,
    "move": "Cistella de 3",
    "min": 1,
    "sec": 44,
    "period": 1,
    "score": "8-21",
    "teamAction": false,
    "timestamp": "20251220191933",
    "licenseId": 1184903,
    "eventUuid": "0ae30103-733e-4d54-b1b7-c4edad0d8a3d"
  },
  {
    "idTeam": 500514,
    "actorName": "WEN ZE DONG CHEN",
    "actorId": 8836459,
    "actorShirtNumber": "13",
    "idMove": 94,
    "move": "Cistella de 3",
    "min": 1,
    "sec": 18,
    "period": 1,
    "score": "11-21",
    "teamAction": false,
    "timestamp": "20251220191959",
    "licenseId": 1186707,
    "eventUuid": "c7fc7587-1cc7-49c9-a330-e956a7f808ca"
  },
  {
    "idTeam": 500515,
    "actorName": "IKER CAPELL DE LA FUENTE",
    "actorId": 8836334,
    "actorShirtNumber": "19",
    "idMove": 93,
    "move": "Cistella de 2",
    "min": 1,
    "sec": 3,
    "period": 1,
    "score": "11-23",
    "teamAction": false,
    "timestamp": "20251220192014",
    "licenseId": 1184911,
    "eventUuid": "a36fc1bd-8390-4de6-89bf-914d00c021bb"
  },
  {
    "idTeam": 500515,
    "actorName": "GERARD FERRER GONZÁLEZ",
    "actorId": 8836331,
    "actorShirtNumber": "13",
    "idMove": 115,
    "move": "Surt del camp",
    "min": 0,
    "sec": 55,
    "period": 1,
    "score": "11-23",
    "teamAction": false,
    "timestamp": "20251220192023",
    "licenseId": 1184909,
    "eventUuid": "0865a7c6-fc75-4f8d-bcc5-1039b2734fa1"
  },
  {
    "idTeam": 500515,
    "actorName": "FRANCESC ALBIOL SERRA",
    "actorId": 8836333,
    "actorShirtNumber": "16",
    "idMove": 112,
    "move": "Entra al camp",
    "min": 0,
    "sec": 55,
    "period": 1,
    "score": "11-23",
    "teamAction": false,
    "timestamp": "20251220192023",
    "licenseId": 1184910,
    "eventUuid": "c7016a42-6943-47e1-beb4-fe46b615f9ea"
  },
  {
    "idTeam": 500515,
    "actorName": "FRANCESC ALBIOL SERRA",
    "actorId": 8836333,
    "actorShirtNumber": "16",
    "idMove": 159,
    "move": "Personal, 1a falta",
    "min": 0,
    "sec": 38,
    "period": 1,
    "score": "11-23",
    "teamAction": false,
    "foulNumber": 1,
    "timestamp": "20251220192103",
    "licenseId": 1184910,
    "eventUuid": "cc20a997-3b52-4de5-bc95-0710a27d397e"
  },
  {
    "idTeam": 500514,
    "actorName": "GUILLEM BABIO DEL AGUILA",
    "actorId": 8836458,
    "actorShirtNumber": "11",
    "idMove": 93,
    "move": "Cistella de 2",
    "min": 0,
    "sec": 38,
    "period": 1,
    "score": "13-23",
    "teamAction": false,
    "timestamp": "20251220192106",
    "licenseId": 1190242,
    "eventUuid": "719892d8-9269-40fc-a3ee-64b85d85bd7b"
  },
  {
    "idTeam": 0,
    "actorName": "",
    "actorId": 0,
    "actorShirtNumber": "",
    "idMove": 116,
    "move": "Final de període",
    "min": 0,
    "sec": 0,
    "period": 1,
    "score": "13-23",
    "teamAction": true,
    "timestamp": "20251220192212",
    "eventUuid": "e995ccd2-7765-42d9-985d-f6c54a05eeba"
  },
  {
    "idTeam": 500514,
    "actorName": "VICTOR RODRIGUEZ ESTRADA",
    "actorId": 8836462,
    "actorShirtNumber": "33",
    "idMove": 115,
    "move": "Surt del camp",
    "min": 10,
    "sec": 0,
    "period": 2,
    "score": "13-23",
    "teamAction": false,
    "timestamp": "20251220192214",
    "licenseId": 1186710,
    "eventUuid": "824f4f47-13d0-471d-929e-6b9720f42c8a"
  },
  {
    "idTeam": 500514,
    "actorName": "YASSIN AHAIDAR EL MEZRAOUI",
    "actorId": 8836465,
    "actorShirtNumber": "59",
    "idMove": 115,
    "move": "Surt del camp",
    "min": 10,
    "sec": 0,
    "period": 2,
    "score": "13-23",
    "teamAction": false,
    "timestamp": "20251220192214",
    "licenseId": 1186704,
    "eventUuid": "06364ed4-74e8-4e43-a60e-f4b6cf139ef4"
  },
  {
    "idTeam": 500514,
    "actorName": "YOUSSEF EL JAANIN ZOUADI",
    "actorId": 8836463,
    "actorShirtNumber": "40",
    "idMove": 112,
    "move": "Entra al camp",
    "min": 10,
    "sec": 0,
    "period": 2,
    "score": "13-23",
    "teamAction": false,
    "timestamp": "20251220192214",
    "licenseId": 1203013,
    "eventUuid": "200a14f4-391d-4afc-9f52-0faddb79f100"
  },
  {
    "idTeam": 500514,
    "actorName": "EMILIO IZQUIERDO REINA",
    "actorId": 8836461,
    "actorShirtNumber": "25",
    "idMove": 112,
    "move": "Entra al camp",
    "min": 10,
    "sec": 0,
    "period": 2,
    "score": "13-23",
    "teamAction": false,
    "timestamp": "20251220192214",
    "licenseId": 1190250,
    "eventUuid": "763e4de8-f8e3-401e-a9aa-306795373786"
  },
  {
    "idTeam": 500514,
    "actorName": "GUILLEM BABIO DEL AGUILA",
    "actorId": 8836458,
    "actorShirtNumber": "11",
    "idMove": 93,
    "move": "Cistella de 2",
    "min": 9,
    "sec": 17,
    "period": 2,
    "score": "15-23",
    "teamAction": false,
    "timestamp": "20251220192427",
    "licenseId": 1190242,
    "eventUuid": "fd22ce4d-784d-4573-b467-4f6aa58fc4be"
  },
  {
    "idTeam": 500515,
    "actorName": "FRANCESC ALBIOL SERRA",
    "actorId": 8836333,
    "actorShirtNumber": "16",
    "idMove": 161,
    "move": "Personal 2 tirs lliures, 2a falta",
    "min": 8,
    "sec": 52,
    "period": 2,
    "score": "15-23",
    "teamAction": false,
    "foulNumber": 2,
    "timestamp": "20251220192507",
    "licenseId": 1184910,
    "eventUuid": "158c56dd-bd70-410d-aa4e-0f99c1bd2d20"
  },
  {
    "idTeam": 500514,
    "actorName": "WEN ZE DONG CHEN",
    "actorId": 8836459,
    "actorShirtNumber": "13",
    "idMove": 96,
    "move": "Intent fallat de 1",
    "min": 8,
    "sec": 52,
    "period": 2,
    "score": "15-23",
    "teamAction": false,
    "timestamp": "20251220192529",
    "licenseId": 1186707,
    "eventUuid": "3704234e-e311-48f3-864b-bae9916b3507"
  },
  {
    "idTeam": 500514,
    "actorName": "WEN ZE DONG CHEN",
    "actorId": 8836459,
    "actorShirtNumber": "13",
    "idMove": 92,
    "move": "Cistella de 1",
    "min": 8,
    "sec": 52,
    "period": 2,
    "score": "16-23",
    "teamAction": false,
    "timestamp": "20251220192541",
    "licenseId": 1186707,
    "eventUuid": "4273a281-250f-434d-9d4a-44669ad1af80"
  },
  {
    "idTeam": 500515,
    "actorName": "FRANCESC ALBIOL SERRA",
    "actorId": 8836333,
    "actorShirtNumber": "16",
    "idMove": 115,
    "move": "Surt del camp",
    "min": 8,
    "sec": 52,
    "period": 2,
    "score": "16-23",
    "teamAction": false,
    "timestamp": "20251220192543",
    "licenseId": 1184910,
    "eventUuid": "e470e285-4d73-487e-8e52-1e70d4fff74a"
  },
  {
    "idTeam": 500515,
    "actorName": "GERARD FERRER GONZÁLEZ",
    "actorId": 8836331,
    "actorShirtNumber": "13",
    "idMove": 112,
    "move": "Entra al camp",
    "min": 8,
    "sec": 52,
    "period": 2,
    "score": "16-23",
    "teamAction": false,
    "timestamp": "20251220192543",
    "licenseId": 1184909,
    "eventUuid": "c6ac7974-4fe9-4b11-9e1c-c0fdfb3410ef"
  },
  {
    "idTeam": 500514,
    "actorName": "EMILIO IZQUIERDO REINA",
    "actorId": 8836461,
    "actorShirtNumber": "25",
    "idMove": 93,
    "move": "Cistella de 2",
    "min": 8,
    "sec": 27,
    "period": 2,
    "score": "18-23",
    "teamAction": false,
    "timestamp": "20251220192629",
    "licenseId": 1190250,
    "eventUuid": "9cf74080-86a8-469a-bb20-80e8db4dc0b3"
  },
  {
    "idTeam": 500515,
    "actorName": "ASIER SERRATO MENDIOLA",
    "actorId": 8836330,
    "actorShirtNumber": "10",
    "idMove": 93,
    "move": "Cistella de 2",
    "min": 8,
    "sec": 12,
    "period": 2,
    "score": "18-25",
    "teamAction": false,
    "timestamp": "20251220192645",
    "licenseId": 1184903,
    "eventUuid": "85080b70-429a-421b-9338-5b7d7215799d"
  },
  {
    "idTeam": 500515,
    "actorName": "IKER CAPELL DE LA FUENTE",
    "actorId": 8836334,
    "actorShirtNumber": "19",
    "idMove": 93,
    "move": "Cistella de 2",
    "min": 7,
    "sec": 53,
    "period": 2,
    "score": "18-27",
    "teamAction": false,
    "timestamp": "20251220192703",
    "licenseId": 1184911,
    "eventUuid": "363f1a2a-c445-4eac-bd5f-a821051ba792"
  },
  {
    "idTeam": 500515,
    "actorName": "FACUNDO LANFRANCONI GALLEGOS",
    "actorId": 8836332,
    "actorShirtNumber": "15",
    "idMove": 161,
    "move": "Personal 2 tirs lliures, 1a falta",
    "min": 7,
    "sec": 39,
    "period": 2,
    "score": "18-27",
    "teamAction": false,
    "foulNumber": 1,
    "timestamp": "20251220192721",
    "licenseId": 1187410,
    "eventUuid": "b6be3b6b-ed93-4faa-8d96-5c657e0b1e74"
  },
  {
    "idTeam": 500514,
    "actorName": "MARCOS MARTIN MARTINEZ",
    "actorId": 8836454,
    "actorShirtNumber": "3",
    "idMove": 115,
    "move": "Surt del camp",
    "min": 7,
    "sec": 39,
    "period": 2,
    "score": "18-27",
    "teamAction": false,
    "timestamp": "20251220192724",
    "licenseId": 1201434,
    "eventUuid": "aa2cc1bd-8e6e-4940-8751-d966ed7e1221"
  },
  {
    "idTeam": 500514,
    "actorName": "PAU ALVAREZ BABIO",
    "actorId": 8836456,
    "actorShirtNumber": "7",
    "idMove": 112,
    "move": "Entra al camp",
    "min": 7,
    "sec": 39,
    "period": 2,
    "score": "18-27",
    "teamAction": false,
    "timestamp": "20251220192724",
    "licenseId": 1205039,
    "eventUuid": "853704d2-c5df-417b-b5e9-a38beabf79f0"
  },
  {
    "idTeam": 500515,
    "actorName": "FACUNDO LANFRANCONI GALLEGOS",
    "actorId": 8836332,
    "actorShirtNumber": "15",
    "idMove": 115,
    "move": "Surt del camp",
    "min": 7,
    "sec": 39,
    "period": 2,
    "score": "18-27",
    "teamAction": false,
    "timestamp": "20251220192724",
    "licenseId": 1187410,
    "eventUuid": "9b55e305-3a05-4ded-8e88-bed986053c71"
  },
  {
    "idTeam": 500515,
    "actorName": "LEONARDO ANTONIO ROJAS NÚÑEZ",
    "actorId": 8836328,
    "actorShirtNumber": "4",
    "idMove": 112,
    "move": "Entra al camp",
    "min": 7,
    "sec": 39,
    "period": 2,
    "score": "18-27",
    "teamAction": false,
    "timestamp": "20251220192724",
    "licenseId": 1195274,
    "eventUuid": "0bf9d4e8-862c-4956-91dc-bfb5d0a7bf71"
  },
  {
    "idTeam": 500514,
    "actorName": "EMILIO IZQUIERDO REINA",
    "actorId": 8836461,
    "actorShirtNumber": "25",
    "idMove": 92,
    "move": "Cistella de 1",
    "min": 7,
    "sec": 39,
    "period": 2,
    "score": "19-27",
    "teamAction": false,
    "timestamp": "20251220192747",
    "licenseId": 1190250,
    "eventUuid": "2f0fe399-7bc9-445c-9b0f-3644bc0212c4"
  },
  {
    "idTeam": 500514,
    "actorName": "EMILIO IZQUIERDO REINA",
    "actorId": 8836461,
    "actorShirtNumber": "25",
    "idMove": 92,
    "move": "Cistella de 1",
    "min": 7,
    "sec": 39,
    "period": 2,
    "score": "20-27",
    "teamAction": false,
    "timestamp": "20251220192759",
    "licenseId": 1190250,
    "eventUuid": "2e545969-b576-4eb0-a662-05f54ebd8262"
  },
  {
    "idTeam": 500514,
    "actorName": "YOUSSEF EL JAANIN ZOUADI",
    "actorId": 8836463,
    "actorShirtNumber": "40",
    "idMove": 161,
    "move": "Personal 2 tirs lliures, 1a falta",
    "min": 7,
    "sec": 6,
    "period": 2,
    "score": "20-27",
    "teamAction": false,
    "foulNumber": 1,
    "timestamp": "20251220192842",
    "licenseId": 1203013,
    "eventUuid": "22539a42-586e-422a-bda5-9481b0e62a2b"
  },
  {
    "idTeam": 500515,
    "actorName": "LUCAS ROSSO RAMOS",
    "actorId": 8836335,
    "actorShirtNumber": "54",
    "idMove": 96,
    "move": "Intent fallat de 1",
    "min": 7,
    "sec": 6,
    "period": 2,
    "score": "20-27",
    "teamAction": false,
    "timestamp": "20251220192912",
    "licenseId": 1209335,
    "eventUuid": "ea84a4c1-dbac-457b-a72b-bcb69500abdc"
  },
  {
    "idTeam": 500515,
    "actorName": "LUCAS ROSSO RAMOS",
    "actorId": 8836335,
    "actorShirtNumber": "54",
    "idMove": 96,
    "move": "Intent fallat de 1",
    "min": 7,
    "sec": 6,
    "period": 2,
    "score": "20-27",
    "teamAction": false,
    "timestamp": "20251220192914",
    "licenseId": 1209335,
    "eventUuid": "d2598a3c-5dd0-4aac-b26b-41c1cba24f52"
  },
  {
    "idTeam": 500515,
    "actorName": "ASIER SERRATO MENDIOLA",
    "actorId": 8836330,
    "actorShirtNumber": "10",
    "idMove": 93,
    "move": "Cistella de 2",
    "min": 7,
    "sec": 6,
    "period": 2,
    "score": "20-29",
    "teamAction": false,
    "timestamp": "20251220192923",
    "licenseId": 1184903,
    "eventUuid": "032ad5a0-e319-4d65-9705-c527f3935db4"
  },
  {
    "idTeam": 500514,
    "actorName": "CLUB BÀSQUET CAN PARELLADA 2",
    "actorId": 0,
    "actorShirtNumber": "",
    "idMove": 113,
    "move": "Temps mort",
    "min": 7,
    "sec": 6,
    "period": 2,
    "score": "20-29",
    "teamAction": true,
    "timestamp": "20251220192927",
    "eventUuid": "c90ae2db-c567-4cd4-b13a-f3bd4489cbcf"
  },
  {
    "idTeam": 500514,
    "actorName": "YOUSSEF EL JAANIN ZOUADI",
    "actorId": 8836463,
    "actorShirtNumber": "40",
    "idMove": 115,
    "move": "Surt del camp",
    "min": 7,
    "sec": 6,
    "period": 2,
    "score": "20-29",
    "teamAction": false,
    "timestamp": "20251220192933",
    "licenseId": 1203013,
    "eventUuid": "f0b69cf1-1c89-4149-b0bd-3a32ba4867b0"
  },
  {
    "idTeam": 500514,
    "actorName": "VICTOR RODRIGUEZ ESTRADA",
    "actorId": 8836462,
    "actorShirtNumber": "33",
    "idMove": 112,
    "move": "Entra al camp",
    "min": 7,
    "sec": 6,
    "period": 2,
    "score": "20-29",
    "teamAction": false,
    "timestamp": "20251220192933",
    "licenseId": 1186710,
    "eventUuid": "b56d5346-656e-4c9b-aff1-b650ad34df67"
  },
  {
    "idTeam": 500515,
    "actorName": "GERARD FERRER GONZÁLEZ",
    "actorId": 8836331,
    "actorShirtNumber": "13",
    "idMove": 93,
    "move": "Cistella de 2",
    "min": 6,
    "sec": 20,
    "period": 2,
    "score": "20-31",
    "teamAction": false,
    "timestamp": "20251220193157",
    "licenseId": 1184909,
    "eventUuid": "11352d90-811f-4562-b303-d176bab90b91"
  },
  {
    "idTeam": 500514,
    "actorName": "WEN ZE DONG CHEN",
    "actorId": 8836459,
    "actorShirtNumber": "13",
    "idMove": 115,
    "move": "Surt del camp",
    "min": 5,
    "sec": 59,
    "period": 2,
    "score": "20-31",
    "teamAction": false,
    "timestamp": "20251220193219",
    "licenseId": 1186707,
    "eventUuid": "d330cc43-5994-4607-a11b-66efbfdd38a4"
  },
  {
    "idTeam": 500514,
    "actorName": "MARC GAVILAN CEREZO",
    "actorId": 8836455,
    "actorShirtNumber": "5",
    "idMove": 112,
    "move": "Entra al camp",
    "min": 5,
    "sec": 59,
    "period": 2,
    "score": "20-31",
    "teamAction": false,
    "timestamp": "20251220193219",
    "licenseId": 1196508,
    "eventUuid": "35682042-74f4-47cd-9b99-f1b6eff2041c"
  },
  {
    "idTeam": 500515,
    "actorName": "LUCAS ROSSO RAMOS",
    "actorId": 8836335,
    "actorShirtNumber": "54",
    "idMove": 115,
    "move": "Surt del camp",
    "min": 5,
    "sec": 59,
    "period": 2,
    "score": "20-31",
    "teamAction": false,
    "timestamp": "20251220193219",
    "licenseId": 1209335,
    "eventUuid": "5b0415d1-1719-4fc1-832a-a60d8fb3b924"
  },
  {
    "idTeam": 500515,
    "actorName": "ASIER SERRATO MENDIOLA",
    "actorId": 8836330,
    "actorShirtNumber": "10",
    "idMove": 115,
    "move": "Surt del camp",
    "min": 5,
    "sec": 59,
    "period": 2,
    "score": "20-31",
    "teamAction": false,
    "timestamp": "20251220193219",
    "licenseId": 1184903,
    "eventUuid": "cecd3109-02ca-4a8d-9875-a210ef2a03a9"
  },
  {
    "idTeam": 500515,
    "actorName": "LORIÉN REINÉS ASCASO",
    "actorId": 8836326,
    "actorShirtNumber": "0",
    "idMove": 112,
    "move": "Entra al camp",
    "min": 5,
    "sec": 59,
    "period": 2,
    "score": "20-31",
    "teamAction": false,
    "timestamp": "20251220193219",
    "licenseId": 1184905,
    "eventUuid": "0cd57125-834d-4086-aa89-5bc228a5bc82"
  },
  {
    "idTeam": 500515,
    "actorName": "HÉCTOR CABEZAS AISA",
    "actorId": 8836329,
    "actorShirtNumber": "7",
    "idMove": 112,
    "move": "Entra al camp",
    "min": 5,
    "sec": 59,
    "period": 2,
    "score": "20-31",
    "teamAction": false,
    "timestamp": "20251220193219",
    "licenseId": 1184907,
    "eventUuid": "ced4d729-fc2c-4445-9621-11549b684520"
  },
  {
    "idTeam": 500515,
    "actorName": "LORIÉN REINÉS ASCASO",
    "actorId": 8836326,
    "actorShirtNumber": "0",
    "idMove": 93,
    "move": "Cistella de 2",
    "min": 5,
    "sec": 39,
    "period": 2,
    "score": "20-33",
    "teamAction": false,
    "timestamp": "20251220193311",
    "licenseId": 1184905,
    "eventUuid": "92cc043e-c882-4139-8dd4-a3fd5573422e"
  },
  {
    "idTeam": 500515,
    "actorName": "HÉCTOR CABEZAS AISA",
    "actorId": 8836329,
    "actorShirtNumber": "7",
    "idMove": 93,
    "move": "Cistella de 2",
    "min": 4,
    "sec": 55,
    "period": 2,
    "score": "20-35",
    "teamAction": false,
    "timestamp": "20251220193401",
    "licenseId": 1184907,
    "eventUuid": "5b8b295b-7eb9-4b40-a371-2cec830526df"
  },
  {
    "idTeam": 500514,
    "actorName": "PAU ALVAREZ BABIO",
    "actorId": 8836456,
    "actorShirtNumber": "7",
    "idMove": 115,
    "move": "Surt del camp",
    "min": 4,
    "sec": 41,
    "period": 2,
    "score": "20-35",
    "teamAction": false,
    "timestamp": "20251220193416",
    "licenseId": 1205039,
    "eventUuid": "d27a3e5d-a54d-4f02-8af4-de2ee899651b"
  },
  {
    "idTeam": 500514,
    "actorName": "DAVID BENAIGUES OMOREGIE",
    "actorId": 8836460,
    "actorShirtNumber": "14",
    "idMove": 112,
    "move": "Entra al camp",
    "min": 4,
    "sec": 41,
    "period": 2,
    "score": "20-35",
    "teamAction": false,
    "timestamp": "20251220193416",
    "licenseId": 1186712,
    "eventUuid": "0d5bbeb8-aa09-4de9-9926-b215c63afaa7"
  },
  {
    "idTeam": 500515,
    "actorName": "IKER CAPELL DE LA FUENTE",
    "actorId": 8836334,
    "actorShirtNumber": "19",
    "idMove": 115,
    "move": "Surt del camp",
    "min": 4,
    "sec": 41,
    "period": 2,
    "score": "20-35",
    "teamAction": false,
    "timestamp": "20251220193416",
    "licenseId": 1184911,
    "eventUuid": "00eb4f6b-3bdc-4859-ad8f-5425ff01d3cf"
  },
  {
    "idTeam": 500515,
    "actorName": "FACUNDO LANFRANCONI GALLEGOS",
    "actorId": 8836332,
    "actorShirtNumber": "15",
    "idMove": 112,
    "move": "Entra al camp",
    "min": 4,
    "sec": 41,
    "period": 2,
    "score": "20-35",
    "teamAction": false,
    "timestamp": "20251220193416",
    "licenseId": 1187410,
    "eventUuid": "af8ac6b8-ec82-4f1f-9dbd-f20ca62e81dd"
  },
  {
    "idTeam": 500515,
    "actorName": "LORIÉN REINÉS ASCASO",
    "actorId": 8836326,
    "actorShirtNumber": "0",
    "idMove": 93,
    "move": "Cistella de 2",
    "min": 3,
    "sec": 32,
    "period": 2,
    "score": "20-37",
    "teamAction": false,
    "timestamp": "20251220193546",
    "licenseId": 1184905,
    "eventUuid": "e7d715de-5bbe-46dd-9194-7b81946bc28c"
  },
  {
    "idTeam": 500515,
    "actorName": "LORIÉN REINÉS ASCASO",
    "actorId": 8836326,
    "actorShirtNumber": "0",
    "idMove": 159,
    "move": "Personal, 1a falta",
    "min": 3,
    "sec": 20,
    "period": 2,
    "score": "20-37",
    "teamAction": false,
    "foulNumber": 1,
    "timestamp": "20251220193609",
    "licenseId": 1184905,
    "eventUuid": "3e920d27-9ad8-469e-9700-851cdead7f2d"
  },
  {
    "idTeam": 500515,
    "actorName": "HÉCTOR CABEZAS AISA",
    "actorId": 8836329,
    "actorShirtNumber": "7",
    "idMove": 93,
    "move": "Cistella de 2",
    "min": 3,
    "sec": 0,
    "period": 2,
    "score": "20-39",
    "teamAction": false,
    "timestamp": "20251220193639",
    "licenseId": 1184907,
    "eventUuid": "413ca748-b466-4240-a17a-8eab038ab771"
  },
  {
    "idTeam": 500515,
    "actorName": "HÉCTOR CABEZAS AISA",
    "actorId": 8836329,
    "actorShirtNumber": "7",
    "idMove": 93,
    "move": "Cistella de 2",
    "min": 2,
    "sec": 38,
    "period": 2,
    "score": "20-41",
    "teamAction": false,
    "timestamp": "20251220193702",
    "licenseId": 1184907,
    "eventUuid": "8236897e-f5d8-450c-9bec-0120eef37d3d"
  },
  {
    "idTeam": 500515,
    "actorName": "LEONARDO ANTONIO ROJAS NÚÑEZ",
    "actorId": 8836328,
    "actorShirtNumber": "4",
    "idMove": 93,
    "move": "Cistella de 2",
    "min": 2,
    "sec": 7,
    "period": 2,
    "score": "20-43",
    "teamAction": false,
    "timestamp": "20251220193732",
    "licenseId": 1195274,
    "eventUuid": "a641f724-a593-4a6f-b015-088e53b154fe"
  },
  {
    "idTeam": 500515,
    "actorName": "HÉCTOR CABEZAS AISA",
    "actorId": 8836329,
    "actorShirtNumber": "7",
    "idMove": 159,
    "move": "Personal, 1a falta",
    "min": 1,
    "sec": 48,
    "period": 2,
    "score": "20-43",
    "teamAction": false,
    "foulNumber": 1,
    "timestamp": "20251220193753",
    "licenseId": 1184907,
    "eventUuid": "911ef738-1dee-4ea1-9a0d-52df6b1ce99e"
  },
  {
    "idTeam": 500514,
    "actorName": "GUILLEM BABIO DEL AGUILA",
    "actorId": 8836458,
    "actorShirtNumber": "11",
    "idMove": 115,
    "move": "Surt del camp",
    "min": 1,
    "sec": 48,
    "period": 2,
    "score": "20-43",
    "teamAction": false,
    "timestamp": "20251220193806",
    "licenseId": 1190242,
    "eventUuid": "7668fbee-1daa-442a-a194-175f25ccc26c"
  },
  {
    "idTeam": 500514,
    "actorName": "VICTOR RODRIGUEZ ESTRADA",
    "actorId": 8836462,
    "actorShirtNumber": "33",
    "idMove": 115,
    "move": "Surt del camp",
    "min": 1,
    "sec": 48,
    "period": 2,
    "score": "20-43",
    "teamAction": false,
    "timestamp": "20251220193806",
    "licenseId": 1186710,
    "eventUuid": "123ac465-958e-4e05-8c11-1c2b4f2b52d5"
  },
  {
    "idTeam": 500514,
    "actorName": "YOUSSEF EL JAANIN ZOUADI",
    "actorId": 8836463,
    "actorShirtNumber": "40",
    "idMove": 112,
    "move": "Entra al camp",
    "min": 1,
    "sec": 48,
    "period": 2,
    "score": "20-43",
    "teamAction": false,
    "timestamp": "20251220193806",
    "licenseId": 1203013,
    "eventUuid": "7b1e4acd-ca77-4da6-9b4a-f80d4a6ef750"
  },
  {
    "idTeam": 500514,
    "actorName": "WEN ZE DONG CHEN",
    "actorId": 8836459,
    "actorShirtNumber": "13",
    "idMove": 112,
    "move": "Entra al camp",
    "min": 1,
    "sec": 48,
    "period": 2,
    "score": "20-43",
    "teamAction": false,
    "timestamp": "20251220193806",
    "licenseId": 1186707,
    "eventUuid": "db18314b-f5f7-4df7-aba7-7c091eb5d413"
  },
  {
    "idTeam": 500515,
    "actorName": "GERARD FERRER GONZÁLEZ",
    "actorId": 8836331,
    "actorShirtNumber": "13",
    "idMove": 115,
    "move": "Surt del camp",
    "min": 1,
    "sec": 48,
    "period": 2,
    "score": "20-43",
    "teamAction": false,
    "timestamp": "20251220193806",
    "licenseId": 1184909,
    "eventUuid": "afb7c7fe-9077-4cc1-b337-331bd5a0e07e"
  },
  {
    "idTeam": 500515,
    "actorName": "FRANCESC ALBIOL SERRA",
    "actorId": 8836333,
    "actorShirtNumber": "16",
    "idMove": 112,
    "move": "Entra al camp",
    "min": 1,
    "sec": 48,
    "period": 2,
    "score": "20-43",
    "teamAction": false,
    "timestamp": "20251220193806",
    "licenseId": 1184910,
    "eventUuid": "132c4dd2-ff65-449e-88fe-cf08bfcb29f6"
  },
  {
    "idTeam": 500515,
    "actorName": "HÉCTOR CABEZAS AISA",
    "actorId": 8836329,
    "actorShirtNumber": "7",
    "idMove": 161,
    "move": "Personal 2 tirs lliures, 2a falta",
    "min": 1,
    "sec": 30,
    "period": 2,
    "score": "20-43",
    "teamAction": false,
    "foulNumber": 2,
    "timestamp": "20251220193840",
    "licenseId": 1184907,
    "eventUuid": "b6844556-76a1-4168-8fc5-3833fa86b5c9"
  },
  {
    "idTeam": 500514,
    "actorName": "WEN ZE DONG CHEN",
    "actorId": 8836459,
    "actorShirtNumber": "13",
    "idMove": 96,
    "move": "Intent fallat de 1",
    "min": 1,
    "sec": 30,
    "period": 2,
    "score": "20-43",
    "teamAction": false,
    "timestamp": "20251220193856",
    "licenseId": 1186707,
    "eventUuid": "441de9f4-c90a-46ee-8d18-10853e002e44"
  },
  {
    "idTeam": 500514,
    "actorName": "WEN ZE DONG CHEN",
    "actorId": 8836459,
    "actorShirtNumber": "13",
    "idMove": 96,
    "move": "Intent fallat de 1",
    "min": 1,
    "sec": 30,
    "period": 2,
    "score": "20-43",
    "teamAction": false,
    "timestamp": "20251220193909",
    "licenseId": 1186707,
    "eventUuid": "c546a7d1-ab1a-40a9-868e-5585aeb948fd"
  },
  {
    "idTeam": 500515,
    "actorName": "HÉCTOR CABEZAS AISA",
    "actorId": 8836329,
    "actorShirtNumber": "7",
    "idMove": 93,
    "move": "Cistella de 2",
    "min": 1,
    "sec": 20,
    "period": 2,
    "score": "20-45",
    "teamAction": false,
    "timestamp": "20251220193922",
    "licenseId": 1184907,
    "eventUuid": "b1ef6228-d6aa-42e9-9609-69e63ca92007"
  },
  {
    "idTeam": 500515,
    "actorName": "LEONARDO ANTONIO ROJAS NÚÑEZ",
    "actorId": 8836328,
    "actorShirtNumber": "4",
    "idMove": 93,
    "move": "Cistella de 2",
    "min": 0,
    "sec": 42,
    "period": 2,
    "score": "20-47",
    "teamAction": false,
    "timestamp": "20251220194024",
    "licenseId": 1195274,
    "eventUuid": "5fd8756f-b1eb-4553-8171-4c59755431df"
  },
  {
    "idTeam": 500514,
    "actorName": "EMILIO IZQUIERDO REINA",
    "actorId": 8836461,
    "actorShirtNumber": "25",
    "idMove": 93,
    "move": "Cistella de 2",
    "min": 0,
    "sec": 12,
    "period": 2,
    "score": "22-47",
    "teamAction": false,
    "timestamp": "20251220194054",
    "licenseId": 1190250,
    "eventUuid": "3b6ba314-9ffc-47fb-b4e5-8384262cc7ab"
  },
  {
    "idTeam": 0,
    "actorName": "",
    "actorId": 0,
    "actorShirtNumber": "",
    "idMove": 116,
    "move": "Final de període",
    "min": 0,
    "sec": 0,
    "period": 2,
    "score": "22-47",
    "teamAction": true,
    "timestamp": "20251220194116",
    "eventUuid": "0706fc54-cc35-49b0-919d-3a42a98f5f9f"
  },
  {
    "idTeam": 500514,
    "actorName": "MARC GAVILAN CEREZO",
    "actorId": 8836455,
    "actorShirtNumber": "5",
    "idMove": 115,
    "move": "Surt del camp",
    "min": 10,
    "sec": 0,
    "period": 3,
    "score": "22-47",
    "teamAction": false,
    "timestamp": "20251220194856",
    "licenseId": 1196508,
    "eventUuid": "e2b6eac1-b924-4996-b0ce-5f4d74501c60"
  },
  {
    "idTeam": 500514,
    "actorName": "YOUSSEF EL JAANIN ZOUADI",
    "actorId": 8836463,
    "actorShirtNumber": "40",
    "idMove": 115,
    "move": "Surt del camp",
    "min": 10,
    "sec": 0,
    "period": 3,
    "score": "22-47",
    "teamAction": false,
    "timestamp": "20251220194856",
    "licenseId": 1203013,
    "eventUuid": "14eaec8c-d46c-419b-9e11-ffaee0aa3756"
  },
  {
    "idTeam": 500514,
    "actorName": "YASSIN AHAIDAR EL MEZRAOUI",
    "actorId": 8836465,
    "actorShirtNumber": "59",
    "idMove": 112,
    "move": "Entra al camp",
    "min": 10,
    "sec": 0,
    "period": 3,
    "score": "22-47",
    "teamAction": false,
    "timestamp": "20251220194856",
    "licenseId": 1186704,
    "eventUuid": "28ed232f-9bdf-4ccd-8bbe-9d5bdb9c8c6a"
  },
  {
    "idTeam": 500514,
    "actorName": "GUILLEM BABIO DEL AGUILA",
    "actorId": 8836458,
    "actorShirtNumber": "11",
    "idMove": 112,
    "move": "Entra al camp",
    "min": 10,
    "sec": 0,
    "period": 3,
    "score": "22-47",
    "teamAction": false,
    "timestamp": "20251220194856",
    "licenseId": 1190242,
    "eventUuid": "0d281fba-3410-47cf-96ff-e155f9484037"
  },
  {
    "idTeam": 500515,
    "actorName": "FACUNDO LANFRANCONI GALLEGOS",
    "actorId": 8836332,
    "actorShirtNumber": "15",
    "idMove": 115,
    "move": "Surt del camp",
    "min": 10,
    "sec": 0,
    "period": 3,
    "score": "22-47",
    "teamAction": false,
    "timestamp": "20251220194856",
    "licenseId": 1187410,
    "eventUuid": "06388f15-a636-4d5a-9833-c78ab8eaecce"
  },
  {
    "idTeam": 500515,
    "actorName": "GERARD FERRER GONZÁLEZ",
    "actorId": 8836331,
    "actorShirtNumber": "13",
    "idMove": 112,
    "move": "Entra al camp",
    "min": 10,
    "sec": 0,
    "period": 3,
    "score": "22-47",
    "teamAction": false,
    "timestamp": "20251220194856",
    "licenseId": 1184909,
    "eventUuid": "8c2d0133-d198-4b44-a6f7-cdd1c85717e2"
  },
  {
    "idTeam": 500515,
    "actorName": "GERARD FERRER GONZÁLEZ",
    "actorId": 8836331,
    "actorShirtNumber": "13",
    "idMove": 94,
    "move": "Cistella de 3",
    "min": 9,
    "sec": 28,
    "period": 3,
    "score": "22-50",
    "teamAction": false,
    "timestamp": "20251220195025",
    "licenseId": 1184909,
    "eventUuid": "f34c223f-a6c2-43c2-8cbb-fc53413b18d4"
  },
  {
    "idTeam": 500515,
    "actorName": "FRANCESC ALBIOL SERRA",
    "actorId": 8836333,
    "actorShirtNumber": "16",
    "idMove": 93,
    "move": "Cistella de 2",
    "min": 9,
    "sec": 2,
    "period": 3,
    "score": "22-52",
    "teamAction": false,
    "timestamp": "20251220195052",
    "licenseId": 1184910,
    "eventUuid": "d62cf29c-6852-424e-95f0-d7572cc188a3"
  },
  {
    "idTeam": 500515,
    "actorName": "FRANCESC ALBIOL SERRA",
    "actorId": 8836333,
    "actorShirtNumber": "16",
    "idMove": 159,
    "move": "Personal, 3a falta",
    "min": 8,
    "sec": 26,
    "period": 3,
    "score": "22-52",
    "teamAction": false,
    "foulNumber": 3,
    "timestamp": "20251220195158",
    "licenseId": 1184910,
    "eventUuid": "98dabc03-f04c-4d1b-91b9-b8e671388a8b"
  },
  {
    "idTeam": 500515,
    "actorName": "LEONARDO ANTONIO ROJAS NÚÑEZ",
    "actorId": 8836328,
    "actorShirtNumber": "4",
    "idMove": 93,
    "move": "Cistella de 2",
    "min": 8,
    "sec": 12,
    "period": 3,
    "score": "22-54",
    "teamAction": false,
    "timestamp": "20251220195216",
    "licenseId": 1195274,
    "eventUuid": "a24cc020-7522-4790-9a57-21059556ca68"
  },
  {
    "idTeam": 500514,
    "actorName": "YASSIN AHAIDAR EL MEZRAOUI",
    "actorId": 8836465,
    "actorShirtNumber": "59",
    "idMove": 159,
    "move": "Personal, 1a falta",
    "min": 7,
    "sec": 55,
    "period": 3,
    "score": "22-54",
    "teamAction": false,
    "foulNumber": 1,
    "timestamp": "20251220195236",
    "licenseId": 1186704,
    "eventUuid": "41f0d9c2-5a2a-4c63-a7f5-fbbcb8dca818"
  },
  {
    "idTeam": 500515,
    "actorName": "FRANCESC ALBIOL SERRA",
    "actorId": 8836333,
    "actorShirtNumber": "16",
    "idMove": 115,
    "move": "Surt del camp",
    "min": 7,
    "sec": 55,
    "period": 3,
    "score": "22-54",
    "teamAction": false,
    "timestamp": "20251220195239",
    "licenseId": 1184910,
    "eventUuid": "d5b5647e-d910-4bbb-93f7-e3f2592a7e31"
  },
  {
    "idTeam": 500515,
    "actorName": "IKER CAPELL DE LA FUENTE",
    "actorId": 8836334,
    "actorShirtNumber": "19",
    "idMove": 112,
    "move": "Entra al camp",
    "min": 7,
    "sec": 55,
    "period": 3,
    "score": "22-54",
    "teamAction": false,
    "timestamp": "20251220195239",
    "licenseId": 1184911,
    "eventUuid": "dadf0905-50cc-4cfa-84ad-ee5465f76284"
  },
  {
    "idTeam": 500514,
    "actorName": "DAVID BENAIGUES OMOREGIE",
    "actorId": 8836460,
    "actorShirtNumber": "14",
    "idMove": 115,
    "move": "Surt del camp",
    "min": 7,
    "sec": 49,
    "period": 3,
    "score": "22-54",
    "teamAction": false,
    "timestamp": "20251220195318",
    "licenseId": 1186712,
    "eventUuid": "ee74edf9-8874-43f7-98e0-03a91edd6485"
  },
  {
    "idTeam": 500514,
    "actorName": "MARC GAVILAN CEREZO",
    "actorId": 8836455,
    "actorShirtNumber": "5",
    "idMove": 112,
    "move": "Entra al camp",
    "min": 7,
    "sec": 49,
    "period": 3,
    "score": "22-54",
    "teamAction": false,
    "timestamp": "20251220195318",
    "licenseId": 1196508,
    "eventUuid": "ab089bb5-483c-4ccf-af84-6dbfce4f6d09"
  },
  {
    "idTeam": 500515,
    "actorName": "LORIÉN REINÉS ASCASO",
    "actorId": 8836326,
    "actorShirtNumber": "0",
    "idMove": 93,
    "move": "Cistella de 2",
    "min": 7,
    "sec": 27,
    "period": 3,
    "score": "22-56",
    "teamAction": false,
    "timestamp": "20251220195356",
    "licenseId": 1184905,
    "eventUuid": "da822f86-d44e-4e51-85c9-49df7050404f"
  },
  {
    "idTeam": 500514,
    "actorName": "EMILIO IZQUIERDO REINA",
    "actorId": 8836461,
    "actorShirtNumber": "25",
    "idMove": 93,
    "move": "Cistella de 2",
    "min": 7,
    "sec": 11,
    "period": 3,
    "score": "24-56",
    "teamAction": false,
    "timestamp": "20251220195413",
    "licenseId": 1190250,
    "eventUuid": "31eaec17-0ea6-4f86-99eb-0e5818e85442"
  },
  {
    "idTeam": 500514,
    "actorName": "YASSIN AHAIDAR EL MEZRAOUI",
    "actorId": 8836465,
    "actorShirtNumber": "59",
    "idMove": 161,
    "move": "Personal 2 tirs lliures, 2a falta",
    "min": 6,
    "sec": 59,
    "period": 3,
    "score": "24-56",
    "teamAction": false,
    "foulNumber": 2,
    "timestamp": "20251220195428",
    "licenseId": 1186704,
    "eventUuid": "46705d4c-f220-4aa8-a053-dac9c0b52555"
  },
  {
    "idTeam": 500515,
    "actorName": "LEONARDO ANTONIO ROJAS NÚÑEZ",
    "actorId": 8836328,
    "actorShirtNumber": "4",
    "idMove": 92,
    "move": "Cistella de 1",
    "min": 6,
    "sec": 59,
    "period": 3,
    "score": "24-57",
    "teamAction": false,
    "timestamp": "20251220195446",
    "licenseId": 1195274,
    "eventUuid": "6d4eddd4-0d18-4472-b42d-250ec61b0d22"
  },
  {
    "idTeam": 500515,
    "actorName": "LEONARDO ANTONIO ROJAS NÚÑEZ",
    "actorId": 8836328,
    "actorShirtNumber": "4",
    "idMove": 92,
    "move": "Cistella de 1",
    "min": 6,
    "sec": 59,
    "period": 3,
    "score": "24-58",
    "teamAction": false,
    "timestamp": "20251220195500",
    "licenseId": 1195274,
    "eventUuid": "23d1c003-0991-4cf9-82ab-085e562dbfdf"
  },
  {
    "idTeam": 500514,
    "actorName": "EMILIO IZQUIERDO REINA",
    "actorId": 8836461,
    "actorShirtNumber": "25",
    "idMove": 159,
    "move": "Personal, 3a falta",
    "min": 6,
    "sec": 52,
    "period": 3,
    "score": "24-58",
    "teamAction": false,
    "foulNumber": 3,
    "timestamp": "20251220195514",
    "licenseId": 1190250,
    "eventUuid": "40e21604-adb5-4a74-a396-5a72c0a2c670"
  },
  {
    "idTeam": 500514,
    "actorName": "MARC GAVILAN CEREZO",
    "actorId": 8836455,
    "actorShirtNumber": "5",
    "idMove": 115,
    "move": "Surt del camp",
    "min": 6,
    "sec": 52,
    "period": 3,
    "score": "24-58",
    "teamAction": false,
    "timestamp": "20251220195523",
    "licenseId": 1196508,
    "eventUuid": "8c4e2d65-0e6c-4f2f-84f8-b1c97e5c0e4a"
  },
  {
    "idTeam": 500514,
    "actorName": "MARCOS MARTIN MARTINEZ",
    "actorId": 8836454,
    "actorShirtNumber": "3",
    "idMove": 112,
    "move": "Entra al camp",
    "min": 6,
    "sec": 52,
    "period": 3,
    "score": "24-58",
    "teamAction": false,
    "timestamp": "20251220195523",
    "licenseId": 1201434,
    "eventUuid": "81452484-6870-4cea-add4-56f8218fe174"
  },
  {
    "idTeam": 500515,
    "actorName": "HÉCTOR CABEZAS AISA",
    "actorId": 8836329,
    "actorShirtNumber": "7",
    "idMove": 115,
    "move": "Surt del camp",
    "min": 6,
    "sec": 18,
    "period": 3,
    "score": "24-58",
    "teamAction": false,
    "timestamp": "20251220195605",
    "licenseId": 1184907,
    "eventUuid": "3e1802b7-3b6d-4253-9058-860db976e22f"
  },
  {
    "idTeam": 500515,
    "actorName": "ASIER SERRATO MENDIOLA",
    "actorId": 8836330,
    "actorShirtNumber": "10",
    "idMove": 112,
    "move": "Entra al camp",
    "min": 6,
    "sec": 18,
    "period": 3,
    "score": "24-58",
    "teamAction": false,
    "timestamp": "20251220195605",
    "licenseId": 1184903,
    "eventUuid": "524e4d8c-229a-41c9-98a8-11d6a6bfceda"
  },
  {
    "idTeam": 500514,
    "actorName": "MARCOS MARTIN MARTINEZ",
    "actorId": 8836454,
    "actorShirtNumber": "3",
    "idMove": 159,
    "move": "Personal, 1a falta",
    "min": 6,
    "sec": 5,
    "period": 3,
    "score": "24-58",
    "teamAction": false,
    "foulNumber": 1,
    "timestamp": "20251220195641",
    "licenseId": 1201434,
    "eventUuid": "61f2c225-4abb-492d-ab50-2a481109bdc5"
  },
  {
    "idTeam": 500514,
    "actorName": "EMILIO IZQUIERDO REINA",
    "actorId": 8836461,
    "actorShirtNumber": "25",
    "idMove": 93,
    "move": "Cistella de 2",
    "min": 5,
    "sec": 57,
    "period": 3,
    "score": "26-58",
    "teamAction": false,
    "timestamp": "20251220195706",
    "licenseId": 1190250,
    "eventUuid": "18c60879-c6a0-4fa1-a53e-3c2f31ac3e9a"
  },
  {
    "idTeam": 500514,
    "actorName": "WEN ZE DONG CHEN",
    "actorId": 8836459,
    "actorShirtNumber": "13",
    "idMove": 161,
    "move": "Personal 2 tirs lliures, 1a falta",
    "min": 5,
    "sec": 38,
    "period": 3,
    "score": "26-58",
    "teamAction": false,
    "foulNumber": 1,
    "timestamp": "20251220195728",
    "licenseId": 1186707,
    "eventUuid": "47a66dbc-3478-4364-b0d4-5f045057c517"
  },
  {
    "idTeam": 500515,
    "actorName": "LORIÉN REINÉS ASCASO",
    "actorId": 8836326,
    "actorShirtNumber": "0",
    "idMove": 115,
    "move": "Surt del camp",
    "min": 5,
    "sec": 38,
    "period": 3,
    "score": "26-58",
    "teamAction": false,
    "timestamp": "20251220195731",
    "licenseId": 1184905,
    "eventUuid": "2998c531-7e81-4110-aff1-d7ff5257c893"
  },
  {
    "idTeam": 500515,
    "actorName": "LEONARDO ANTONIO ROJAS NÚÑEZ",
    "actorId": 8836328,
    "actorShirtNumber": "4",
    "idMove": 115,
    "move": "Surt del camp",
    "min": 5,
    "sec": 38,
    "period": 3,
    "score": "26-58",
    "teamAction": false,
    "timestamp": "20251220195731",
    "licenseId": 1195274,
    "eventUuid": "eb08cc7b-86d6-4f43-a892-4575d74670fe"
  },
  {
    "idTeam": 500515,
    "actorName": "LUCAS ROSSO RAMOS",
    "actorId": 8836335,
    "actorShirtNumber": "54",
    "idMove": 112,
    "move": "Entra al camp",
    "min": 5,
    "sec": 38,
    "period": 3,
    "score": "26-58",
    "teamAction": false,
    "timestamp": "20251220195731",
    "licenseId": 1209335,
    "eventUuid": "028ca45d-6d5a-4e77-96a0-9c7afc94bb64"
  },
  {
    "idTeam": 500515,
    "actorName": "FACUNDO LANFRANCONI GALLEGOS",
    "actorId": 8836332,
    "actorShirtNumber": "15",
    "idMove": 112,
    "move": "Entra al camp",
    "min": 5,
    "sec": 38,
    "period": 3,
    "score": "26-58",
    "teamAction": false,
    "timestamp": "20251220195731",
    "licenseId": 1187410,
    "eventUuid": "c6eebfd6-2cbd-404a-91ac-82989265744d"
  },
  {
    "idTeam": 500515,
    "actorName": "GERARD FERRER GONZÁLEZ",
    "actorId": 8836331,
    "actorShirtNumber": "13",
    "idMove": 92,
    "move": "Cistella de 1",
    "min": 5,
    "sec": 38,
    "period": 3,
    "score": "26-59",
    "teamAction": false,
    "timestamp": "20251220195804",
    "licenseId": 1184909,
    "eventUuid": "0bdfe138-1652-4d9a-8a46-342e0033431d"
  },
  {
    "idTeam": 500515,
    "actorName": "GERARD FERRER GONZÁLEZ",
    "actorId": 8836331,
    "actorShirtNumber": "13",
    "idMove": 96,
    "move": "Intent fallat de 1",
    "min": 5,
    "sec": 38,
    "period": 3,
    "score": "26-59",
    "teamAction": false,
    "timestamp": "20251220195819",
    "licenseId": 1184909,
    "eventUuid": "4eca70a7-2393-4ae9-a5a3-de3e06ad0250"
  },
  {
    "idTeam": 500515,
    "actorName": "LUCAS ROSSO RAMOS",
    "actorId": 8836335,
    "actorShirtNumber": "54",
    "idMove": 159,
    "move": "Personal, 1a falta",
    "min": 5,
    "sec": 33,
    "period": 3,
    "score": "26-59",
    "teamAction": false,
    "foulNumber": 1,
    "timestamp": "20251220195831",
    "licenseId": 1209335,
    "eventUuid": "1a3f4340-efbc-4b76-9a16-718f619e80ae"
  },
  {
    "idTeam": 500514,
    "actorName": "GUILLEM BABIO DEL AGUILA",
    "actorId": 8836458,
    "actorShirtNumber": "11",
    "idMove": 115,
    "move": "Surt del camp",
    "min": 5,
    "sec": 33,
    "period": 3,
    "score": "26-59",
    "teamAction": false,
    "timestamp": "20251220195835",
    "licenseId": 1190242,
    "eventUuid": "6e415237-bb68-467e-bf49-c655610b8376"
  },
  {
    "idTeam": 500514,
    "actorName": "YOUSSEF EL JAANIN ZOUADI",
    "actorId": 8836463,
    "actorShirtNumber": "40",
    "idMove": 112,
    "move": "Entra al camp",
    "min": 5,
    "sec": 33,
    "period": 3,
    "score": "26-59",
    "teamAction": false,
    "timestamp": "20251220195835",
    "licenseId": 1203013,
    "eventUuid": "35727b48-a25e-4592-a36b-90671bd22326"
  },
  {
    "idTeam": 500515,
    "actorName": "LUCAS ROSSO RAMOS",
    "actorId": 8836335,
    "actorShirtNumber": "54",
    "idMove": 93,
    "move": "Cistella de 2",
    "min": 5,
    "sec": 6,
    "period": 3,
    "score": "26-61",
    "teamAction": false,
    "timestamp": "20251220195920",
    "licenseId": 1209335,
    "eventUuid": "aa7f0757-0b17-4e88-aed6-bdffc1ef0d80"
  },
  {
    "idTeam": 500515,
    "actorName": "GERARD FERRER GONZÁLEZ",
    "actorId": 8836331,
    "actorShirtNumber": "13",
    "idMove": 93,
    "move": "Cistella de 2",
    "min": 5,
    "sec": 6,
    "period": 3,
    "score": "26-63",
    "teamAction": false,
    "timestamp": "20251220195947",
    "licenseId": 1184909,
    "eventUuid": "4a9fcf9f-2edb-4f46-8000-1b69d5ac267d"
  },
  {
    "idTeam": 500514,
    "actorName": "YASSIN AHAIDAR EL MEZRAOUI",
    "actorId": 8836465,
    "actorShirtNumber": "59",
    "idMove": 115,
    "move": "Surt del camp",
    "min": 5,
    "sec": 6,
    "period": 3,
    "score": "26-63",
    "teamAction": false,
    "timestamp": "20251220195956",
    "licenseId": 1186704,
    "eventUuid": "932fc38b-5adb-4c80-a63d-296763a39c0a"
  },
  {
    "idTeam": 500514,
    "actorName": "PAU ALVAREZ BABIO",
    "actorId": 8836456,
    "actorShirtNumber": "7",
    "idMove": 112,
    "move": "Entra al camp",
    "min": 5,
    "sec": 6,
    "period": 3,
    "score": "26-63",
    "teamAction": false,
    "timestamp": "20251220195956",
    "licenseId": 1205039,
    "eventUuid": "7f9d701b-9082-4f86-a6cd-d9062be6d1a9"
  },
  {
    "idTeam": 500514,
    "actorName": "YOUSSEF EL JAANIN ZOUADI",
    "actorId": 8836463,
    "actorShirtNumber": "40",
    "idMove": 161,
    "move": "Personal 2 tirs lliures, 2a falta",
    "min": 3,
    "sec": 30,
    "period": 3,
    "score": "26-63",
    "teamAction": false,
    "foulNumber": 2,
    "timestamp": "20251220200137",
    "licenseId": 1203013,
    "eventUuid": "daaa861c-ca32-439d-aa04-97135eeb8ead"
  },
  {
    "idTeam": 500515,
    "actorName": "IKER CAPELL DE LA FUENTE",
    "actorId": 8836334,
    "actorShirtNumber": "19",
    "idMove": 92,
    "move": "Cistella de 1",
    "min": 3,
    "sec": 30,
    "period": 3,
    "score": "26-64",
    "teamAction": false,
    "timestamp": "20251220200202",
    "licenseId": 1184911,
    "eventUuid": "8c8ab7f3-fedc-48c9-957c-5e76b0ec8cec"
  },
  {
    "idTeam": 500515,
    "actorName": "IKER CAPELL DE LA FUENTE",
    "actorId": 8836334,
    "actorShirtNumber": "19",
    "idMove": 92,
    "move": "Cistella de 1",
    "min": 3,
    "sec": 30,
    "period": 3,
    "score": "26-65",
    "teamAction": false,
    "timestamp": "20251220200206",
    "licenseId": 1184911,
    "eventUuid": "18d660b7-2948-4ae8-b82d-21d4f1e7ce29"
  },
  {
    "idTeam": 500515,
    "actorName": "ASIER SERRATO MENDIOLA",
    "actorId": 8836330,
    "actorShirtNumber": "10",
    "idMove": 93,
    "move": "Cistella de 2",
    "min": 3,
    "sec": 2,
    "period": 3,
    "score": "26-67",
    "teamAction": false,
    "timestamp": "20251220200235",
    "licenseId": 1184903,
    "eventUuid": "57e7657a-f961-4186-8f80-7e083b97ea1f"
  },
  {
    "idTeam": 500515,
    "actorName": "GERARD FERRER GONZÁLEZ",
    "actorId": 8836331,
    "actorShirtNumber": "13",
    "idMove": 115,
    "move": "Surt del camp",
    "min": 2,
    "sec": 23,
    "period": 3,
    "score": "26-67",
    "teamAction": false,
    "timestamp": "20251220200315",
    "licenseId": 1184909,
    "eventUuid": "6d948008-ac3c-4c9b-8a8b-9a4935f2111d"
  },
  {
    "idTeam": 500515,
    "actorName": "FRANCESC ALBIOL SERRA",
    "actorId": 8836333,
    "actorShirtNumber": "16",
    "idMove": 112,
    "move": "Entra al camp",
    "min": 2,
    "sec": 23,
    "period": 3,
    "score": "26-67",
    "teamAction": false,
    "timestamp": "20251220200315",
    "licenseId": 1184910,
    "eventUuid": "21269096-54fb-4502-b61f-7e3a894dac09"
  },
  {
    "idTeam": 500514,
    "actorName": "YOUSSEF EL JAANIN ZOUADI",
    "actorId": 8836463,
    "actorShirtNumber": "40",
    "idMove": 93,
    "move": "Cistella de 2",
    "min": 2,
    "sec": 6,
    "period": 3,
    "score": "28-67",
    "teamAction": false,
    "timestamp": "20251220200403",
    "licenseId": 1203013,
    "eventUuid": "6d110a06-3745-4b08-85aa-3473dffb729d"
  },
  {
    "idTeam": 500515,
    "actorName": "LUCAS ROSSO RAMOS",
    "actorId": 8836335,
    "actorShirtNumber": "54",
    "idMove": 93,
    "move": "Cistella de 2",
    "min": 1,
    "sec": 45,
    "period": 3,
    "score": "28-69",
    "teamAction": false,
    "timestamp": "20251220200424",
    "licenseId": 1209335,
    "eventUuid": "0125176d-0628-4e47-8491-e36f19bc738b"
  },
  {
    "idTeam": 500515,
    "actorName": "LUCAS ROSSO RAMOS",
    "actorId": 8836335,
    "actorShirtNumber": "54",
    "idMove": 161,
    "move": "Personal 2 tirs lliures, 2a falta",
    "min": 1,
    "sec": 35,
    "period": 3,
    "score": "28-69",
    "teamAction": false,
    "foulNumber": 2,
    "timestamp": "20251220200437",
    "licenseId": 1209335,
    "eventUuid": "12a09498-fca4-4961-8744-e897f6bc4525"
  },
  {
    "idTeam": 500514,
    "actorName": "YOUSSEF EL JAANIN ZOUADI",
    "actorId": 8836463,
    "actorShirtNumber": "40",
    "idMove": 92,
    "move": "Cistella de 1",
    "min": 1,
    "sec": 35,
    "period": 3,
    "score": "29-69",
    "teamAction": false,
    "timestamp": "20251220200453",
    "licenseId": 1203013,
    "eventUuid": "3be11786-8389-423b-bdea-360f4b82fa7d"
  },
  {
    "idTeam": 500514,
    "actorName": "YOUSSEF EL JAANIN ZOUADI",
    "actorId": 8836463,
    "actorShirtNumber": "40",
    "idMove": 96,
    "move": "Intent fallat de 1",
    "min": 1,
    "sec": 35,
    "period": 3,
    "score": "29-69",
    "teamAction": false,
    "timestamp": "20251220200509",
    "licenseId": 1203013,
    "eventUuid": "4fd65e3b-8a23-4845-b4a6-07795d8f8d09"
  },
  {
    "idTeam": 500515,
    "actorName": "IKER CAPELL DE LA FUENTE",
    "actorId": 8836334,
    "actorShirtNumber": "19",
    "idMove": 93,
    "move": "Cistella de 2",
    "min": 1,
    "sec": 27,
    "period": 3,
    "score": "29-71",
    "teamAction": false,
    "timestamp": "20251220200519",
    "licenseId": 1184911,
    "eventUuid": "62fad8d0-eb80-4d09-84ca-01c62d702310"
  },
  {
    "idTeam": 500515,
    "actorName": "FRANCESC ALBIOL SERRA",
    "actorId": 8836333,
    "actorShirtNumber": "16",
    "idMove": 161,
    "move": "Personal 2 tirs lliures, 4a falta",
    "min": 1,
    "sec": 11,
    "period": 3,
    "score": "29-71",
    "teamAction": false,
    "foulNumber": 4,
    "timestamp": "20251220200540",
    "licenseId": 1184910,
    "eventUuid": "ca7a07d7-ad8b-4eb0-af9b-e993e5c503df"
  },
  {
    "idTeam": 500514,
    "actorName": "PAU ALVAREZ BABIO",
    "actorId": 8836456,
    "actorShirtNumber": "7",
    "idMove": 115,
    "move": "Surt del camp",
    "min": 1,
    "sec": 11,
    "period": 3,
    "score": "29-71",
    "teamAction": false,
    "timestamp": "20251220200546",
    "licenseId": 1205039,
    "eventUuid": "ca38a4da-f5f3-48d0-920b-2f6263bd0f6b"
  },
  {
    "idTeam": 500514,
    "actorName": "GUILLEM BABIO DEL AGUILA",
    "actorId": 8836458,
    "actorShirtNumber": "11",
    "idMove": 112,
    "move": "Entra al camp",
    "min": 1,
    "sec": 11,
    "period": 3,
    "score": "29-71",
    "teamAction": false,
    "timestamp": "20251220200546",
    "licenseId": 1190242,
    "eventUuid": "f2cd247a-b000-4312-9340-8eb989aa725a"
  },
  {
    "idTeam": 500514,
    "actorName": "WEN ZE DONG CHEN",
    "actorId": 8836459,
    "actorShirtNumber": "13",
    "idMove": 92,
    "move": "Cistella de 1",
    "min": 1,
    "sec": 11,
    "period": 3,
    "score": "30-71",
    "teamAction": false,
    "timestamp": "20251220200605",
    "licenseId": 1186707,
    "eventUuid": "96d060f4-dea9-477f-81c7-0040d5d85cc6"
  },
  {
    "idTeam": 500514,
    "actorName": "WEN ZE DONG CHEN",
    "actorId": 8836459,
    "actorShirtNumber": "13",
    "idMove": 96,
    "move": "Intent fallat de 1",
    "min": 1,
    "sec": 11,
    "period": 3,
    "score": "30-71",
    "teamAction": false,
    "timestamp": "20251220200610",
    "licenseId": 1186707,
    "eventUuid": "d0ad8176-dcb2-4a30-9b43-233d52f9b909"
  },
  {
    "idTeam": 500514,
    "actorName": "EMILIO IZQUIERDO REINA",
    "actorId": 8836461,
    "actorShirtNumber": "25",
    "idMove": 93,
    "move": "Cistella de 2",
    "min": 1,
    "sec": 9,
    "period": 3,
    "score": "32-71",
    "teamAction": false,
    "timestamp": "20251220200614",
    "licenseId": 1190250,
    "eventUuid": "06567619-c657-4795-9d3c-9a75498502a4"
  },
  {
    "idTeam": 500515,
    "actorName": "IKER CAPELL DE LA FUENTE",
    "actorId": 8836334,
    "actorShirtNumber": "19",
    "idMove": 93,
    "move": "Cistella de 2",
    "min": 1,
    "sec": 0,
    "period": 3,
    "score": "32-73",
    "teamAction": false,
    "timestamp": "20251220200623",
    "licenseId": 1184911,
    "eventUuid": "6c268d3d-9b5a-4a25-ae20-63d079dbb6ea"
  },
  {
    "idTeam": 500515,
    "actorName": "FRANCESC ALBIOL SERRA",
    "actorId": 8836333,
    "actorShirtNumber": "16",
    "idMove": 115,
    "move": "Surt del camp",
    "min": 0,
    "sec": 43,
    "period": 3,
    "score": "32-73",
    "teamAction": false,
    "timestamp": "20251220200641",
    "licenseId": 1184910,
    "eventUuid": "94f14b2d-776f-48c6-abd8-2dcf2a9d26ec"
  },
  {
    "idTeam": 500515,
    "actorName": "LEONARDO ANTONIO ROJAS NÚÑEZ",
    "actorId": 8836328,
    "actorShirtNumber": "4",
    "idMove": 112,
    "move": "Entra al camp",
    "min": 0,
    "sec": 43,
    "period": 3,
    "score": "32-73",
    "teamAction": false,
    "timestamp": "20251220200641",
    "licenseId": 1195274,
    "eventUuid": "6ec8287a-5f26-4d1f-b2c9-745f84ceaa33"
  },
  {
    "idTeam": 500514,
    "actorName": "WEN ZE DONG CHEN",
    "actorId": 8836459,
    "actorShirtNumber": "13",
    "idMove": 161,
    "move": "Personal 2 tirs lliures, 2a falta",
    "min": 0,
    "sec": 30,
    "period": 3,
    "score": "32-73",
    "teamAction": false,
    "foulNumber": 2,
    "timestamp": "20251220200718",
    "licenseId": 1186707,
    "eventUuid": "80fc6cf3-64b1-4a94-bbdf-451d91b513ac"
  },
  {
    "idTeam": 500515,
    "actorName": "LEONARDO ANTONIO ROJAS NÚÑEZ",
    "actorId": 8836328,
    "actorShirtNumber": "4",
    "idMove": 96,
    "move": "Intent fallat de 1",
    "min": 0,
    "sec": 30,
    "period": 3,
    "score": "32-73",
    "teamAction": false,
    "timestamp": "20251220200738",
    "licenseId": 1195274,
    "eventUuid": "730c9974-22e4-46fc-b088-8f231542988c"
  },
  {
    "idTeam": 500515,
    "actorName": "LEONARDO ANTONIO ROJAS NÚÑEZ",
    "actorId": 8836328,
    "actorShirtNumber": "4",
    "idMove": 92,
    "move": "Cistella de 1",
    "min": 0,
    "sec": 30,
    "period": 3,
    "score": "32-74",
    "teamAction": false,
    "timestamp": "20251220200751",
    "licenseId": 1195274,
    "eventUuid": "46f137db-3654-46f7-a471-2457d414cd17"
  },
  {
    "idTeam": 500515,
    "actorName": "LEONARDO ANTONIO ROJAS NÚÑEZ",
    "actorId": 8836328,
    "actorShirtNumber": "4",
    "idMove": 93,
    "move": "Cistella de 2",
    "min": 0,
    "sec": 14,
    "period": 3,
    "score": "32-76",
    "teamAction": false,
    "timestamp": "20251220200817",
    "licenseId": 1195274,
    "eventUuid": "2e2fa293-8219-4188-9108-bd8a76866548"
  },
  {
    "idTeam": 500514,
    "actorName": "EMILIO IZQUIERDO REINA",
    "actorId": 8836461,
    "actorShirtNumber": "25",
    "idMove": 93,
    "move": "Cistella de 2",
    "min": 0,
    "sec": 2,
    "period": 3,
    "score": "34-76",
    "teamAction": false,
    "timestamp": "20251220200829",
    "licenseId": 1190250,
    "eventUuid": "cbfbca27-3ca7-4797-b327-702a37829d81"
  },
  {
    "idTeam": 500514,
    "actorName": "EMILIO IZQUIERDO REINA",
    "actorId": 8836461,
    "actorShirtNumber": "25",
    "idMove": 160,
    "move": "Personal 1 tir lliure, 4a falta",
    "min": 0,
    "sec": 0,
    "period": 3,
    "score": "34-76",
    "teamAction": false,
    "foulNumber": 4,
    "timestamp": "20251220200841",
    "licenseId": 1190250,
    "eventUuid": "08022075-7ff4-4a92-b7d6-4177cc84c487"
  },
  {
    "idTeam": 500515,
    "actorName": "LUCAS ROSSO RAMOS",
    "actorId": 8836335,
    "actorShirtNumber": "54",
    "idMove": 93,
    "move": "Cistella de 2",
    "min": 0,
    "sec": 0,
    "period": 3,
    "score": "34-78",
    "teamAction": false,
    "timestamp": "20251220200850",
    "licenseId": 1209335,
    "eventUuid": "37908caf-ebbd-444d-9a26-b488a0291510"
  },
  {
    "idTeam": 500515,
    "actorName": "LUCAS ROSSO RAMOS",
    "actorId": 8836335,
    "actorShirtNumber": "54",
    "idMove": 96,
    "move": "Intent fallat de 1",
    "min": 0,
    "sec": 0,
    "period": 3,
    "score": "34-78",
    "teamAction": false,
    "timestamp": "20251220200858",
    "licenseId": 1209335,
    "eventUuid": "1f261022-90a5-47bd-8770-f0bcf8baa4bf"
  },
  {
    "idTeam": 0,
    "actorName": "",
    "actorId": 0,
    "actorShirtNumber": "",
    "idMove": 116,
    "move": "Final de període",
    "min": 0,
    "sec": 0,
    "period": 3,
    "score": "34-78",
    "teamAction": true,
    "timestamp": "20251220200923",
    "eventUuid": "4aa123f7-1f1a-4acb-bf51-ca0f27d8b7de"
  },
  {
    "idTeam": 500515,
    "actorName": "LEONARDO ANTONIO ROJAS NÚÑEZ",
    "actorId": 8836328,
    "actorShirtNumber": "4",
    "idMove": 94,
    "move": "Cistella de 3",
    "min": 9,
    "sec": 49,
    "period": 4,
    "score": "34-81",
    "teamAction": false,
    "timestamp": "20251220201047",
    "licenseId": 1195274,
    "eventUuid": "cc9ce783-b2d7-48c0-84d1-b12a876a9446"
  },
  {
    "idTeam": 500514,
    "actorName": "MARCOS MARTIN MARTINEZ",
    "actorId": 8836454,
    "actorShirtNumber": "3",
    "idMove": 159,
    "move": "Personal, 2a falta",
    "min": 9,
    "sec": 19,
    "period": 4,
    "score": "34-81",
    "teamAction": false,
    "foulNumber": 2,
    "timestamp": "20251220201119",
    "licenseId": 1201434,
    "eventUuid": "82370123-f0b0-4480-8ecb-0cbc4c7a5eea"
  },
  {
    "idTeam": 500514,
    "actorName": "EMILIO IZQUIERDO REINA",
    "actorId": 8836461,
    "actorShirtNumber": "25",
    "idMove": 93,
    "move": "Cistella de 2",
    "min": 9,
    "sec": 0,
    "period": 4,
    "score": "36-81",
    "teamAction": false,
    "timestamp": "20251220201157",
    "licenseId": 1190250,
    "eventUuid": "84ff309d-4073-4044-9b8e-fd826be13024"
  },
  {
    "idTeam": 500515,
    "actorName": "LEONARDO ANTONIO ROJAS NÚÑEZ",
    "actorId": 8836328,
    "actorShirtNumber": "4",
    "idMove": 93,
    "move": "Cistella de 2",
    "min": 8,
    "sec": 7,
    "period": 4,
    "score": "36-83",
    "teamAction": false,
    "timestamp": "20251220201250",
    "licenseId": 1195274,
    "eventUuid": "6625d071-1aaa-4578-b934-9746b26d0f87"
  },
  {
    "idTeam": 500514,
    "actorName": "EMILIO IZQUIERDO REINA",
    "actorId": 8836461,
    "actorShirtNumber": "25",
    "idMove": 93,
    "move": "Cistella de 2",
    "min": 7,
    "sec": 54,
    "period": 4,
    "score": "38-83",
    "teamAction": false,
    "timestamp": "20251220201303",
    "licenseId": 1190250,
    "eventUuid": "fb2e3118-dc41-472f-a8db-7c832f87214e"
  },
  {
    "idTeam": 500514,
    "actorName": "MARCOS MARTIN MARTINEZ",
    "actorId": 8836454,
    "actorShirtNumber": "3",
    "idMove": 161,
    "move": "Personal 2 tirs lliures, 3a falta",
    "min": 7,
    "sec": 24,
    "period": 4,
    "score": "38-83",
    "teamAction": false,
    "foulNumber": 3,
    "timestamp": "20251220201335",
    "licenseId": 1201434,
    "eventUuid": "6cce8488-d23a-43c1-9ec7-e8024aa38d22"
  },
  {
    "idTeam": 500514,
    "actorName": "MARCOS MARTIN MARTINEZ",
    "actorId": 8836454,
    "actorShirtNumber": "3",
    "idMove": 115,
    "move": "Surt del camp",
    "min": 7,
    "sec": 24,
    "period": 4,
    "score": "38-83",
    "teamAction": false,
    "timestamp": "20251220201338",
    "licenseId": 1201434,
    "eventUuid": "9d53807d-b980-4549-8e9e-7f5160958a54"
  },
  {
    "idTeam": 500514,
    "actorName": "GUILLEM BABIO DEL AGUILA",
    "actorId": 8836458,
    "actorShirtNumber": "11",
    "idMove": 115,
    "move": "Surt del camp",
    "min": 7,
    "sec": 24,
    "period": 4,
    "score": "38-83",
    "teamAction": false,
    "timestamp": "20251220201338",
    "licenseId": 1190242,
    "eventUuid": "7dd27483-84a9-46bd-97df-264debb6f2b8"
  },
  {
    "idTeam": 500514,
    "actorName": "YOUSSEF EL JAANIN ZOUADI",
    "actorId": 8836463,
    "actorShirtNumber": "40",
    "idMove": 115,
    "move": "Surt del camp",
    "min": 7,
    "sec": 24,
    "period": 4,
    "score": "38-83",
    "teamAction": false,
    "timestamp": "20251220201338",
    "licenseId": 1203013,
    "eventUuid": "3a6975f1-580c-4b64-bad5-3e569352c54d"
  },
  {
    "idTeam": 500514,
    "actorName": "MARC GAVILAN CEREZO",
    "actorId": 8836455,
    "actorShirtNumber": "5",
    "idMove": 112,
    "move": "Entra al camp",
    "min": 7,
    "sec": 24,
    "period": 4,
    "score": "38-83",
    "teamAction": false,
    "timestamp": "20251220201338",
    "licenseId": 1196508,
    "eventUuid": "48366bc8-3351-4892-a5f0-29a21bc50d29"
  },
  {
    "idTeam": 500514,
    "actorName": "DAVID BENAIGUES OMOREGIE",
    "actorId": 8836460,
    "actorShirtNumber": "14",
    "idMove": 112,
    "move": "Entra al camp",
    "min": 7,
    "sec": 24,
    "period": 4,
    "score": "38-83",
    "teamAction": false,
    "timestamp": "20251220201338",
    "licenseId": 1186712,
    "eventUuid": "bdb3febb-0c2e-4903-b5eb-251ea7b21467"
  },
  {
    "idTeam": 500514,
    "actorName": "PAU ALVAREZ BABIO",
    "actorId": 8836456,
    "actorShirtNumber": "7",
    "idMove": 112,
    "move": "Entra al camp",
    "min": 7,
    "sec": 24,
    "period": 4,
    "score": "38-83",
    "teamAction": false,
    "timestamp": "20251220201338",
    "licenseId": 1205039,
    "eventUuid": "346110c0-9b90-4264-8a80-8fae67dd8ebc"
  },
  {
    "idTeam": 500515,
    "actorName": "FACUNDO LANFRANCONI GALLEGOS",
    "actorId": 8836332,
    "actorShirtNumber": "15",
    "idMove": 115,
    "move": "Surt del camp",
    "min": 7,
    "sec": 24,
    "period": 4,
    "score": "38-83",
    "teamAction": false,
    "timestamp": "20251220201338",
    "licenseId": 1187410,
    "eventUuid": "47dee30f-beae-430a-8cbf-84e0b50a0222"
  },
  {
    "idTeam": 500515,
    "actorName": "LEONARDO ANTONIO ROJAS NÚÑEZ",
    "actorId": 8836328,
    "actorShirtNumber": "4",
    "idMove": 115,
    "move": "Surt del camp",
    "min": 7,
    "sec": 24,
    "period": 4,
    "score": "38-83",
    "teamAction": false,
    "timestamp": "20251220201338",
    "licenseId": 1195274,
    "eventUuid": "a61e40d0-3445-470e-b860-8180f94d578c"
  },
  {
    "idTeam": 500515,
    "actorName": "GERARD FERRER GONZÁLEZ",
    "actorId": 8836331,
    "actorShirtNumber": "13",
    "idMove": 112,
    "move": "Entra al camp",
    "min": 7,
    "sec": 24,
    "period": 4,
    "score": "38-83",
    "teamAction": false,
    "timestamp": "20251220201338",
    "licenseId": 1184909,
    "eventUuid": "077f9647-4179-4f4e-b27f-992a1b4e6b9c"
  },
  {
    "idTeam": 500515,
    "actorName": "HÉCTOR CABEZAS AISA",
    "actorId": 8836329,
    "actorShirtNumber": "7",
    "idMove": 112,
    "move": "Entra al camp",
    "min": 7,
    "sec": 24,
    "period": 4,
    "score": "38-83",
    "teamAction": false,
    "timestamp": "20251220201338",
    "licenseId": 1184907,
    "eventUuid": "53249493-ddff-4050-90e7-2238f93dea68"
  },
  {
    "idTeam": 500515,
    "actorName": "LUCAS ROSSO RAMOS",
    "actorId": 8836335,
    "actorShirtNumber": "54",
    "idMove": 96,
    "move": "Intent fallat de 1",
    "min": 7,
    "sec": 24,
    "period": 4,
    "score": "38-83",
    "teamAction": false,
    "timestamp": "20251220201419",
    "licenseId": 1209335,
    "eventUuid": "21b92fe7-9967-4a15-8edc-115da71e6ebc"
  },
  {
    "idTeam": 500515,
    "actorName": "LUCAS ROSSO RAMOS",
    "actorId": 8836335,
    "actorShirtNumber": "54",
    "idMove": 96,
    "move": "Intent fallat de 1",
    "min": 7,
    "sec": 24,
    "period": 4,
    "score": "38-83",
    "teamAction": false,
    "timestamp": "20251220201424",
    "licenseId": 1209335,
    "eventUuid": "b8eb0ef9-5f4a-40e4-a0d4-896b7dd5fc54"
  },
  {
    "idTeam": 500514,
    "actorName": "EMILIO IZQUIERDO REINA",
    "actorId": 8836461,
    "actorShirtNumber": "25",
    "idMove": 93,
    "move": "Cistella de 2",
    "min": 7,
    "sec": 15,
    "period": 4,
    "score": "40-83",
    "teamAction": false,
    "timestamp": "20251220201435",
    "licenseId": 1190250,
    "eventUuid": "ceff95c6-1f80-426f-9ec9-18b343c0fd82"
  },
  {
    "idTeam": 500514,
    "actorName": "PAU ALVAREZ BABIO",
    "actorId": 8836456,
    "actorShirtNumber": "7",
    "idMove": 159,
    "move": "Personal, 1a falta",
    "min": 6,
    "sec": 58,
    "period": 4,
    "score": "40-83",
    "teamAction": false,
    "foulNumber": 1,
    "timestamp": "20251220201456",
    "licenseId": 1205039,
    "eventUuid": "3e628f17-a6e6-49c8-8d3c-f28c3505706c"
  },
  {
    "idTeam": 500515,
    "actorName": "HÉCTOR CABEZAS AISA",
    "actorId": 8836329,
    "actorShirtNumber": "7",
    "idMove": 93,
    "move": "Cistella de 2",
    "min": 6,
    "sec": 37,
    "period": 4,
    "score": "40-85",
    "teamAction": false,
    "timestamp": "20251220201532",
    "licenseId": 1184907,
    "eventUuid": "ecd76a65-ac77-43df-9696-a82f26c4dafd"
  },
  {
    "idTeam": 500514,
    "actorName": "WEN ZE DONG CHEN",
    "actorId": 8836459,
    "actorShirtNumber": "13",
    "idMove": 159,
    "move": "Personal, 3a falta",
    "min": 5,
    "sec": 57,
    "period": 4,
    "score": "40-85",
    "teamAction": false,
    "foulNumber": 3,
    "timestamp": "20251220201617",
    "licenseId": 1186707,
    "eventUuid": "4ed6ff3f-4dd6-4655-97b1-47a1358e7864"
  },
  {
    "idTeam": 500514,
    "actorName": "WEN ZE DONG CHEN",
    "actorId": 8836459,
    "actorShirtNumber": "13",
    "idMove": 161,
    "move": "Personal 2 tirs lliures, 4a falta",
    "min": 5,
    "sec": 54,
    "period": 4,
    "score": "40-85",
    "teamAction": false,
    "foulNumber": 4,
    "timestamp": "20251220201709",
    "licenseId": 1186707,
    "eventUuid": "21686f43-95a9-4f8a-8da0-f8a356818dd5"
  },
  {
    "idTeam": 500515,
    "actorName": "IKER CAPELL DE LA FUENTE",
    "actorId": 8836334,
    "actorShirtNumber": "19",
    "idMove": 92,
    "move": "Cistella de 1",
    "min": 5,
    "sec": 54,
    "period": 4,
    "score": "40-86",
    "teamAction": false,
    "timestamp": "20251220201727",
    "licenseId": 1184911,
    "eventUuid": "b0d7696a-74e5-4a7f-94f2-be5b0c80eb8a"
  },
  {
    "idTeam": 500515,
    "actorName": "IKER CAPELL DE LA FUENTE",
    "actorId": 8836334,
    "actorShirtNumber": "19",
    "idMove": 92,
    "move": "Cistella de 1",
    "min": 5,
    "sec": 54,
    "period": 4,
    "score": "40-87",
    "teamAction": false,
    "timestamp": "20251220201741",
    "licenseId": 1184911,
    "eventUuid": "833695e8-a069-4b6d-9f4b-71decc979a07"
  },
  {
    "idTeam": 500514,
    "actorName": "MARC GAVILAN CEREZO",
    "actorId": 8836455,
    "actorShirtNumber": "5",
    "idMove": 93,
    "move": "Cistella de 2",
    "min": 5,
    "sec": 44,
    "period": 4,
    "score": "42-87",
    "teamAction": false,
    "timestamp": "20251220201753",
    "licenseId": 1196508,
    "eventUuid": "ecb63a1f-d84b-43b0-bbec-e9b234098eea"
  },
  {
    "idTeam": 500515,
    "actorName": "GERARD FERRER GONZÁLEZ",
    "actorId": 8836331,
    "actorShirtNumber": "13",
    "idMove": 93,
    "move": "Cistella de 2",
    "min": 5,
    "sec": 29,
    "period": 4,
    "score": "42-89",
    "teamAction": false,
    "timestamp": "20251220201808",
    "licenseId": 1184909,
    "eventUuid": "546de7ba-8a88-4d7f-809a-cdc627968db1"
  },
  {
    "idTeam": 500515,
    "actorName": "IKER CAPELL DE LA FUENTE",
    "actorId": 8836334,
    "actorShirtNumber": "19",
    "idMove": 115,
    "move": "Surt del camp",
    "min": 5,
    "sec": 11,
    "period": 4,
    "score": "42-89",
    "teamAction": false,
    "timestamp": "20251220201828",
    "licenseId": 1184911,
    "eventUuid": "7edaa1f6-b97d-4564-8a6c-77f8fb003993"
  },
  {
    "idTeam": 500515,
    "actorName": "FRANCESC ALBIOL SERRA",
    "actorId": 8836333,
    "actorShirtNumber": "16",
    "idMove": 112,
    "move": "Entra al camp",
    "min": 5,
    "sec": 11,
    "period": 4,
    "score": "42-89",
    "teamAction": false,
    "timestamp": "20251220201828",
    "licenseId": 1184910,
    "eventUuid": "40959736-4867-4274-9d48-b71a84c8b7f7"
  },
  {
    "idTeam": 500515,
    "actorName": "LUCAS ROSSO RAMOS",
    "actorId": 8836335,
    "actorShirtNumber": "54",
    "idMove": 93,
    "move": "Cistella de 2",
    "min": 4,
    "sec": 42,
    "period": 4,
    "score": "42-91",
    "teamAction": false,
    "timestamp": "20251220201910",
    "licenseId": 1209335,
    "eventUuid": "fcd7d472-5237-41f0-a4b9-8fc1a3fdd86e"
  },
  {
    "idTeam": 500514,
    "actorName": "EMILIO IZQUIERDO REINA",
    "actorId": 8836461,
    "actorShirtNumber": "25",
    "idMove": 93,
    "move": "Cistella de 2",
    "min": 4,
    "sec": 28,
    "period": 4,
    "score": "44-91",
    "teamAction": false,
    "timestamp": "20251220201924",
    "licenseId": 1190250,
    "eventUuid": "0d2c7ee1-b905-4699-8e48-8e74415c2e41"
  },
  {
    "idTeam": 500514,
    "actorName": "EMILIO IZQUIERDO REINA",
    "actorId": 8836461,
    "actorShirtNumber": "25",
    "idMove": 93,
    "move": "Cistella de 2",
    "min": 4,
    "sec": 9,
    "period": 4,
    "score": "46-91",
    "teamAction": false,
    "timestamp": "20251220201943",
    "licenseId": 1190250,
    "eventUuid": "4b2d1fe3-8e78-4584-922f-2b4f2f235628"
  },
  {
    "idTeam": 500515,
    "actorName": "HÉCTOR CABEZAS AISA",
    "actorId": 8836329,
    "actorShirtNumber": "7",
    "idMove": 109,
    "move": "Falta en atac, 3a falta",
    "min": 3,
    "sec": 55,
    "period": 4,
    "score": "46-91",
    "teamAction": false,
    "foulNumber": 3,
    "timestamp": "20251220202000",
    "licenseId": 1184907,
    "eventUuid": "428d21e3-e852-49cc-97dd-9ddf01a6b23c"
  },
  {
    "idTeam": 500515,
    "actorName": "HÉCTOR CABEZAS AISA",
    "actorId": 8836329,
    "actorShirtNumber": "7",
    "idMove": 106,
    "move": "Pèrdua",
    "min": 3,
    "sec": 55,
    "period": 4,
    "score": "46-91",
    "teamAction": false,
    "timestamp": "20251220202000",
    "licenseId": 1184907,
    "eventUuid": "d6f2c668-09fb-4370-a93f-2ca237185736"
  },
  {
    "idTeam": 500515,
    "actorName": "GERARD FERRER GONZÁLEZ",
    "actorId": 8836331,
    "actorShirtNumber": "13",
    "idMove": 115,
    "move": "Surt del camp",
    "min": 3,
    "sec": 55,
    "period": 4,
    "score": "46-91",
    "teamAction": false,
    "timestamp": "20251220202005",
    "licenseId": 1184909,
    "eventUuid": "c1234d4d-334d-473a-b533-e5de731c9a94"
  },
  {
    "idTeam": 500515,
    "actorName": "ASIER SERRATO MENDIOLA",
    "actorId": 8836330,
    "actorShirtNumber": "10",
    "idMove": 115,
    "move": "Surt del camp",
    "min": 3,
    "sec": 55,
    "period": 4,
    "score": "46-91",
    "teamAction": false,
    "timestamp": "20251220202005",
    "licenseId": 1184903,
    "eventUuid": "7d359a7b-8ab7-4aef-84d8-541099ae4332"
  },
  {
    "idTeam": 500515,
    "actorName": "LEONARDO ANTONIO ROJAS NÚÑEZ",
    "actorId": 8836328,
    "actorShirtNumber": "4",
    "idMove": 112,
    "move": "Entra al camp",
    "min": 3,
    "sec": 55,
    "period": 4,
    "score": "46-91",
    "teamAction": false,
    "timestamp": "20251220202005",
    "licenseId": 1195274,
    "eventUuid": "14b871fe-e2e7-4ffe-81c6-cc5c50b05946"
  },
  {
    "idTeam": 500515,
    "actorName": "LORIÉN REINÉS ASCASO",
    "actorId": 8836326,
    "actorShirtNumber": "0",
    "idMove": 112,
    "move": "Entra al camp",
    "min": 3,
    "sec": 55,
    "period": 4,
    "score": "46-91",
    "teamAction": false,
    "timestamp": "20251220202005",
    "licenseId": 1184905,
    "eventUuid": "8ed716be-2872-4bbb-ad96-5fe3cffca457"
  },
  {
    "idTeam": 500515,
    "actorName": "FRANCESC ALBIOL SERRA",
    "actorId": 8836333,
    "actorShirtNumber": "16",
    "idMove": 93,
    "move": "Cistella de 2",
    "min": 3,
    "sec": 27,
    "period": 4,
    "score": "46-93",
    "teamAction": false,
    "timestamp": "20251220202059",
    "licenseId": 1184910,
    "eventUuid": "3b588d38-d029-404c-b09f-6809d6d1b1f6"
  },
  {
    "idTeam": 500515,
    "actorName": "HÉCTOR CABEZAS AISA",
    "actorId": 8836329,
    "actorShirtNumber": "7",
    "idMove": 93,
    "move": "Cistella de 2",
    "min": 3,
    "sec": 0,
    "period": 4,
    "score": "46-95",
    "teamAction": false,
    "timestamp": "20251220202132",
    "licenseId": 1184907,
    "eventUuid": "9ba8cd41-149b-4fb6-a549-a51421f62393"
  },
  {
    "idTeam": 500514,
    "actorName": "DAVID BENAIGUES OMOREGIE",
    "actorId": 8836460,
    "actorShirtNumber": "14",
    "idMove": 115,
    "move": "Surt del camp",
    "min": 2,
    "sec": 38,
    "period": 4,
    "score": "46-95",
    "teamAction": false,
    "timestamp": "20251220202155",
    "licenseId": 1186712,
    "eventUuid": "47f8b26b-0333-4ab5-aed1-31fb793cbdf9"
  },
  {
    "idTeam": 500514,
    "actorName": "MARCOS MARTIN MARTINEZ",
    "actorId": 8836454,
    "actorShirtNumber": "3",
    "idMove": 112,
    "move": "Entra al camp",
    "min": 2,
    "sec": 38,
    "period": 4,
    "score": "46-95",
    "teamAction": false,
    "timestamp": "20251220202155",
    "licenseId": 1201434,
    "eventUuid": "f32bfeb6-84ef-4505-bb15-e0c125e8bd45"
  },
  {
    "idTeam": 500515,
    "actorName": "LORIÉN REINÉS ASCASO",
    "actorId": 8836326,
    "actorShirtNumber": "0",
    "idMove": 93,
    "move": "Cistella de 2",
    "min": 2,
    "sec": 23,
    "period": 4,
    "score": "46-97",
    "teamAction": false,
    "timestamp": "20251220202222",
    "licenseId": 1184905,
    "eventUuid": "dcea5632-817e-488e-a4db-92cbc40958ab"
  },
  {
    "idTeam": 500514,
    "actorName": "WEN ZE DONG CHEN",
    "actorId": 8836459,
    "actorShirtNumber": "13",
    "idMove": 115,
    "move": "Surt del camp",
    "min": 2,
    "sec": 10,
    "period": 4,
    "score": "46-97",
    "teamAction": false,
    "timestamp": "20251220202236",
    "licenseId": 1186707,
    "eventUuid": "6d99b9f1-6d2c-466d-87c1-9509a9eb38a0"
  },
  {
    "idTeam": 500514,
    "actorName": "GUILLEM BABIO DEL AGUILA",
    "actorId": 8836458,
    "actorShirtNumber": "11",
    "idMove": 112,
    "move": "Entra al camp",
    "min": 2,
    "sec": 10,
    "period": 4,
    "score": "46-97",
    "teamAction": false,
    "timestamp": "20251220202236",
    "licenseId": 1190242,
    "eventUuid": "72df7666-956f-4bb7-9ea5-1eca93d6a513"
  },
  {
    "idTeam": 500515,
    "actorName": "LUCAS ROSSO RAMOS",
    "actorId": 8836335,
    "actorShirtNumber": "54",
    "idMove": 115,
    "move": "Surt del camp",
    "min": 2,
    "sec": 10,
    "period": 4,
    "score": "46-97",
    "teamAction": false,
    "timestamp": "20251220202236",
    "licenseId": 1209335,
    "eventUuid": "3da2920b-9eb0-494e-88ba-07e9267e2bf5"
  },
  {
    "idTeam": 500515,
    "actorName": "FACUNDO LANFRANCONI GALLEGOS",
    "actorId": 8836332,
    "actorShirtNumber": "15",
    "idMove": 112,
    "move": "Entra al camp",
    "min": 2,
    "sec": 10,
    "period": 4,
    "score": "46-97",
    "teamAction": false,
    "timestamp": "20251220202236",
    "licenseId": 1187410,
    "eventUuid": "7f39ca46-a6f0-4eb6-9295-580ee12da812"
  },
  {
    "idTeam": 500515,
    "actorName": "FACUNDO LANFRANCONI GALLEGOS",
    "actorId": 8836332,
    "actorShirtNumber": "15",
    "idMove": 161,
    "move": "Personal 2 tirs lliures, 2a falta",
    "min": 1,
    "sec": 52,
    "period": 4,
    "score": "46-97",
    "teamAction": false,
    "foulNumber": 2,
    "timestamp": "20251220202308",
    "licenseId": 1187410,
    "eventUuid": "2fa71b13-882b-4cc4-9091-845c7196ea79"
  },
  {
    "idTeam": 500514,
    "actorName": "PAU ALVAREZ BABIO",
    "actorId": 8836456,
    "actorShirtNumber": "7",
    "idMove": 96,
    "move": "Intent fallat de 1",
    "min": 1,
    "sec": 52,
    "period": 4,
    "score": "46-97",
    "teamAction": false,
    "timestamp": "20251220202324",
    "licenseId": 1205039,
    "eventUuid": "d1691cb6-1f3a-41c0-a251-7a2d6db45616"
  },
  {
    "idTeam": 500514,
    "actorName": "PAU ALVAREZ BABIO",
    "actorId": 8836456,
    "actorShirtNumber": "7",
    "idMove": 92,
    "move": "Cistella de 1",
    "min": 1,
    "sec": 52,
    "period": 4,
    "score": "47-97",
    "teamAction": false,
    "timestamp": "20251220202335",
    "licenseId": 1205039,
    "eventUuid": "f03a7d92-1ed7-4cf8-b3a3-66dd91810c25"
  },
  {
    "idTeam": 500515,
    "actorName": "FRANCESC ALBIOL SERRA",
    "actorId": 8836333,
    "actorShirtNumber": "16",
    "idMove": 159,
    "move": "Personal, 5a falta",
    "min": 1,
    "sec": 32,
    "period": 4,
    "score": "47-97",
    "teamAction": false,
    "foulNumber": 5,
    "timestamp": "20251220202408",
    "licenseId": 1184910,
    "eventUuid": "366edb2a-968b-4859-9089-5a4fcf79ac4f"
  },
  {
    "idTeam": 500515,
    "actorName": "FRANCESC ALBIOL SERRA",
    "actorId": 8836333,
    "actorShirtNumber": "16",
    "idMove": 115,
    "move": "Surt del camp",
    "min": 1,
    "sec": 32,
    "period": 4,
    "score": "47-97",
    "teamAction": false,
    "timestamp": "20251220202413",
    "licenseId": 1184910,
    "eventUuid": "bc442113-c092-4c5c-887d-a191299e5d76"
  },
  {
    "idTeam": 500515,
    "actorName": "IKER CAPELL DE LA FUENTE",
    "actorId": 8836334,
    "actorShirtNumber": "19",
    "idMove": 112,
    "move": "Entra al camp",
    "min": 1,
    "sec": 32,
    "period": 4,
    "score": "47-97",
    "teamAction": false,
    "timestamp": "20251220202413",
    "licenseId": 1184911,
    "eventUuid": "39e11a07-089e-48d0-bab2-07f4efb00d54"
  },
  {
    "idTeam": 500514,
    "actorName": "EMILIO IZQUIERDO REINA",
    "actorId": 8836461,
    "actorShirtNumber": "25",
    "idMove": 93,
    "move": "Cistella de 2",
    "min": 1,
    "sec": 28,
    "period": 4,
    "score": "49-97",
    "teamAction": false,
    "timestamp": "20251220202425",
    "licenseId": 1190250,
    "eventUuid": "b64ed4d3-384f-4dae-8750-beea710e6f86"
  },
  {
    "idTeam": 500515,
    "actorName": "LORIÉN REINÉS ASCASO",
    "actorId": 8836326,
    "actorShirtNumber": "0",
    "idMove": 161,
    "move": "Personal 2 tirs lliures, 2a falta",
    "min": 0,
    "sec": 10,
    "period": 4,
    "score": "49-97",
    "teamAction": false,
    "foulNumber": 2,
    "timestamp": "20251220202616",
    "licenseId": 1184905,
    "eventUuid": "e840d3d4-bf7d-46f6-ac43-12cbbb12ed00"
  },
  {
    "idTeam": 500514,
    "actorName": "GUILLEM BABIO DEL AGUILA",
    "actorId": 8836458,
    "actorShirtNumber": "11",
    "idMove": 92,
    "move": "Cistella de 1",
    "min": 0,
    "sec": 10,
    "period": 4,
    "score": "50-97",
    "teamAction": false,
    "timestamp": "20251220202635",
    "licenseId": 1190242,
    "eventUuid": "a0b4f625-f510-49f0-93d6-cf061a7dcf96"
  },
  {
    "idTeam": 500514,
    "actorName": "GUILLEM BABIO DEL AGUILA",
    "actorId": 8836458,
    "actorShirtNumber": "11",
    "idMove": 96,
    "move": "Intent fallat de 1",
    "min": 0,
    "sec": 10,
    "period": 4,
    "score": "50-97",
    "teamAction": false,
    "timestamp": "20251220202648",
    "licenseId": 1190242,
    "eventUuid": "a7d761da-2d49-44db-937b-8d66bfc3f7cb"
  },
  {
    "idTeam": 0,
    "actorName": "",
    "actorId": 0,
    "actorShirtNumber": "",
    "idMove": 116,
    "move": "Final de període",
    "min": 0,
    "sec": 0,
    "period": 4,
    "score": "50-97",
    "teamAction": true,
    "timestamp": "20251220202834",
    "eventUuid": "aa5ab61c-d02e-4715-a3de-87711407db97"
  }
]